Workbook

Sheet 【国内】特殊&小众用户招募-数据源
A1: 特殊用户数据源
A2: 一级难度 | F2: 600 | G2: 已知成本 | H2: 二级难度 | M2: 750 | N2: 已知成本 | O2: 三级难度 | T2: 950 | V2: 四级难度 | AA2: 1000 | AC2: =AVERAGE(F2,M2,T2,AA2) -> 825 | AD2: 市场价：1100
A3: 样本数 | B3: P5 | C3: P3 | D3: OP | E3: 实习 | F3: =AVERAGE(F5:F14) -> 650 | H3: 样本数 | I3: P5 | J3: P3 | K3: OP | L3: 实习 | O3: 样本数 | P3: P5 | Q3: P3 | R3: OP | S3: 实习 | V3: 样本数 | W3: P5 | X3: P3 | Y3: OP | Z3: 实习
A4: 0 | B4: 0 | C4: =(G4*A4-B4*5900-D4*1200-E4*300)/3400 -> 0 | D4: ='【国内】常规用户招募-数据源(正职+OP混合执行）'!AC4*2 -> 0 | E4: 0 | G4: 650 | H4: 0 | I4: 0 | J4: =(N4*H4-I4*5900-K4*1200-L4*300)/3400 -> 0 | K4: ='【国内】常规用户招募-数据源(正职+OP混合执行）'!AO4*2.2 -> 0 | L4: 0 | N4: 750 | O4: 0 | P4: 0 | Q4: =(U4*O4-P4*5900-R4*1200-S4*300)/3400 -> 0 | R4: ='【国内】常规用户招募-数据源(正职+OP混合执行）'!BA4*2.3 -> 0 | S4: 0 | T4: =(P4*7200+R4*3200+S4*300+(800+300)*O4)/O4 -> #DIV/0! | U4: 950 | V4: 0 | W4: 0 | X4: =(AB4*V4-W4*5900-Y4*1200-Z4*300)/3400 -> 0 | Y4: =R4*1.2 -> 0 | Z4: 0 | AA4: =(W4*7200+Y4*3200+Z4*300+(800+300)*V4)/V4 -> #DIV/0! | AB4: 1000
A5: 1 | B5: 0 | C5: =(G5*A5-B5*5900-D5*1200-E5*300)/3400 -> 0.12529412 | D5: ='【国内】常规用户招募-数据源(正职+OP混合执行）'!AC5*2 -> 0.18666667 | E5: 0 | F5: =(B5*5900+C5*3400+D5*1200+E5*300)/A5 -> 650 | G5: 650 | H5: 1 | I5: 0 | J5: =(N5*H5-I5*5900-K5*1200-L5*300)/3400 -> 0.066475294 | K5: ='【国内】常规用户招募-数据源(正职+OP混合执行）'!AO5*2.2 -> 0.26165333 | L5: 0.7 | M5: =(I5*5900+J5*3400+K5*1200+L5*300)/H5 -> 750 | N5: 750 | O5: 1 | P5: 0 | Q5: =(U5*O5-P5*5900-R5*1200-S5*300)/3400 -> 0.040176471 | R5: ='【国内】常规用户招募-数据源(正职+OP混合执行）'!BA5*2.3 -> 0.30283333 | S5: 1.5 | T5: =(P5*5900+Q5*3400+R5*1200+S5*300)/O5 -> 950 | U5: 950 | V5: 1 | W5: 0 | X5: =(AB5*V5-W5*5900-Y5*1200-Z5*300)/3400 -> 0.046331765 | Y5: =R5*1.08 -> 0.32706 | Z5: 1.5 | AA5: =(W5*5900+X5*3400+Y5*1200+Z5*300)/V5 -> 1000 | AB5: 1000
A6: 2 | B6: 0 | C6: =(G6*A6-B6*5900-D6*1200-E6*300)/3400 -> 0.15294118 | D6: 0.5 | E6: 0.6 | F6: =(B6*5900+C6*3400+D6*1200+E6*300)/A6 -> 650 | G6: 650 | H6: 2 | I6: 0 | J6: =(N6*H6-I6*5900-K6*1200-L6*300)/3400 -> 0.065025882 | K6: ='【国内】常规用户招募-数据源(正职+OP混合执行）'!AO6*2.2 -> 0.81576 | L6: 1 | M6: =(I6*5900+J6*3400+K6*1200+L6*300)/H6 -> 750 | N6: 750 | O6: 2 | P6: 0 | Q6: =(U6*O6-P6*5900-R6*1200-S6*300)/3400 -> 0.065147059 | R6: ='【国内】常规用户招募-数据源(正职+OP混合执行）'!BA6*2.3 -> 0.94875 | S6: 1.8 | T6: =(P6*5900+Q6*3400+R6*1200+S6*300)/O6 -> 950 | U6: 950 | V6: 2 | W6: 0 | X6: =(AB6*V6-W6*5900-Y6*1200-Z6*300)/3400 -> 0.067770588 | Y6: =R6*1.08 -> 1.02465 | Z6: 1.8 | AA6: =(W6*5900+X6*3400+Y6*1200+Z6*300)/V6 -> 1000 | AB6: 1000
A7: 3 | B7: 0 | C7: =(G7*A7-B7*5900-D7*1200-E7*300)/3400 -> 0.26470588 | D7: 0.7 | E7: 0.7 | F7: =(B7*5900+C7*3400+D7*1200+E7*300)/A7 -> 650 | G7: 650 | H7: 3 | I7: 0 | J7: =(N7*H7-I7*5900-K7*1200-L7*300)/3400 -> 0.22058824 | K7: 1 | L7: 1 | M7: =(I7*5900+J7*3400+K7*1200+L7*300)/H7 -> 750 | N7: 750 | O7: 3 | P7: 0 | Q7: =(U7*O7-P7*5900-R7*1200-S7*300)/3400 -> 0.20035294 | R7: ='【国内】常规用户招募-数据源(正职+OP混合执行）'!BA7*2.3 -> 1.2573333 | S7: 2.2 | T7: =(P7*5900+Q7*3400+R7*1200+S7*300)/O7 -> 950 | U7: 950 | V7: 3 | W7: 0 | X7: =(AB7*V7-W7*5900-Y7*1200-Z7*300)/3400 -> 0.20896941 | Y7: =R7*1.08 -> 1.35792 | Z7: 2.2 | AA7: =(W7*5900+X7*3400+Y7*1200+Z7*300)/V7 -> 1000 | AB7: 1000
A8: 4 | B8: 0 | C8: =(G8*A8-B8*5900-D8*1200-E8*300)/3400 -> 0.24588235 | D8: ='【国内】常规用户招募-数据源(正职+OP混合执行）'!AC8*2 -> 1.27 | E8: 0.8 | F8: =(B8*5900+C8*3400+D8*1200+E8*300)/A8 -> 650 | G8: 650 | H8: 4 | I8: =P8/2 -> 0.05 | J8: =(N8*H8-I8*5900-K8*1200-L8*300)/3400 -> 0.13911765 | K8: 1.5 | L8: =S8*0.6 -> 1.44 | M8: =(I8*5900+J8*3400+K8*1200+L8*300)/H8 -> 750 | N8: 750 | O8: 4 | P8: 0.1 | Q8: =(U8*O8-P8*5900-R8*1200-S8*300)/3400 -> 0.097058824 | R8: 1.8 | S8: 2.4 | T8: =(P8*5900+Q8*3400+R8*1200+S8*300)/O8 -> 950 | U8: 950 | V8: 4 | W8: 0.1 | X8: =(AB8*V8-W8*5900-Y8*1200-Z8*300)/3400 -> 0.10505882 | Y8: =R8*1.08 -> 1.944 | Z8: 2.4 | AA8: =(W8*5900+X8*3400+Y8*1200+Z8*300)/V8 -> 1000 | AB8: 1000
A9: 5 | B9: 0 | C9: =(G9*A9-B9*5900-D9*1200-E9*300)/3400 -> 0.38235294 | D9: 1.4 | E9: 0.9 | F9: =(B9*5900+C9*3400+D9*1200+E9*300)/A9 -> 650 | G9: 650 | H9: 5 | I9: =P9/2 -> 0.05 | J9: =(N9*H9-I9*5900-K9*1200-L9*300)/3400 -> 0.31382353 | K9: 1.6 | L9: =S9*0.6 -> 1.56 | M9: =(I9*5900+J9*3400+K9*1200+L9*300)/H9 -> 750 | N9: 750 | O9: 5 | P9: 0.1 | Q9: =(U9*O9-P9*5900-R9*1200-S9*300)/3400 -> 0.32352941 | R9: 1.9 | S9: 2.6 | T9: =(P9*5900+Q9*3400+R9*1200+S9*300)/O9 -> 950 | U9: 950 | V9: 5 | W9: 0.1 | X9: =(AB9*V9-W9*5900-Y9*1200-Z9*300)/3400 -> 0.34341176 | Y9: =R9*1.08 -> 2.052 | Z9: 2.6 | AA9: =(W9*5900+X9*3400+Y9*1200+Z9*300)/V9 -> 1000 | AB9: 1000
A10: 6 | B10: 0 | C10: =(G10*A10-B10*5900-D10*1200-E10*300)/3400 -> 0.49411765 | D10: 1.6 | E10: 1 | F10: =(B10*5900+C10*3400+D10*1200+E10*300)/A10 -> 650 | G10: 650 | H10: 6 | I10: =P10/2 -> 0.1 | J10: =(N10*H10-I10*5900-K10*1200-L10*300)/3400 -> 0.40705882 | K10: 1.7 | L10: =S10*0.6 -> 1.62 | M10: =(I10*5900+J10*3400+K10*1200+L10*300)/H10 -> 750 | N10: 750 | O10: 6 | P10: 0.2 | Q10: =(U10*O10-P10*5900-R10*1200-S10*300)/3400 -> 0.38529412 | R10: 2 | S10: 2.7 | T10: =(P10*5900+Q10*3400+R10*1200+S10*300)/O10 -> 950 | U10: 950 | V10: 6 | W10: 0.2 | X10: =(AB10*V10-W10*5900-Y10*1200-Z10*300)/3400 -> 0.41705882 | Y10: =R10*1.08 -> 2.16 | Z10: 2.7 | AA10: =(W10*5900+X10*3400+Y10*1200+Z10*300)/V10 -> 1000 | AB10: 1000
A11: 7 | B11: 0 | C11: =(G11*A11-B11*5900-D11*1200-E11*300)/3400 -> 0.53529412 | D11: 2 | E11: 1.1 | F11: =(B11*5900+C11*3400+D11*1200+E11*300)/A11 -> 650 | G11: 650 | H11: 7 | I11: =P11/2 -> 0.1 | J11: =(N11*H11-I11*5900-K11*1200-L11*300)/3400 -> 0.50588235 | K11: 2 | L11: =S11*0.6 -> 1.8 | M11: =(I11*5900+J11*3400+K11*1200+L11*300)/H11 -> 750 | N11: 750 | O11: 7 | P11: 0.2 | Q11: =(U11*O11-P11*5900-R11*1200-S11*300)/3400 -> 0.56764706 | R11: 2.2 | S11: 3 | T11: =(P11*5900+Q11*3400+R11*1200+S11*300)/O11 -> 950 | U11: 950 | V11: 7 | W11: 0.2 | X11: =(AB11*V11-W11*5900-Y11*1200-Z11*300)/3400 -> 0.60847059 | Y11: =R11*1.08 -> 2.376 | Z11: 3 | AA11: =(W11*5900+X11*3400+Y11*1200+Z11*300)/V11 -> 1000 | AB11: 1000
A12: 8 | B12: 0 | C12: =(G12*A12-B12*5900-D12*1200-E12*300)/3400 -> 0.62058824 | D12: 2.2 | E12: 1.5 | F12: =(B12*5900+C12*3400+D12*1200+E12*300)/A12 -> 650 | G12: 650 | H12: 8 | I12: =P12/2 -> 0.1 | J12: =(N12*H12-I12*5900-K12*1200-L12*300)/3400 -> 0.64529412 | K12: 2.2 | L12: =S12*0.6 -> 1.92 | M12: =(I12*5900+J12*3400+K12*1200+L12*300)/H12 -> 750 | N12: 750 | O12: 8 | P12: 0.2 | Q12: =(U12*O12-P12*5900-R12*1200-S12*300)/3400 -> 0.75882353 | R12: 2.4 | S12: 3.2 | T12: =(P12*5900+Q12*3400+R12*1200+S12*300)/O12 -> 950 | U12: 950 | V12: 8 | W12: 0.2 | X12: =(AB12*V12-W12*5900-Y12*1200-Z12*300)/3400 -> 0.80870588 | Y12: =R12*1.08 -> 2.592 | Z12: 3.2 | AA12: =(W12*5900+X12*3400+Y12*1200+Z12*300)/V12 -> 1000 | AB12: 1000
A13: 9 | B13: 0 | C13: =(G13*A13-B13*5900-D13*1200-E13*300)/3400 -> 0.66176471 | D13: 2.5 | E13: 2 | F13: =(B13*5900+C13*3400+D13*1200+E13*300)/A13 -> 650 | G13: 650 | H13: 9 | I13: =P13/2 -> 0.1 | J13: =(N13*H13-I13*5900-K13*1200-L13*300)/3400 -> 0.73882353 | K13: 2.5 | L13: =S13*0.6 -> 2.16 | M13: =(I13*5900+J13*3400+K13*1200+L13*300)/H13 -> 750 | N13: 750 | O13: 9 | P13: 0.2 | Q13: =(U13*O13-P13*5900-R13*1200-S13*300)/3400 -> 0.93235294 | R13: 2.6 | S13: 3.6 | T13: =(P13*5900+Q13*3400+R13*1200+S13*300)/O13 -> 950 | U13: 950 | V13: 9 | W13: 0.2 | X13: =(AB13*V13-W13*5900-Y13*1200-Z13*300)/3400 -> 0.99129412 | Y13: =R13*1.08 -> 2.808 | Z13: 3.6 | AA13: =(W13*5900+X13*3400+Y13*1200+Z13*300)/V13 -> 1000 | AB13: 1000
A14: 10 | B14: 0 | C14: =(G14*A14-B14*5900-D14*1200-E14*300)/3400 -> 0.72941176 | D14: 2.8 | E14: 2.2 | F14: =(B14*5900+C14*3400+D14*1200+E14*300)/A14 -> 650 | G14: 650 | H14: 10 | I14: =P14/2 -> 0.1 | J14: =(N14*H14-I14*5900-K14*1200-L14*300)/3400 -> 0.84294118 | K14: 2.8 | L14: =S14*0.6 -> 2.28 | M14: =(I14*5900+J14*3400+K14*1200+L14*300)/H14 -> 750 | N14: 750 | O14: 10 | P14: 0.2 | Q14: =(U14*O14-P14*5900-R14*1200-S14*300)/3400 -> 1.1235294 | R14: 2.8 | S14: 3.8 | T14: =(P14*5900+Q14*3400+R14*1200+S14*300)/O14 -> 950 | U14: 950 | V14: 10 | W14: 0.2 | X14: =(AB14*V14-W14*5900-Y14*1200-Z14*300)/3400 -> 1.1915294 | Y14: =R14*1.08 -> 3.024 | Z14: 3.8 | AA14: =(W14*5900+X14*3400+Y14*1200+Z14*300)/V14 -> 1000 | AB14: 1000
A15: 线下礼金 | H15: 线下礼金 | O15: 线下礼金 | V15: 线下礼金
A16: 2小时及以内玩家礼金 | E16: 800 | H16: 2小时及以内玩家礼金 | L16: 800 | O16: 2小时及以内玩家礼金 | S16: 1000 | V16: 2小时及以内玩家礼金 | Z16: 1200
A17: 每增加0.5小时，礼金+200 | H17: 每增加0.5小时，礼金+200 | O17: 每增加0.5小时，礼金+250 | V17: 每增加0.5小时，礼金+300
A18: 线上礼金 | H18: 线上礼金 | O18: 线上礼金 | V18: 线上礼金
A19: 2小时及以内玩家礼金 | E19: 300 | H19: 2小时及以内玩家礼金 | L19: 400 | O19: 2小时及以内玩家礼金 | S19: 500 | V19: 2小时及以内玩家礼金 | Z19: 600
A20: 每增加0.5小时，礼金+70 | H20: 每增加0.5小时，礼金+100 | O20: 每增加0.5小时，礼金+120 | V20: 每增加0.5小时，礼金+150
A22: 小众用户数据源
A23: 一级难度 | F23: =AVERAGE(F26:F35) -> 1200 | G23: 已知成本 | H23: 二级难度 | M23: =AVERAGE(M26:M35) -> 1400 | O23: 三级难度 | T23: =AVERAGE(T26:T35) -> 1500 | V23: 四级难度 | AA23: =AVERAGE(AA26:AA35) -> 1800 | AC23: =AVERAGE(F23,M23,T23,AA23) -> 1475
A24: 样本数 | B24: P5 | C24: P3 | D24: OP | E24: 实习 | H24: 样本数 | I24: P5 | J24: P3 | K24: OP | L24: 实习 | O24: 样本数 | P24: P5 | Q24: P3 | R24: OP | S24: 实习 | V24: 样本数 | W24: P5 | X24: P3 | Y24: OP | Z24: 实习
A25: 0 | B25: 0 | C25: =(G25*A25-B25*5900-E25*300)/3400 -> 0 | D25: 0 | E25: 0 | F25: =(B25*7200+D25*3200+E25*300+(450+400)*A25)/A25 -> #DIV/0! | G25: 1200 | H25: 0 | I25: =B25*1.15 -> 0 | J25: =(N25*H25-I25*5900-L25*300)/3400 -> 0 | K25: =D25*1.15 -> 0 | L25: 0 | M25: =(I25*7200+K25*3200+L25*300+(450+400)*H25)/H25 -> #DIV/0! | N25: 1400 | O25: 0 | P25: =I25*1.2 -> 0 | Q25: =(U25*O25-P25*5900-S25*300)/3400 -> 0 | R25: 0 | S25: 0 | T25: =(P25*7200+R25*3200+S25*300+(450+400)*O25)/O25 -> #DIV/0! | U25: 1500 | V25: 0 | W25: 0 | X25: =(AB25*V25-W25*5900-Z25*300)/3400 -> 0 | Y25: 0 | Z25: 0 | AA25: =(W25*7200+Y25*3200+Z25*300+(450+400)*V25)/V25 -> #DIV/0! | AB25: 1800
A26: 1 | B26: 0 | C26: =(G26*A26-B26*5900-E26*300)/3400 -> 0.35294118 | D26: 0 | E26: 0 | F26: =(B26*5900+C26*3400+E26*300)/A26 -> 1200 | G26: 1200 | H26: 1 | I26: =B26*1.15 -> 0 | J26: =(N26*H26-I26*5900-L26*300)/3400 -> 0.23529412 | K26: =D26*1.15 -> 0 | L26: 2 | M26: =(I26*5900+J26*3400+L26*300)/H26 -> 1400 | N26: 1400 | O26: 1 | P26: 0 | Q26: =(U26*O26-P26*5900-S26*300)/3400 -> 0.26470588 | R26: =K26*1.3 -> 0 | S26: 2 | T26: =(P26*5900+Q26*3400+S26*300)/O26 -> 1500 | U26: 1500 | V26: 1 | W26: 0 | X26: =(AB26*V26-W26*5900-Z26*300)/3400 -> 0.35294118 | Y26: =R26*1.2 -> 0 | Z26: 2 | AA26: =(W26*5900+X26*3400+Z26*300)/V26 -> 1800 | AB26: =U26*1.2 -> 1800
A27: 2 | B27: 0.1 | C27: =(G27*A27-B27*5900-E27*300)/3400 -> 0.35588235 | D27: 0 | E27: 2 | F27: =(B27*5900+C27*3400+E27*300)/A27 -> 1200 | G27: 1200 | H27: 2 | I27: =B27*1.15 -> 0.115 | J27: =(N27*H27-I27*5900-L27*300)/3400 -> 0.40338235 | K27: =D27*1.2 -> 0 | L27: 2.5 | M27: =(I27*5900+J27*3400+L27*300)/H27 -> 1400 | N27: 1400 | O27: 2 | P27: 0.1 | Q27: =(U27*O27-P27*5900-S27*300)/3400 -> 0.48823529 | R27: =K27*1.3 -> 0 | S27: 2.5 | T27: =(P27*5900+Q27*3400+S27*300)/O27 -> 1500 | U27: 1500 | V27: 2 | W27: 0.1 | X27: =(AB27*V27-W27*5900-Z27*300)/3400 -> 0.66470588 | Y27: =R27*1.2 -> 0 | Z27: 2.5 | AA27: =(W27*5900+X27*3400+Z27*300)/V27 -> 1800 | AB27: =U27*1.2 -> 1800
A28: 3 | B28: 0.1 | C28: =(G28*A28-B28*5900-E28*300)/3400 -> 0.7 | D28: 0 | E28: 2.1 | F28: =(B28*5900+C28*3400+E28*300)/A28 -> 1200 | G28: 1200 | H28: 3 | I28: =B28*1.15 -> 0.115 | J28: =(N28*H28-I28*5900-L28*300)/3400 -> 0.81514706 | K28: =D28*1.2 -> 0 | L28: 2.5 | M28: =(I28*5900+J28*3400+L28*300)/H28 -> 1400 | N28: 1400 | O28: 3 | P28: =I28*1.5 -> 0.1725 | Q28: =(U28*O28-P28*5900-S28*300)/3400 -> 0.80360294 | R28: =K28*1.3 -> 0 | S28: 2.5 | T28: =(P28*5900+Q28*3400+S28*300)/O28 -> 1500 | U28: 1500 | V28: 3 | W28: 0.1725 | X28: =(AB28*V28-W28*5900-Z28*300)/3400 -> 1.0683088 | Y28: =R28*1.2 -> 0 | Z28: 2.5 | AA28: =(W28*5900+X28*3400+Z28*300)/V28 -> 1800 | AB28: =U28*1.2 -> 1800
A29: 4 | B29: 0.1 | C29: =(G29*A29-B29*5900-E29*300)/3400 -> 1.0441176 | D29: 0 | E29: 2.2 | F29: =(B29*5900+C29*3400+E29*300)/A29 -> 1200 | G29: 1200 | H29: 4 | I29: =B29*1.15 -> 0.115 | J29: =(N29*H29-I29*5900-L29*300)/3400 -> 1.2269118 | K29: =D29*1.2 -> 0 | L29: 2.5 | M29: =(I29*5900+J29*3400+L29*300)/H29 -> 1400 | N29: 1400 | O29: 4 | P29: =I29*1.5 -> 0.1725 | Q29: =(U29*O29-P29*5900-S29*300)/3400 -> 1.2447794 | R29: =K29*1.3 -> 0 | S29: 2.5 | T29: =(P29*5900+Q29*3400+S29*300)/O29 -> 1500 | U29: 1500 | V29: 4 | W29: 0.1725 | X29: =(AB29*V29-W29*5900-Z29*300)/3400 -> 1.5977206 | Y29: =R29*1.2 -> 0 | Z29: 2.5 | AA29: =(W29*5900+X29*3400+Z29*300)/V29 -> 1800 | AB29: =U29*1.2 -> 1800
A30: 5 | B30: =0.1*1.5 -> 0.15 | C30: =(G30*A30-B30*5900-E30*300)/3400 -> 1.2838235 | D30: 0 | E30: 2.5 | F30: =(B30*5900+C30*3400+E30*300)/A30 -> 1200 | G30: 1200 | H30: 5 | I30: =B30*1.15 -> 0.1725 | J30: =(N30*H30-I30*5900-L30*300)/3400 -> 1.4947794 | K30: =D30*1.2 -> 0 | L30: 3 | M30: =(I30*5900+J30*3400+L30*300)/H30 -> 1400 | N30: 1400 | O30: 5 | P30: 0.2 | Q30: =(U30*O30-P30*5900-S30*300)/3400 -> 1.5941176 | R30: =K30*1.3 -> 0 | S30: 3 | T30: =(P30*5900+Q30*3400+S30*300)/O30 -> 1500 | U30: 1500 | V30: 5 | W30: 0.25875 | X30: =(AB30*V30-W30*5900-Z30*300)/3400 -> 1.9333456 | Y30: =R30*1.2 -> 0 | Z30: 3 | AA30: =(W30*5900+X30*3400+Z30*300)/V30 -> 1800 | AB30: =U30*1.2 -> 1800
A31: 6 | B31: =0.1*1.5 -> 0.15 | C31: =(G31*A31-B31*5900-E31*300)/3400 -> 1.6191176 | D31: 0 | E31: 2.7 | F31: =(B31*5900+C31*3400+E31*300)/A31 -> 1200 | G31: 1200 | H31: 6 | I31: =B31*1.15 -> 0.1725 | J31: =(N31*H31-I31*5900-L31*300)/3400 -> 1.9065441 | K31: =D31*1.2 -> 0 | L31: 3 | M31: =(I31*5900+J31*3400+L31*300)/H31 -> 1400 | N31: 1400 | O31: 6 | P31: 0.2 | Q31: =(U31*O31-P31*5900-S31*300)/3400 -> 2.0352941 | R31: =K31*1.3 -> 0 | S31: 3 | T31: =(P31*5900+Q31*3400+S31*300)/O31 -> 1500 | U31: 1500 | V31: 6 | W31: 0.25875 | X31: =(AB31*V31-W31*5900-Z31*300)/3400 -> 2.4627574 | Y31: =R31*1.2 -> 0 | Z31: 3 | AA31: =(W31*5900+X31*3400+Z31*300)/V31 -> 1800 | AB31: =U31*1.2 -> 1800
A32: 7 | B32: =0.1*1.5 -> 0.15 | C32: =(G32*A32-B32*5900-E32*300)/3400 -> 1.9455882 | D32: 0 | E32: 3 | F32: =(B32*5900+C32*3400+E32*300)/A32 -> 1200 | G32: 1200 | H32: 7 | I32: =B32*1.15 -> 0.1725 | J32: =(N32*H32-I32*5900-L32*300)/3400 -> 2.3183088 | K32: =D32*1.2 -> 0 | L32: 3 | M32: =(I32*5900+J32*3400+L32*300)/H32 -> 1400 | N32: 1400 | O32: 7 | P32: =I32*1.5 -> 0.25875 | Q32: =(U32*O32-P32*5900-S32*300)/3400 -> 2.3745221 | R32: =K32*1.3 -> 0 | S32: 3 | T32: =(P32*5900+Q32*3400+S32*300)/O32 -> 1500 | U32: 1500 | V32: 7 | W32: 0.25875 | X32: =(AB32*V32-W32*5900-Z32*300)/3400 -> 2.9921691 | Y32: =R32*1.2 -> 0 | Z32: 3 | AA32: =(W32*5900+X32*3400+Z32*300)/V32 -> 1800 | AB32: =U32*1.2 -> 1800
A33: 8 | B33: =0.1*1.5 -> 0.15 | C33: =(G33*A33-B33*5900-E33*300)/3400 -> 2.2897059 | D33: 0 | E33: 3.1 | F33: =(B33*5900+C33*3400+E33*300)/A33 -> 1200 | G33: 1200 | H33: 8 | I33: =B33*1.15 -> 0.1725 | J33: =(N33*H33-I33*5900-L33*300)/3400 -> 2.6859559 | K33: =D33*1.2 -> 0 | L33: 3.5 | M33: =(I33*5900+J33*3400+L33*300)/H33 -> 1400 | N33: 1400 | O33: 8 | P33: =I33*1.5 -> 0.25875 | Q33: =(U33*O33-P33*5900-S33*300)/3400 -> 2.7715809 | R33: =K33*1.3 -> 0 | S33: 3.5 | T33: =(P33*5900+Q33*3400+S33*300)/O33 -> 1500 | U33: 1500 | V33: 8 | W33: 0.25875 | X33: =(AB33*V33-W33*5900-Z33*300)/3400 -> 3.4774632 | Y33: =R33*1.2 -> 0 | Z33: 3.5 | AA33: =(W33*5900+X33*3400+Z33*300)/V33 -> 1800 | AB33: =U33*1.2 -> 1800
A34: 9 | B34: =0.1*1.5 -> 0.15 | C34: =(G34*A34-B34*5900-E34*300)/3400 -> 2.6073529 | D34: 0 | E34: 3.5 | F34: =(B34*5900+C34*3400+E34*300)/A34 -> 1200 | G34: 1200 | H34: 9 | I34: =B34*1.15 -> 0.1725 | J34: =(N34*H34-I34*5900-L34*300)/3400 -> 3.0536029 | K34: =D34*1.2 -> 0 | L34: 4 | M34: =(I34*5900+J34*3400+L34*300)/H34 -> 1400 | N34: 1400 | O34: 9 | P34: =I34*1.5 -> 0.25875 | Q34: =(U34*O34-P34*5900-S34*300)/3400 -> 3.1686397 | R34: =K34*1.3 -> 0 | S34: 4 | T34: =(P34*5900+Q34*3400+S34*300)/O34 -> 1500 | U34: 1500 | V34: 9 | W34: 0.25875 | X34: =(AB34*V34-W34*5900-Z34*300)/3400 -> 3.9627574 | Y34: =R34*1.2 -> 0 | Z34: 4 | AA34: =(W34*5900+X34*3400+Z34*300)/V34 -> 1800 | AB34: =U34*1.2 -> 1800
A35: 10 | B35: =0.1*1.5 -> 0.15 | C35: =(G35*A35-B35*5900-E35*300)/3400 -> 2.9602941 | D35: 0 | E35: 3.5 | F35: =(B35*5900+C35*3400+E35*300)/A35 -> 1200 | G35: 1200 | H35: 10 | I35: =B35*1.15 -> 0.1725 | J35: =(N35*H35-I35*5900-L35*300)/3400 -> 3.4653676 | K35: =D35*1.2 -> 0 | L35: 4 | M35: =(I35*5900+J35*3400+L35*300)/H35 -> 1400 | N35: 1400 | O35: 10 | P35: =I35*1.5 -> 0.25875 | Q35: =(U35*O35-P35*5900-S35*300)/3400 -> 3.6098162 | R35: =K35*1.3 -> 0 | S35: 4 | T35: =(P35*5900+Q35*3400+S35*300)/O35 -> 1500 | U35: 1500 | V35: 10 | W35: 0.5 | X35: =(AB35*V35-W35*5900-Z35*300)/3400 -> 4.0294118 | Y35: =R35*1.2 -> 0 | Z35: 4.5 | AA35: =(W35*5900+X35*3400+Z35*300)/V35 -> 1800 | AB35: =U35*1.2 -> 1800
A36: 线下礼金 | H36: 线下礼金 | O36: 线下礼金 | V36: 线下礼金
A37: 2小时及以内玩家礼金 | E37: 450 | H37: 2小时及以内玩家礼金 | L37: 450 | O37: 2小时及以内玩家礼金 | S37: 500 | V37: 2小时及以内玩家礼金 | Z37: 500
A38: 每增加0.5小时，礼金+115 | H38: 每增加0.5小时，礼金+115 | O38: 每增加0.5小时，礼金+115 | V38: 每增加0.5小时，礼金+115
A39: 线上礼金 | H39: 线上礼金 | O39: 线上礼金 | V39: 线上礼金
A40: 2小时及以内玩家礼金 | E40: 350 | H40: 2小时及以内玩家礼金 | L40: 350 | O40: 2小时及以内玩家礼金 | S40: 350 | V40: 2小时及以内玩家礼金 | Z40: 350
A41: 每增加0.5小时，礼金+90 | H41: 每增加0.5小时，礼金+90 | O41: 每增加0.5小时，礼金+90 | V41: 每增加0.5小时，礼金+90

Sheet 24&25年渠道人力对比
A1: 招募 2H以内：2H以上的系数=0.8 国内常规用户难度递增系数：1.2 线上：线下系数=0.8 常规用户-特殊用户难度递增系数=1.64
A2: 国内线下 | B2: 变量范围 | C2: 上半年 | D2: 下半年 | E2: P3单独执行 | F2: 25年预计定价 | G2: 25年实际定价 | H2: 市场价 | L2: 国内线上 | M2: 变量范围 | N2: 24年实际人力 | O2: P3单独执行 | P2: 24年实际人力 线上访谈 | Q2: 24年实际人力 线上测试 | R2: 25年实际定价 | S2: 市场价
A4: 常规一级 | L4: 常规一级
B5: 2H以内 | G5: =G6*0.8 -> 308.8 | H5: 725 | M5: 2H以内 | R5: =G5*0.8 -> 247.04
B6: 2H以上 | G6: 386 | H6: 725 | M6: 2H以上 | R6: =G6*0.8 -> 308.8
A7: 常规二级 | L7: 常规二级
B8: 2H以内 | C8: 263 | F8: 300 | G8: =G9*0.8 -> 349.6 | H8: 900 | M8: 2H以内 | N8: 283 | P8: 227 | Q8: 507 | R8: =G8*0.8 -> 279.68
B9: 2H以上 | C9: 394 | F9: 450 | G9: 437 | H9: 900 | M9: 2H以上 | R9: =G9*0.8 -> 349.6
A10: 常规三级 | L10: 常规三级
B11: 2H以内 | C11: 349 | D11: 280 | E11: 379 | F11: 400 | G11: =G12*0.8 -> 443.12 | H11: 1100 | M11: 2H以内 | N11: 274 | P11: 283 | Q11: 155 | R11: =G11*0.8 -> 354.496
B12: 2H以上 | C12: 400 | D12: 400 | E12: 467 | F12: 550 | G12: 553.9 | H12: 1100 | M12: 2H以上 | N12: 448 | P12: 178 | Q12: 519 | R12: =G12*0.8 -> 443.12
A13: 常规四级 | L13: 常规四级
B14: 2H以内 | C14: 500 | D14: 561 | E14: 846 | G14: =G15*0.8 -> 508 | H14: 1500 | M14: 2H以内 | N14: 268 | O14: 390 | P14: 269 | Q14: 256 | R14: =G14*0.8 -> 406.4
B15: 2H以上 | C15: 524 | D15: 455 | E15: 400 | F15: =F12*1.2 -> 660 | G15: 635 | H15: 1500 | M15: 2H以上 | N15: 217 | O15: 235 | Q15: 217 | R15: =G15*0.8 -> 508
A16: 常规五级 | L16: 常规五级
B17: 2H以内 | C17: 494 | G17: =G18*0.8 -> 544 | H17: 1500 | M17: 2H以内 | N17: 423 | P17: 423 | R17: =G17*0.8 -> 435.2
B18: 2H以上 | C18: 681 | E18: 566 | G18: 680 | H18: 1500 | M18: 2H以上 | N18: 212 | Q18: 212 | R18: =G18*0.8 -> 544
A19: 特殊-一级 | L19: 特殊-一级
B20: 2H以内 | G20: 650 | M20: 2H以内 | R20: =G20 -> 650
B21: 2H以上 | G21: 650 | M21: 2H以上 | R21: =G21 -> 650
A22: 特殊二级 | L22: 特殊二级
B23: 2H以内 | G23: =AVERAGE(F8:F9)*2 -> 750 | M23: 2H以内 | R23: =G23 -> 750
B24: 2H以上 | G24: 750 | M24: 2H以上 | R24: =G24 -> 750
A25: 特殊三级 | L25: 特殊三级
B26: 2H以内 | G26: 950 | M26: 2H以内 | N26: 1053 | R26: =G26 -> 950
B27: 2H以上 | C27: 2060 | G27: 950 | M27: 2H以上 | R27: =G27 -> 950
A28: 特殊-四级 | L28: 特殊-四级
B29: 2H以内 | C29: 1366 | D29: 1366 | G29: 1000 | M29: 2H以内 | N29: 1769 | R29: =G29 -> 1000
B30: 2H以上 | C30: 1150 | G30: 1000 | M30: 2H以上 | R30: =G30 -> 1000
A31: 小众-一级 | L31: 小众-一级
B32: 2H以内 | G32: 1200 | H32: 2000 | M32: 2H以内 | R32: =G32 -> 1200 | S32: 2000
B33: 2H以上 | G33: 1200 | H33: 2000 | M33: 2H以上 | R33: =G33 -> 1200 | S33: 2000
A34: 小众-二级 | L34: 小众-二级
B35: 2H以内 | G35: 1400 | H35: 2000 | M35: 2H以内 | R35: =G35 -> 1400 | S35: 2000
B36: 2H以上 | G36: 1400 | H36: 2000 | M36: 2H以上 | R36: =G36 -> 1400 | S36: 2000
A37: 小众-三级 | L37: 小众-三级
B38: 2H以内 | C38: 387 | G38: 1500 | H38: 2000 | M38: 2H以内 | N38: 2752 | R38: =G38 -> 1500 | S38: 2000
B39: 2H以上 | C39: 679 | G39: 1500 | H39: 2000 | M39: 2H以上 | R39: =G39 -> 1500 | S39: 2000
A40: 小众-四级 | L40: 小众-四级
B41: 2H以内 | G41: 1600 | H41: 2000 | M41: 2H以内 | R41: =G41 -> 1600 | S41: 2000
B42: 2H以上 | G42: 1600 | H42: 2000 | M42: 2H以上 | R42: =G42 -> 1600 | S42: 2000
A44: 海外线下 | B44: 变量范围 | C44: 24年实际人力 | F44: 25年预计定价 | G44: 25年实际定价 | H44: 市场价 | L44: 海外线上 | M44: 变量范围 | N44: 24年实际人力 | Q44: 25年预计定价 | R44: 25年实际定价 | S44: 市场价
A45: 海外常规-简单 | B45: 2H以内 | C45: 730 | G45: =G48*0.9 -> 1246.5 | H45: 2500 | L45: 海外常规-简单 | M45: 2H以内 | N45: 916 | R45: =G45 -> 1246.5 | S45: 2500
B46: 2H以上 | C46: 726 | G46: =G48*0.9 -> 1246.5 | H46: 2500 | M46: 2H以上 | R46: =G46 -> 1246.5 | S46: 2500
A48: 海外常规-中等 | B48: 2H以内 | C48: 1475 | F48: 1450 | G48: 1385 | H48: 2500 | L48: 海外常规-中等 | M48: 2H以内 | N48: 1500 | R48: =G48 -> 1385 | S48: 2500
B49: 2H以上 | C49: 900 | F49: 1450 | G49: 1385 | H49: 2500 | M49: 2H以上 | N49: 1145 | R49: =G49 -> 1385 | S49: 2500
A51: 海外常规-困难 | B51: 2H以内 | F51: 1600 | G51: =G48*1.1 -> 1523.5 | H51: 2500 | L51: 海外常规-困难 | M51: 2H以内 | R51: =R48*1.1 -> 1523.5 | S51: 2500
B52: 2H以上 | F52: 1600 | G52: =G49*1.1 -> 1523.5 | H52: 2500 | M52: 2H以上 | R52: =R49*1.1 -> 1523.5 | S52: 2500
A54: 海外常规-所有（除去供应商） | B54: 平均值 | C54: 1156
B55: 2H以内 | C55: 1292
B56: 2H以上 | C56: 885
A58: 问卷 1.海外平台单价上涨，总单价与24年持平的情况下，人力定价有所下浮 2.国内投放新增渠道系数，若只使用支付宝渠道投放，当投放份数小于500，则X=（800-投放份数）/1000，若投放分数大于500份，X=0.3；若只用单抖音投放，则系数=0.6
A59: 国内问卷 | B59: 变量范围 | C59: 2024年 | H59: 25年（KOL+玩家群渠道定价) | I59: 25年实际定价-单支付宝 | J59: 25年实际定价-单抖音 | K59: 2025年混合报价（混合渠道50%，支付宝渠道45%，抖音渠道5%） | L59: 外部市场价 | O59: 海外 | P59: 变量范围 | Q59: 24年实际人力 | R59: 市场价 | S59: 25年实际定价
C60: P3独立执行 | D60: OP独立执行 | E60: 支付宝渠道人力 | F60: 抖音渠道人力 | G60: 24年的实际投放成本
B61: 一级 | E61: 3 | F61: 0 | G61: 3 | H61: ='【国内】问卷调研-数据源（P3单独执行） '!BF3 -> 7.7739052 | I61: =H61*0.4 -> 3.1095621 | J61: =H61*0.6 -> 4.6643431 | K61: =(H61*0.5+I61*0.45+J61*0.05) -> 5.5194727 | L61: 31
B62: 二级 | C62: 17 | D62: 2.4 | F62: 0.9 | G62: 7.9 | H62: ='【国内】问卷调研-数据源（P3单独执行） '!BF26 -> 10.201085 | I62: =H62*0.4 -> 4.0804339 | J62: =H62*0.6 -> 6.1206509 | K62: =(H62*0.5+I62*0.45+J62*0.05) -> 7.2427702 | L62: 33 | P62: 泛用户 | Q62: 8 | R62: 30 | S62: 12
B63: 三级 | C63: 6.5 | D63: 2.9 | E63: 5 | F63: 1.8 | G63: 4.2 | H63: ='【国内】问卷调研-数据源（P3单独执行） '!BF49 -> 10.488315 | I63: =H63*0.4 -> 4.1953261 | J63: =H63*0.6 -> 6.2929891 | K63: =(H63*0.5+I63*0.45+J63*0.05) -> 7.4467038 | L63: 40 | P63: 定向用户 | Q63: 20 | R63: 45 | S63: 18
B64: 四级 | C64: 12 | D64: 2.67 | E64: 2 | G64: 7.3 | H64: ='【国内】问卷调研-数据源（P3单独执行） '!BF72 -> 11.779072 | I64: =H64*0.4 -> 4.7116288 | J64: =H64*0.6 -> 7.0674431 | K64: =(H64*0.5+I64*0.45+J64*0.05) -> 8.3631411 | L64: 48
B65: 五级 | D65: 4.9 | E65: 2 | G65: =AVERAGE(C65:D65) -> 4.9 | H65: ='【国内】问卷调研-数据源（P3单独执行） '!BF95 -> 12.452637 | I65: =H65*0.4 -> 4.9810548 | J65: =H65*0.6 -> 7.4715822 | K65: =(H65*0.5+I65*0.45+J65*0.05) -> 8.8413723 | L65: 52
B66: 六级 | C66: 6.2 | D66: 12.4 | G66: 8.3 | H66: ='【国内】问卷调研-数据源（P3单独执行） '!BF118 -> 14.370559 | I66: =H66*0.4 -> 5.7482235 | J66: =H66*0.6 -> 8.6223353 | K66: =(H66*0.5+I66*0.45+J66*0.05) -> 10.203097 | L66: 76
G67: 5 | K67: =AVERAGE(K61:K66) -> 7.9360928
A69: CAA投放 1.若CAA测试不包含报告输出，则人力-0.8~1.0 2.5张以下人力一致 3.24年数据默认包含报告输出（OP人力/基础5张）+24年实际人力
A70: CAA投放 | B70: 变量范围 | C70: 24年实际人力单价 | D70: 24年包含报告输出单价 | E70: 25年实际定价 | F70: 25年定价均价
B71: 中国 | C71: =256 -> 256 | D71: 496 | E71: ='【全球】CAA测试-数据源'!H4 -> 512.67647 | F71: =AVERAGE(E71:E74) -> 521.53126
B72: 日本 | C72: =248 -> 248 | D72: 488 | E72: ='【全球】CAA测试-数据源'!O13 -> 517.88235
B73: 美国 | C73: =361 -> 361 | D73: 601 | E73: ='【全球】CAA测试-数据源'!O4 -> 537.68386
B74: 港澳台 | C74: =120 -> 120 | D74: 360 | E74: ='【全球】CAA测试-数据源'!H13 -> 517.88235

Sheet 【国内】问卷调研-数据源（P3单独执行） 
B1: 人群难度 | C1: 一级难度 | J1: 人群难度 | L1: 一级难度 | R1: 人群难度 | T1: 一级难度 | Z1: 人群难度 | AB1: 一级难度 | AH1: 人群难度 | AJ1: 一级难度 | AP1: 人群难度 | AR1: 一级难度 | AX1: 人群难度 | AZ1: 一级难度
B2: 问卷难度 | C2: 20题以内 | J2: 问卷难度 | L2: 21~30题 | R2: 问卷难度 | T2: 31~40题 | Z2: 问卷难度 | AB2: 41~50题 | AH2: 问卷难度 | AJ2: 51~60 | AP2: 问卷难度 | AR2: 61~70 | AX2: 问卷难度 | AZ2: 71~80
B3: 单价 | D3: 2 | G3: =AVERAGE(G7:G22) -> 8.0302204 | J3: 单价 | L3: 3 | O3: =AVERAGE(O6:O22) -> 9.2972786 | R3: 单价 | T3: 4 | W3: =AVERAGE(W6:W22) -> 10.919056 | Z3: 单价 | AB3: 5 | AE3: =AVERAGE(AE7:AE22) -> 12.801738 | AH3: 单价 | AJ3: 6 | AM3: =AVERAGE(AM7:AM22) -> 14.462377 | AP3: 单价 | AR3: 7 | AU3: =AVERAGE(AU7:AU22) -> 16.123015 | AX3: 单价 | AZ3: 8 | BC3: =AVERAGE(BC7:BC22) -> 17.783653 | BE3: =AVERAGE(BC3,AU3,AM3,AE3,W3,O3,G3) -> 12.773905 | BF3: =BE3-AVERAGE(AZ3,AR3,AJ3,AB3,T3,L3,D3) -> 7.7739052
B4: 份数 | C4: P5 | D4: P4 | E4: P3 | F4: 实习生 | G4: 成本 | H4: 上限 | J4: 份数 | K4: P5 | L4: P4 | M4: P3 | N4: 实习生 | O4: 成本 | P4: 上限 | R4: 份数 | S4: P5 | T4: P4 | U4: P3 | V4: 实习生 | W4: 成本 | X4: 上限 | Z4: 份数 | AA4: P5 | AB4: P4 | AC4: P3 | AD4: 实习生 | AE4: 成本 | AF4: 上限 | AH4: 份数 | AI4: P5 | AJ4: P4 | AK4: P3 | AL4: 实习生 | AM4: 成本 | AP4: 份数 | AQ4: P5 | AR4: P4 | AS4: P3 | AT4: 实习生 | AX4: 份数 | AY4: P5 | AZ4: P4 | BA4: P3 | BB4: 实习生
B5: 0 | C5: =S5 -> 0 | D5: 0 | F5: 0 | G5: =(C5*5900+E5*3400+F5*300+B5*$D$3)/B5 -> #DIV/0! | H5: 18 | J5: 0 | K5: =C5 -> 0 | L5: 0 | M5: 0 | N5: 0 | O5: =(K5*5900+M5*3400+N5*300+J5*$L$3)/J5 -> #DIV/0! | P5: 18 | R5: 0 | S5: 0 | T5: 0 | U5: 0 | V5: 0 | W5: =(S5*5900+U5*3400+V5*300+R5*$T$3)/R5 -> #DIV/0! | X5: 18 | Z5: 0 | AA5: =S5 -> 0 | AB5: 0 | AC5: 0 | AD5: 0 | AE5: =(AA5*5900+AC5*3400+AD5*300+Z5*$AB$3)/Z5 -> #DIV/0! | AH5: 0 | AI5: =AA5 -> 0 | AJ5: 0 | AK5: 0 | AL5: 0 | AM5: =(AI5*5900+AK5*3400+AL5*300+AH5*$AJ$3)/AH5 -> #DIV/0! | AP5: 0 | AQ5: =AI5 -> 0 | AR5: 0 | AS5: 0 | AT5: 0 | AU5: =(AQ5*5900+AS5*3400+AT5*300+AP5*$AR$3)/AP5 -> #DIV/0! | AX5: 0 | AY5: =AQ5 -> 0 | AZ5: 0 | BA5: 0 | BB5: 0 | BC5: =(AY5*5900+BA5*3400+BB5*300+AX5*$AZ$3)/AX5 -> #DIV/0!
A6: 100份及以下 | B6: 1 | C6: 0 | D6: =D7 -> 0 | E6: 0 | F6: 0 | G6: =(C6*5900+E6*3400+F6*300+$D$3*B6)/B6 -> 2 | H6: 18 | J6: 1 | K6: 0 | L6: =L7 -> 0 | M6: 0 | N6: 0 | O6: =(K6*5900+M6*3400+N6*300+$L$3*J6)/J6 -> 3 | P6: 18 | R6: 1 | S6: =S7 -> 0 | T6: =T7 -> 0 | U6: 0 | V6: 0 | W6: =(S6*5900+U6*3400+V6*300+$T$3*R6)/R6 -> 4 | X6: 18 | Z6: 1 | AA6: =AA7 -> 0 | AB6: =AB7 -> 0 | AC6: =AC7 -> 0.5 | AD6: =AD7 -> 1.2 | AE6: =(AA6*5900+AC6*3400+AD6*300)/Z6 -> 2060 | AH6: 1 | AI6: =AI7 -> 0 | AJ6: =AJ7 -> 0 | AK6: =AK7 -> 0.6 | AL6: =AL7 -> 1.3 | AM6: =(AI6*5900+AK6*3400+AL6*300+$AJ$3*AH6)/AH6 -> 2436 | AP6: 1 | AQ6: =AQ7 -> 0 | AR6: =AR7 -> 0 | AS6: =AS7 -> 0.7 | AT6: =AT7 -> 1.4 | AU6: =(AQ6*5900+AS6*3400+AT6*300)/AP6 -> 2800 | AX6: 1 | AY6: =AY7 -> 0 | AZ6: =AZ7 -> 0 | BA6: =BA7 -> 0.8 | BB6: =BB7 -> 1.5 | BC6: =(AY6*5900+BA6*3400+BB6*300+$AZ$3*AX6)/AX6 -> 3178
A7: 101~200份 | B7: 101 | C7: =S7 -> 0 | D7: 0 | E7: =E30-0.1 -> 0.3 | F7: =N7-0.1 -> 0.9 | G7: =(C7*5900+E7*3400+F7*300+$D$3*B7)/B7 -> 14.772277 | H7: 18 | J7: 101 | K7: =C7 -> 0 | L7: 0 | M7: =E7+0.1 -> 0.4 | N7: 1 | O7: =(K7*5900+M7*3400+N7*300+$L$3*J7)/J7 -> 19.435644 | P7: 18 | R7: 101 | S7: 0 | T7: 0 | U7: =M7+0.1 -> 0.5 | V7: =N7+0.1 -> 1.1 | W7: =(S7*5900+U7*3400+V7*300+$T$3*R7)/R7 -> 24.09901 | X7: 18 | Z7: 101 | AA7: =S7 -> 0 | AB7: 0 | AC7: 0.5 | AD7: =V7+0.1 -> 1.2 | AE7: =(AA7*5900+AC7*3400+AD7*300+$AB$3*Z7)/Z7 -> 25.39604 | AH7: 101 | AI7: =AA7 -> 0 | AJ7: 0 | AK7: =AC7+0.1 -> 0.6 | AL7: =AD7+0.1 -> 1.3 | AM7: =(AI7*5900+AK7*3400+AL7*300+$AJ$3*AH7)/AH7 -> 30.059406 | AP7: 101 | AQ7: =AI7 -> 0 | AR7: 0 | AS7: =AK7+0.1 -> 0.7 | AT7: =AL7+0.1 -> 1.4 | AU7: =(AQ7*5900+AS7*3400+AT7*300+AP7*$AR$3)/AP7 -> 34.722772 | AX7: 101 | AY7: =AQ7 -> 0 | AZ7: 0 | BA7: =AS7+0.1 -> 0.8 | BB7: =AT7+0.1 -> 1.5 | BC7: =(AY7*5900+BA7*3400+BB7*300+$AZ$3*AX7)/AX7 -> 39.386139
A8: 201~300份 | B8: 201 | C8: =S8 -> 0 | D8: 0 | E8: 0.4 | F8: =N8-0.1 -> 0.9 | G8: =(C8*5900+E8*3400+F8*300+$D$3*B8)/B8 -> 10.109453 | H8: 18 | J8: 201 | K8: =C8 -> 0 | L8: 0 | M8: =E8+0.1 -> 0.5 | N8: 1 | O8: =(K8*5900+M8*3400+N8*300+$L$3*J8)/J8 -> 12.950249 | P8: 18 | R8: 201 | S8: 0 | T8: 0 | U8: =M8+0.1 -> 0.6 | V8: =N8+0.1 -> 1.1 | W8: =(S8*5900+U8*3400+V8*300+$T$3*R8)/R8 -> 15.791045 | X8: 18 | Z8: 201 | AA8: =S8 -> 0 | AB8: 0 | AC8: =U8+0.1 -> 0.7 | AD8: =V8+0.1 -> 1.2 | AE8: =(AA8*5900+AC8*3400+AD8*300+$AB$3*Z8)/Z8 -> 18.631841 | AH8: 201 | AI8: =AA8 -> 0 | AJ8: 0 | AK8: =AC8+0.1 -> 0.8 | AL8: =AD8+0.1 -> 1.3 | AM8: =(AI8*5900+AK8*3400+AL8*300+$AJ$3*AH8)/AH8 -> 21.472637 | AP8: 201 | AQ8: =AI8 -> 0 | AR8: 0 | AS8: =AK8+0.1 -> 0.9 | AT8: =AL8+0.1 -> 1.4 | AU8: =(AQ8*5900+AS8*3400+AT8*300+AP8*$AR$3)/AP8 -> 24.313433 | AX8: 201 | AY8: =AQ8 -> 0 | AZ8: 0 | BA8: =AS8+0.1 -> 1 | BB8: =AT8+0.1 -> 1.5 | BC8: =(AY8*5900+BA8*3400+BB8*300+$AZ$3*AX8)/AX8 -> 27.154229
A9: 301~500份 | B9: 301 | C9: =S9 -> 0 | D9: 0.2 | E9: 0.5 | F9: =N9-0.1 -> 0.9 | G9: =(C9*5900+E9*3400+F9*300+$D$3*B9)/B9 -> 8.5448505 | H9: 18 | J9: 301 | K9: =C9 -> 0 | L9: 0.2 | M9: =E9+0.1 -> 0.6 | N9: 1 | O9: =(K9*5900+M9*3400+N9*300+$L$3*J9)/J9 -> 10.774086 | P9: 18 | R9: 301 | S9: 0 | T9: 0.2 | U9: =M9+0.1 -> 0.7 | V9: =N9+0.1 -> 1.1 | W9: =(S9*5900+U9*3400+V9*300+$T$3*R9)/R9 -> 13.003322 | X9: 18 | Z9: 301 | AA9: =S9 -> 0 | AB9: 0.2 | AC9: =U9+0.1 -> 0.8 | AD9: =V9+0.1 -> 1.2 | AE9: =(AA9*5900+AC9*3400+AD9*300+$AB$3*Z9)/Z9 -> 15.232558 | AH9: 301 | AI9: =AA9 -> 0 | AJ9: 0.2 | AK9: =AC9+0.1 -> 0.9 | AL9: =AD9+0.1 -> 1.3 | AM9: =(AI9*5900+AK9*3400+AL9*300+$AJ$3*AH9)/AH9 -> 17.461794 | AP9: 301 | AQ9: =AI9 -> 0 | AR9: 0.2 | AS9: =AK9+0.1 -> 1 | AT9: =AL9+0.1 -> 1.4 | AU9: =(AQ9*5900+AS9*3400+AT9*300+AP9*$AR$3)/AP9 -> 19.69103 | AX9: 301 | AY9: =AQ9 -> 0 | AZ9: 0.2 | BA9: =AS9+0.1 -> 1.1 | BB9: =AT9+0.1 -> 1.5 | BC9: =(AY9*5900+BA9*3400+BB9*300+$AZ$3*AX9)/AX9 -> 21.920266
A10: 501~700份 | B10: 501 | C10: =S10 -> 0 | D10: 0.2 | E10: 0.9 | F10: =N10-0.1 -> 0.9 | G10: =(C10*5900+E10*3400+F10*300+$D$3*B10)/B10 -> 8.6467066 | H10: 18 | J10: 501 | K10: =C10 -> 0 | L10: 0.2 | M10: =E10+0.1 -> 1 | N10: 1 | O10: =(K10*5900+M10*3400+N10*300+$L$3*J10)/J10 -> 10.38523 | P10: 18 | R10: 501 | S10: 0 | T10: 0.2 | U10: =M10+0.1 -> 1.1 | V10: =N10+0.1 -> 1.1 | W10: =(S10*5900+U10*3400+V10*300+$T$3*R10)/R10 -> 12.123752 | X10: 18 | Z10: 501 | AA10: =S10 -> 0 | AB10: 0.2 | AC10: =U10+0.1 -> 1.2 | AD10: =V10+0.1 -> 1.2 | AE10: =(AA10*5900+AC10*3400+AD10*300+$AB$3*Z10)/Z10 -> 13.862275 | AH10: 501 | AI10: =AA10 -> 0 | AJ10: 0.2 | AK10: =AC10+0.1 -> 1.3 | AL10: =AD10+0.1 -> 1.3 | AM10: =(AI10*5900+AK10*3400+AL10*300+$AJ$3*AH10)/AH10 -> 15.600798 | AP10: 501 | AQ10: =AI10 -> 0 | AR10: 0.2 | AS10: =AK10+0.1 -> 1.4 | AT10: =AL10+0.1 -> 1.4 | AU10: =(AQ10*5900+AS10*3400+AT10*300+AP10*$AR$3)/AP10 -> 17.339321 | AX10: 501 | AY10: =AQ10 -> 0 | AZ10: 0.2 | BA10: =AS10+0.1 -> 1.5 | BB10: =AT10+0.1 -> 1.5 | BC10: =(AY10*5900+BA10*3400+BB10*300+$AZ$3*AX10)/AX10 -> 19.077844
A11: 701~900份 | B11: 701 | C11: =S11 -> 0 | D11: 0.2 | E11: 1.1 | F11: =N11-0.1 -> 0.9 | G11: =(C11*5900+E11*3400+F11*300+$D$3*B11)/B11 -> 7.7203994 | H11: 18 | J11: 701 | K11: =C11 -> 0 | L11: 0.2 | M11: =E11+0.1 -> 1.2 | N11: 1 | O11: =(K11*5900+M11*3400+N11*300+$L$3*J11)/J11 -> 9.2482168 | P11: 18 | R11: 701 | S11: 0 | T11: 0.2 | U11: =M11+0.1 -> 1.3 | V11: =N11+0.1 -> 1.1 | W11: =(S11*5900+U11*3400+V11*300+$T$3*R11)/R11 -> 10.776034 | X11: 18 | Z11: 701 | AA11: =S11 -> 0 | AB11: 0.2 | AC11: =U11+0.1 -> 1.4 | AD11: =V11+0.1 -> 1.2 | AE11: =(AA11*5900+AC11*3400+AD11*300+$AB$3*Z11)/Z11 -> 12.303852 | AH11: 701 | AI11: =AA11 -> 0 | AJ11: 0.2 | AK11: =AC11+0.1 -> 1.5 | AL11: =AD11+0.1 -> 1.3 | AM11: =(AI11*5900+AK11*3400+AL11*300+$AJ$3*AH11)/AH11 -> 13.831669 | AP11: 701 | AQ11: =AI11 -> 0 | AR11: 0.2 | AS11: =AK11+0.1 -> 1.6 | AT11: =AL11+0.1 -> 1.4 | AU11: =(AQ11*5900+AS11*3400+AT11*300+AP11*$AR$3)/AP11 -> 15.359486 | AX11: 701 | AY11: =AQ11 -> 0 | AZ11: 0.2 | BA11: =AS11+0.1 -> 1.7 | BB11: =AT11+0.1 -> 1.5 | BC11: =(AY11*5900+BA11*3400+BB11*300+$AZ$3*AX11)/AX11 -> 16.887304
A12: 901~1000份 | B12: 901 | C12: =S12 -> 0 | D12: 0.3 | E12: 1.5 | F12: =N12-0.1 -> 0.9 | G12: =(C12*5900+E12*3400+F12*300+$D$3*B12)/B12 -> 7.9600444 | H12: 18 | J12: 901 | K12: =C12 -> 0 | L12: 0.3 | M12: =E12+0.1 -> 1.6 | N12: 1 | O12: =(K12*5900+M12*3400+N12*300+$L$3*J12)/J12 -> 9.3706992 | P12: 18 | R12: 901 | S12: 0 | T12: 0.3 | U12: =M12+0.1 -> 1.7 | V12: =N12+0.1 -> 1.1 | W12: =(S12*5900+U12*3400+V12*300+$T$3*R12)/R12 -> 10.781354 | X12: 18 | Z12: 901 | AA12: =S12 -> 0 | AB12: 0.3 | AC12: =U12+0.1 -> 1.8 | AD12: =V12+0.1 -> 1.2 | AE12: =(AA12*5900+AC12*3400+AD12*300+$AB$3*Z12)/Z12 -> 12.192009 | AH12: 901 | AI12: =AA12 -> 0 | AJ12: 0.3 | AK12: =AC12+0.1 -> 1.9 | AL12: =AD12+0.1 -> 1.3 | AM12: =(AI12*5900+AK12*3400+AL12*300+$AJ$3*AH12)/AH12 -> 13.602664 | AP12: 901 | AQ12: =AI12 -> 0 | AR12: 0.3 | AS12: =AK12+0.1 -> 2 | AT12: =AL12+0.1 -> 1.4 | AU12: =(AQ12*5900+AS12*3400+AT12*300+AP12*$AR$3)/AP12 -> 15.013319 | AX12: 901 | AY12: =AQ12 -> 0 | AZ12: 0.3 | BA12: =AS12+0.1 -> 2.1 | BB12: =AT12+0.1 -> 1.5 | BC12: =(AY12*5900+BA12*3400+BB12*300+$AZ$3*AX12)/AX12 -> 16.423973
A13: 1001~1200份 | B13: 1001 | C13: =S13 -> 0 | D13: 0.4 | E13: =E36-0.1 -> 1.8 | F13: =N13-0.1 -> 1.9 | G13: =(C13*5900+E13*3400+F13*300+$D$3*B13)/B13 -> 8.6833167 | H13: 18 | J13: 1001 | K13: =C13 -> 0 | L13: 0.4 | M13: =E13+0.1 -> 1.9 | N13: 2 | O13: =(K13*5900+M13*3400+N13*300+$L$3*J13)/J13 -> 10.052947 | P13: 18 | R13: 1001 | S13: =S36-0.1 -> 0 | T13: 0.4 | U13: =M13+0.1 -> 2 | V13: =N13+0.1 -> 2.1 | W13: =(S13*5900+U13*3400+V13*300+$T$3*R13)/R13 -> 11.422577 | X13: 18 | Z13: 1001 | AA13: =S13 -> 0 | AB13: 0.4 | AC13: =U13+0.1 -> 2.1 | AD13: =V13+0.1 -> 2.2 | AE13: =(AA13*5900+AC13*3400+AD13*300+$AB$3*Z13)/Z13 -> 12.792208 | AH13: 1001 | AI13: =AA13 -> 0 | AJ13: 0.4 | AK13: =AC13+0.1 -> 2.2 | AL13: =AD13+0.1 -> 2.3 | AM13: =(AI13*5900+AK13*3400+AL13*300+$AJ$3*AH13)/AH13 -> 14.161838 | AP13: 1001 | AQ13: =AI13 -> 0 | AR13: 0.4 | AS13: =AK13+0.1 -> 2.3 | AT13: =AL13+0.1 -> 2.4 | AU13: =(AQ13*5900+AS13*3400+AT13*300+AP13*$AR$3)/AP13 -> 15.531469 | AX13: 1001 | AY13: =AQ13 -> 0 | AZ13: 0.4 | BA13: =AS13+0.1 -> 2.4 | BB13: =AT13+0.1 -> 2.5 | BC13: =(AY13*5900+BA13*3400+BB13*300+$AZ$3*AX13)/AX13 -> 16.901099
A14: 1201~1400份 | B14: 1201 | C14: =S14 -> 0 | D14: 0.5 | E14: =E37-0.1 -> 1.9 | F14: =N14-0.1 -> 1.9 | G14: =(C14*5900+E14*3400+F14*300+$D$3*B14)/B14 -> 7.8534555 | H14: 18 | J14: 1201 | K14: =C14 -> 0 | L14: 0.5 | M14: =E14+0.1 -> 2 | N14: 2 | O14: =(K14*5900+M14*3400+N14*300+$L$3*J14)/J14 -> 9.1615321 | P14: 18 | R14: 1201 | S14: =S37-0.1 -> 0 | T14: 0.5 | U14: =M14+0.1 -> 2.1 | V14: =N14+0.1 -> 2.1 | W14: =(S14*5900+U14*3400+V14*300+$T$3*R14)/R14 -> 10.469609 | X14: 18 | Z14: 1201 | AA14: =S14 -> 0 | AB14: 0.5 | AC14: =U14+0.1 -> 2.2 | AD14: =V14+0.1 -> 2.2 | AE14: =(AA14*5900+AC14*3400+AD14*300+$AB$3*Z14)/Z14 -> 11.777685 | AH14: 1201 | AI14: =AA14 -> 0 | AJ14: 0.5 | AK14: =AC14+0.1 -> 2.3 | AL14: =AD14+0.1 -> 2.3 | AM14: =(AI14*5900+AK14*3400+AL14*300+$AJ$3*AH14)/AH14 -> 13.085762 | AP14: 1201 | AQ14: =AI14 -> 0 | AR14: 0.5 | AS14: =AK14+0.1 -> 2.4 | AT14: =AL14+0.1 -> 2.4 | AU14: =(AQ14*5900+AS14*3400+AT14*300+AP14*$AR$3)/AP14 -> 14.393838 | AX14: 1201 | AY14: =AQ14 -> 0 | AZ14: 0.5 | BA14: =AS14+0.1 -> 2.5 | BB14: =AT14+0.1 -> 2.5 | BC14: =(AY14*5900+BA14*3400+BB14*300+$AZ$3*AX14)/AX14 -> 15.701915
A15: 1401~1600份 | B15: 1401 | C15: =S15 -> 0 | D15: 0.5 | E15: =E38-0.1 -> 2 | F15: =N15-0.1 -> 1.9 | G15: =(C15*5900+E15*3400+F15*300+$D$3*B15)/B15 -> 7.2605282 | H15: 18 | J15: 1401 | K15: =C15 -> 0 | L15: 0.5 | M15: =E15+0.1 -> 2.1 | N15: 2 | O15: =(K15*5900+M15*3400+N15*300+$L$3*J15)/J15 -> 8.5246253 | P15: 18 | R15: 1401 | S15: =S38-0.1 -> 0 | T15: 0.5 | U15: =M15+0.1 -> 2.2 | V15: =N15+0.1 -> 2.1 | W15: =(S15*5900+U15*3400+V15*300+$T$3*R15)/R15 -> 9.7887223 | X15: 18 | Z15: 1401 | AA15: =S15 -> 0 | AB15: 0.5 | AC15: =U15+0.1 -> 2.3 | AD15: =V15+0.1 -> 2.2 | AE15: =(AA15*5900+AC15*3400+AD15*300+$AB$3*Z15)/Z15 -> 11.052819 | AH15: 1401 | AI15: =AA15 -> 0 | AJ15: 0.5 | AK15: =AC15+0.1 -> 2.4 | AL15: =AD15+0.1 -> 2.3 | AM15: =(AI15*5900+AK15*3400+AL15*300+$AJ$3*AH15)/AH15 -> 12.316916 | AP15: 1401 | AQ15: =AI15 -> 0 | AR15: 0.5 | AS15: =AK15+0.1 -> 2.5 | AT15: =AL15+0.1 -> 2.4 | AU15: =(AQ15*5900+AS15*3400+AT15*300+AP15*$AR$3)/AP15 -> 13.581014 | AX15: 1401 | AY15: =AQ15 -> 0 | AZ15: 0.5 | BA15: =AS15+0.1 -> 2.6 | BB15: =AT15+0.1 -> 2.5 | BC15: =(AY15*5900+BA15*3400+BB15*300+$AZ$3*AX15)/AX15 -> 14.845111
A16: 1601~1800份 | B16: 1601 | C16: =S16 -> 0 | D16: 0.6 | E16: =E39-0.1 -> 2.2 | F16: =N16-0.1 -> 1.9 | G16: =(C16*5900+E16*3400+F16*300+$D$3*B16)/B16 -> 7.0281074 | H16: 18 | J16: 1601 | K16: =C16 -> 0 | L16: 0.6 | M16: =E16+0.1 -> 2.3 | N16: 2 | O16: =(K16*5900+M16*3400+N16*300+$L$3*J16)/J16 -> 8.259213 | P16: 18 | R16: 1601 | S16: =S39-0.1 -> 0 | T16: 0.6 | U16: =M16+0.1 -> 2.4 | V16: =N16+0.1 -> 2.1 | W16: =(S16*5900+U16*3400+V16*300+$T$3*R16)/R16 -> 9.4903186 | X16: 18 | Z16: 1601 | AA16: =S16 -> 0 | AB16: 0.6 | AC16: =U16+0.1 -> 2.5 | AD16: =V16+0.1 -> 2.2 | AE16: =(AA16*5900+AC16*3400+AD16*300+$AB$3*Z16)/Z16 -> 10.721424 | AH16: 1601 | AI16: =AA16 -> 0 | AJ16: 0.6 | AK16: =AC16+0.1 -> 2.6 | AL16: =AD16+0.1 -> 2.3 | AM16: =(AI16*5900+AK16*3400+AL16*300+$AJ$3*AH16)/AH16 -> 11.95253 | AP16: 1601 | AQ16: =AI16 -> 0 | AR16: 0.6 | AS16: =AK16+0.1 -> 2.7 | AT16: =AL16+0.1 -> 2.4 | AU16: =(AQ16*5900+AS16*3400+AT16*300+AP16*$AR$3)/AP16 -> 13.183635 | AX16: 1601 | AY16: =AQ16 -> 0 | AZ16: 0.6 | BA16: =AS16+0.1 -> 2.8 | BB16: =AT16+0.1 -> 2.5 | BC16: =(AY16*5900+BA16*3400+BB16*300+$AZ$3*AX16)/AX16 -> 14.414741
A17: 1801~2000份 | B17: 1801 | C17: =S17 -> 0 | D17: 0.6 | E17: =E40-0.1 -> 2.4 | F17: =N17-0.1 -> 1.9 | G17: =(C17*5900+E17*3400+F17*300+$D$3*B17)/B17 -> 6.8473071 | H17: 18 | J17: 1801 | K17: =C17 -> 0 | L17: 0.6 | M17: =E17+0.1 -> 2.5 | N17: 2 | O17: =(K17*5900+M17*3400+N17*300+$L$3*J17)/J17 -> 8.0527485 | P17: 18 | R17: 1801 | S17: =S40-0.1 -> 0 | T17: 0.6 | U17: =M17+0.1 -> 2.6 | V17: =N17+0.1 -> 2.1 | W17: =(S17*5900+U17*3400+V17*300+$T$3*R17)/R17 -> 9.2581899 | X17: 18 | Z17: 1801 | AA17: =S17 -> 0 | AB17: 0.6 | AC17: =U17+0.1 -> 2.7 | AD17: =V17+0.1 -> 2.2 | AE17: =(AA17*5900+AC17*3400+AD17*300+$AB$3*Z17)/Z17 -> 10.463631 | AH17: 1801 | AI17: =AA17 -> 0 | AJ17: 0.6 | AK17: =AC17+0.1 -> 2.8 | AL17: =AD17+0.1 -> 2.3 | AM17: =(AI17*5900+AK17*3400+AL17*300+$AJ$3*AH17)/AH17 -> 11.669073 | AP17: 1801 | AQ17: =AI17 -> 0 | AR17: 0.6 | AS17: =AK17+0.1 -> 2.9 | AT17: =AL17+0.1 -> 2.4 | AU17: =(AQ17*5900+AS17*3400+AT17*300+AP17*$AR$3)/AP17 -> 12.874514 | AX17: 1801 | AY17: =AQ17 -> 0 | AZ17: 0.6 | BA17: =AS17+0.1 -> 3 | BB17: =AT17+0.1 -> 2.5 | BC17: =(AY17*5900+BA17*3400+BB17*300+$AZ$3*AX17)/AX17 -> 14.079956
A18: 2001~2200份 | B18: 2001 | C18: =S18 -> 0.1 | D18: 0.7 | E18: 2.5 | F18: =N18-0.1 -> 1.9 | G18: =(C18*5900+E18*3400+F18*300+$D$3*B18)/B18 -> 6.8275862 | H18: 18 | J18: 2001 | K18: =C18 -> 0.1 | L18: 0.7 | M18: =E18+0.1 -> 2.6 | N18: 2 | O18: =(K18*5900+M18*3400+N18*300+$L$3*J18)/J18 -> 8.0124938 | P18: 18 | R18: 2001 | S18: =S41-0.1 -> 0.1 | T18: 0.7 | U18: =M18+0.1 -> 2.7 | V18: =N18+0.1 -> 2.1 | W18: =(S18*5900+U18*3400+V18*300+$T$3*R18)/R18 -> 9.1974013 | X18: 18 | Z18: 2001 | AA18: =S18 -> 0.1 | AB18: 0.7 | AC18: =U18+0.1 -> 2.8 | AD18: =V18+0.1 -> 2.2 | AE18: =(AA18*5900+AC18*3400+AD18*300+$AB$3*Z18)/Z18 -> 10.382309 | AH18: 2001 | AI18: =AA18 -> 0.1 | AJ18: 0.7 | AK18: =AC18+0.1 -> 2.9 | AL18: =AD18+0.1 -> 2.3 | AM18: =(AI18*5900+AK18*3400+AL18*300+$AJ$3*AH18)/AH18 -> 11.567216 | AP18: 2001 | AQ18: =AI18 -> 0.1 | AR18: 0.7 | AS18: =AK18+0.1 -> 3 | AT18: =AL18+0.1 -> 2.4 | AU18: =(AQ18*5900+AS18*3400+AT18*300+AP18*$AR$3)/AP18 -> 12.752124 | AX18: 2001 | AY18: =AQ18 -> 0.1 | AZ18: 0.7 | BA18: =AS18+0.1 -> 3.1 | BB18: =AT18+0.1 -> 2.5 | BC18: =(AY18*5900+BA18*3400+BB18*300+$AZ$3*AX18)/AX18 -> 13.937031
A19: 2201~2400份 | B19: 2201 | C19: =S19 -> 0.1 | D19: 0.7 | E19: =E42-0.1 -> 2.8 | F19: =N19-0.1 -> 1.9 | G19: =(C19*5900+E19*3400+F19*300+$D$3*B19)/B19 -> 6.8523398 | H19: 18 | J19: 2201 | K19: =C19 -> 0.1 | L19: 0.7 | M19: =E19+0.1 -> 2.9 | N19: 2 | O19: =(K19*5900+M19*3400+N19*300+$L$3*J19)/J19 -> 8.0204453 | P19: 18 | R19: 2201 | S19: =S42-0.1 -> 0.1 | T19: 0.7 | U19: =M19+0.1 -> 3 | V19: =N19+0.1 -> 2.1 | W19: =(S19*5900+U19*3400+V19*300+$T$3*R19)/R19 -> 9.1885507 | X19: 18 | Z19: 2201 | AA19: =S19 -> 0.1 | AB19: 0.7 | AC19: =U19+0.1 -> 3.1 | AD19: =V19+0.1 -> 2.2 | AE19: =(AA19*5900+AC19*3400+AD19*300+$AB$3*Z19)/Z19 -> 10.356656 | AH19: 2201 | AI19: =AA19 -> 0.1 | AJ19: 0.7 | AK19: =AC19+0.1 -> 3.2 | AL19: =AD19+0.1 -> 2.3 | AM19: =(AI19*5900+AK19*3400+AL19*300+$AJ$3*AH19)/AH19 -> 11.524761 | AP19: 2201 | AQ19: =AI19 -> 0.1 | AR19: 0.7 | AS19: =AK19+0.1 -> 3.3 | AT19: =AL19+0.1 -> 2.4 | AU19: =(AQ19*5900+AS19*3400+AT19*300+AP19*$AR$3)/AP19 -> 12.692867 | AX19: 2201 | AY19: =AQ19 -> 0.1 | AZ19: 0.7 | BA19: =AS19+0.1 -> 3.4 | BB19: =AT19+0.1 -> 2.5 | BC19: =(AY19*5900+BA19*3400+BB19*300+$AZ$3*AX19)/AX19 -> 13.860972
A20: 2401~2600份 | B20: 2401 | C20: =S20 -> 0.1 | D20: 0.8 | E20: =E43-0.1 -> 2.9 | F20: =N20-0.1 -> 1.9 | G20: =(C20*5900+E20*3400+F20*300+$D$3*B20)/B20 -> 6.5897543 | H20: 18 | J20: 2401 | K20: =C20 -> 0.1 | L20: 0.8 | M20: =E20+0.1 -> 3 | N20: 2 | O20: =(K20*5900+M20*3400+N20*300+$L$3*J20)/J20 -> 7.7438567 | P20: 18 | R20: 2401 | S20: =S43-0.1 -> 0.1 | T20: 0.8 | U20: =M20+0.1 -> 3.1 | V20: =N20+0.1 -> 2.1 | W20: =(S20*5900+U20*3400+V20*300+$T$3*R20)/R20 -> 8.8979592 | X20: 18 | Z20: 2401 | AA20: =S20 -> 0.1 | AB20: 0.8 | AC20: =U20+0.1 -> 3.2 | AD20: =V20+0.1 -> 2.2 | AE20: =(AA20*5900+AC20*3400+AD20*300+$AB$3*Z20)/Z20 -> 10.052062 | AH20: 2401 | AI20: =AA20 -> 0.1 | AJ20: 0.8 | AK20: =AC20+0.1 -> 3.3 | AL20: =AD20+0.1 -> 2.3 | AM20: =(AI20*5900+AK20*3400+AL20*300+$AJ$3*AH20)/AH20 -> 11.206164 | AP20: 2401 | AQ20: =AI20 -> 0.1 | AR20: 0.8 | AS20: =AK20+0.1 -> 3.4 | AT20: =AL20+0.1 -> 2.4 | AU20: =(AQ20*5900+AS20*3400+AT20*300+AP20*$AR$3)/AP20 -> 12.360267 | AX20: 2401 | AY20: =AQ20 -> 0.1 | AZ20: 0.8 | BA20: =AS20+0.1 -> 3.5 | BB20: =AT20+0.1 -> 2.5 | BC20: =(AY20*5900+BA20*3400+BB20*300+$AZ$3*AX20)/AX20 -> 13.514369
A21: 2601~2800份 | B21: 2601 | C21: =S21 -> 0.1 | D21: 0.8 | E21: =E44-0.1 -> 3 | F21: =N21-0.1 -> 1.9 | G21: =(C21*5900+E21*3400+F21*300+$D$3*B21)/B21 -> 6.3675509 | H21: 18 | J21: 2601 | K21: =C21 -> 0.1 | L21: 0.8 | M21: =E21+0.1 -> 3.1 | N21: 2 | O21: =(K21*5900+M21*3400+N21*300+$L$3*J21)/J21 -> 7.5098039 | P21: 18 | R21: 2601 | S21: 0.1 | T21: 0.8 | U21: =M21+0.1 -> 3.2 | V21: =N21+0.1 -> 2.1 | W21: =(S21*5900+U21*3400+V21*300+$T$3*R21)/R21 -> 8.6520569 | X21: 18 | Z21: 2601 | AA21: =S21 -> 0.1 | AB21: 0.8 | AC21: =U21+0.1 -> 3.3 | AD21: =V21+0.1 -> 2.2 | AE21: =(AA21*5900+AC21*3400+AD21*300+$AB$3*Z21)/Z21 -> 9.7943099 | AH21: 2601 | AI21: =AA21 -> 0.1 | AJ21: 0.8 | AK21: =AC21+0.1 -> 3.4 | AL21: =AD21+0.1 -> 2.3 | AM21: =(AI21*5900+AK21*3400+AL21*300+$AJ$3*AH21)/AH21 -> 10.936563 | AP21: 2601 | AQ21: =AI21 -> 0.1 | AR21: 0.8 | AS21: =AK21+0.1 -> 3.5 | AT21: =AL21+0.1 -> 2.4 | AU21: =(AQ21*5900+AS21*3400+AT21*300+AP21*$AR$3)/AP21 -> 12.078816 | AX21: 2601 | AY21: =AQ21 -> 0.1 | AZ21: 0.8 | BA21: =AS21+0.1 -> 3.6 | BB21: =AT21+0.1 -> 2.5 | BC21: =(AY21*5900+BA21*3400+BB21*300+$AZ$3*AX21)/AX21 -> 13.221069
A22: 2801~3000份 | B22: 2801 | C22: =S22 -> 0.1 | D22: 0.8 | E22: 3.3 | F22: =N22-0.1 -> 1.9 | G22: =(C22*5900+E22*3400+F22*300+$D$3*B22)/B22 -> 6.4198501 | H22: 18 | J22: 2801 | K22: =C22 -> 0.1 | L22: 0.8 | M22: =E22+0.1 -> 3.4 | N22: 2 | O22: =(K22*5900+M22*3400+N22*300+$L$3*J22)/J22 -> 7.5519457 | P22: 18 | R22: 2801 | S22: 0.1 | T22: 0.8 | U22: =M22+0.1 -> 3.5 | V22: =N22+0.1 -> 2.1 | W22: =(S22*5900+U22*3400+V22*300+$T$3*R22)/R22 -> 8.6840414 | X22: 18 | Z22: 2801 | AA22: =S22 -> 0.1 | AB22: 0.8 | AC22: =U22+0.1 -> 3.6 | AD22: =V22+0.1 -> 2.2 | AE22: =(AA22*5900+AC22*3400+AD22*300+$AB$3*Z22)/Z22 -> 9.8161371 | AH22: 2801 | AI22: =AA22 -> 0.1 | AJ22: 0.8 | AK22: =AC22+0.1 -> 3.7 | AL22: =AD22+0.1 -> 2.3 | AM22: =(AI22*5900+AK22*3400+AL22*300+$AJ$3*AH22)/AH22 -> 10.948233 | AP22: 2801 | AQ22: =AI22 -> 0.1 | AR22: 0.8 | AS22: =AK22+0.1 -> 3.8 | AT22: =AL22+0.1 -> 2.4 | AU22: =(AQ22*5900+AS22*3400+AT22*300+AP22*$AR$3)/AP22 -> 12.080328 | AX22: 2801 | AY22: =AQ22 -> 0.1 | AZ22: 0.8 | BA22: =AS22+0.1 -> 3.9 | BB22: =AT22+0.1 -> 2.5 | BC22: =(AY22*5900+BA22*3400+BB22*300+$AZ$3*AX22)/AX22 -> 13.212424
B24: 人群难度 | C24: 二级难度 | J24: 人群难度 | L24: 二级难度 | R24: 人群难度 | T24: 二级难度 | Z24: 人群难度 | AB24: 二级难度 | AH24: 人群难度 | AJ24: 二级难度 | AP24: 人群难度 | AR24: 二级难度 | AX24: 人群难度 | AZ24: 二级难度
B25: 问卷难度 | C25: 20题以内 | G25: =AVERAGE(G30:G45) -> 10.529116 | J25: 问卷难度 | L25: 21~30题 | R25: 问卷难度 | T25: 31~40题 | Z25: 问卷难度 | AB25: 41~50题 | AH25: 问卷难度 | AJ25: 51~60 | AP25: 问卷难度 | AR25: 61~70 | AX25: 问卷难度 | AZ25: 71~80
B26: 单价 | D26: =D3+1 -> 3 | G26: 成本 | H26: 上限 | J26: 单价 | L26: =L3+1 -> 4 | O26: =AVERAGE(O30:O45) -> 12.189754 | R26: 单价 | T26: =T3+1 -> 5 | W26: =AVERAGE(W30:W45) -> 13.850392 | Z26: 单价 | AB26: =AB3+1 -> 6 | AE26: =AVERAGE(AE30:AE45) -> 15.300634 | AH26: 单价 | AJ26: =AJ3+1 -> 7 | AM26: =AVERAGE(AM30:AM45) -> 16.961272 | AP26: 单价 | AR26: =AR3+1 -> 8 | AU26: =AVERAGE(AU30:AU45) -> 18.62191 | AX26: 单价 | AZ26: =AZ3+1 -> 9 | BC26: =AVERAGE(BC30:BC45) -> 20.282548 | BE26: =AVERAGE(BC26,AU26,AM26,AE26,W26,O26,G26) -> 16.201085 | BF26: =BE26-AVERAGE(AZ26,AR26,AJ26,AB26,T26,L26,D26) -> 10.201085
B27: 份数 | C27: P5 | D27: P4 | E27: P3 | F27: 实习生 | J27: 份数 | K27: P5 | L27: P4 | M27: P3 | N27: 实习生 | O27: 成本 | R27: 份数 | S27: P5 | T27: P4 | U27: P3 | V27: 实习生 | W27: 成本 | Z27: 份数 | AA27: P5 | AB27: P4 | AC27: P3 | AD27: 实习生 | AH27: 份数 | AI27: P5 | AJ27: P4 | AK27: P3 | AL27: 实习生 | AP27: 份数 | AR27: P4 | AS27: P3 | AT27: 实习生 | AX27: 份数 | AZ27: P4 | BA27: P3 | BB27: 实习生
B28: 0 | D28: 0 | E28: 0 | F28: =F51 -> 0 | G28: =(C28*5900+E28*3400+F28*300+B28*$D$26)/B28 -> #DIV/0! | J28: 0 | K28: =S28 -> 0 | L28: 0 | M28: 0 | N28: =N51 -> 0 | O28: =(K28*5900+M28*3400+N28*300+J28*$L$26)/J28 -> #DIV/0! | R28: 0 | S28: 0 | T28: 0 | U28: 0 | V28: =V51 -> 0 | W28: =(S28*5900+U28*3400+V28*300+R28*$T$26)/R28 -> #DIV/0! | Z28: 0 | AA28: =S28 -> 0 | AB28: 0 | AC28: 0 | AD28: =AD51 -> 0.1 | AE28: =(AA28*5900+AC28*3400+AD28*300+Z28*$AB$26)/Z28 -> #DIV/0! | AH28: 0 | AI28: =S28 -> 0 | AJ28: 0 | AK28: 0 | AL28: =AL51 -> 0.2 | AM28: =(AI28*5900+AK28*3400+AL28*300+AH28*$AJ$26)/AH28 -> #DIV/0! | AP28: 0 | AQ28: =AI28 -> 0 | AR28: 0 | AS28: 0 | AT28: =AT51 -> 0.3 | AU28: =(AQ28*5900+AS28*3400+AT28*300+AP28*$AR$26)/AP28 -> #DIV/0! | AX28: 0 | AY28: =AQ28 -> 0 | AZ28: 0 | BA28: 0 | BB28: =BB51 -> 0.4 | BC28: =(AY28*5900+BA28*3400+BB28*300+AX28*$AZ$26)/AX28 -> #DIV/0!
A29: 100份及以下 | B29: 1 | C29: =K29 -> 0 | D29: 0 | E29: =E52-0.1 -> 0.4 | F29: =F52 -> 0.6 | G29: =(C29*5900+E29*3400+F29*300+$D$26*B29)/B29 -> 1543 | J29: 1 | K29: =S29 -> 0 | L29: 0 | M29: =E29+0.1 -> 0.5 | N29: =N52 -> 0.7 | O29: =(K29*5900+M29*3400+N29*300+$L$26*J29)/J29 -> 1914 | R29: 1 | S29: 0 | T29: 0 | U29: =M29+0.1 -> 0.6 | V29: =V52 -> 0.8 | W29: =(S29*5900+U29*3400+V29*300+$T$26*R29)/R29 -> 2285 | Z29: 1 | AA29: =S29 -> 0 | AB29: 0 | AC29: =U29+0.1 -> 0.7 | AD29: =AD52 -> 0.9 | AE29: =(AA29*5900+AC29*3400+AD29*300+$AB$26*Z29)/Z29 -> 2656 | AH29: 1 | AI29: =S29 -> 0 | AJ29: 0 | AK29: =AC29+0.1 -> 0.8 | AL29: =AL52 -> 1 | AM29: =(AI29*5900+AK29*3400+AL29*300+$AJ$26*AH29)/AH29 -> 3027 | AP29: 1 | AQ29: =AI29 -> 0 | AR29: 0 | AS29: =AK29+0.1 -> 0.9 | AT29: =AT52 -> 1.1 | AU29: =(AQ29*5900+AS29*3400+AT29*300+$AR$26*AP29)/AP29 -> 3398 | AX29: 1 | AY29: =AQ29 -> 0 | AZ29: =AZ30 -> 0 | BA29: =BA30 -> 0.9 | BB29: =BB30 -> 1.2 | BC29: =(AY29*5900+BA29*3400+BB29*300+$AZ$26*AX29)/AX29 -> 3429
A30: 101~200份 | B30: 101 | C30: =K30 -> 0 | D30: 0 | E30: =E53-0.1 -> 0.4 | F30: =F53 -> 0.6 | G30: =(C30*5900+E30*3400+F30*300+$D$26*B30)/B30 -> 18.247525 | J30: 101 | K30: =S30 -> 0 | L30: 0 | M30: =E30+0.1 -> 0.5 | N30: =N53 -> 0.7 | O30: =(K30*5900+M30*3400+N30*300+$L$26*J30)/J30 -> 22.910891 | R30: 101 | S30: 0 | T30: 0 | U30: =M30+0.1 -> 0.6 | V30: =V53 -> 0.8 | W30: =(S30*5900+U30*3400+V30*300+$T$26*R30)/R30 -> 27.574257 | Z30: 101 | AA30: =S30 -> 0 | AB30: 0 | AC30: 0.6 | AD30: =AD53 -> 0.9 | AE30: =(AA30*5900+AC30*3400+AD30*300+$AB$26*Z30)/Z30 -> 28.871287 | AH30: 101 | AI30: =S30 -> 0 | AJ30: 0 | AK30: 0.7 | AL30: =AL53 -> 1 | AM30: =(AI30*5900+AK30*3400+AL30*300+$AJ$26*AH30)/AH30 -> 33.534653 | AP30: 101 | AQ30: =AI30 -> 0 | AR30: 0 | AS30: =AK30+0.1 -> 0.8 | AT30: =AT53 -> 1.1 | AU30: =(AQ30*5900+AS30*3400+AT30*300+$AR$26*AP30)/AP30 -> 38.19802 | AX30: 101 | AY30: =AQ30 -> 0 | AZ30: 0 | BA30: =AS30+0.1 -> 0.9 | BB30: =BB53 -> 1.2 | BC30: =(AY30*5900+BA30*3400+BB30*300+$AZ$26*AX30)/AX30 -> 42.861386
A31: 201~300份 | B31: 201 | C31: =K31 -> 0 | D31: 0.2 | E31: =E54-0.1 -> 0.7 | F31: =F54 -> 1 | G31: =(C31*5900+E31*3400+F31*300+$D$26*B31)/B31 -> 16.333333 | J31: 201 | K31: =S31 -> 0 | L31: 0.2 | M31: =E31+0.1 -> 0.8 | N31: =N54 -> 1.1 | O31: =(K31*5900+M31*3400+N31*300+$L$26*J31)/J31 -> 19.174129 | R31: 201 | S31: 0 | T31: 0.2 | U31: =M31+0.1 -> 0.9 | V31: =V54 -> 1.2 | W31: =(S31*5900+U31*3400+V31*300+$T$26*R31)/R31 -> 22.014925 | Z31: 201 | AA31: =S31 -> 0 | AB31: 0.2 | AC31: =U31+0.1 -> 1 | AD31: =AD54 -> 1.3 | AE31: =(AA31*5900+AC31*3400+AD31*300+$AB$26*Z31)/Z31 -> 24.855721 | AH31: 201 | AI31: =S31 -> 0 | AJ31: 0.2 | AK31: =AC31+0.1 -> 1.1 | AL31: =AL54 -> 1.4 | AM31: =(AI31*5900+AK31*3400+AL31*300+$AJ$26*AH31)/AH31 -> 27.696517 | AP31: 201 | AQ31: =AI31 -> 0 | AR31: 0.2 | AS31: =AK31+0.1 -> 1.2 | AT31: =AT54 -> 1.5 | AU31: =(AQ31*5900+AS31*3400+AT31*300+$AR$26*AP31)/AP31 -> 30.537313 | AX31: 201 | AY31: =AQ31 -> 0 | AZ31: 0.2 | BA31: =AS31+0.1 -> 1.3 | BB31: =BB54 -> 1.6 | BC31: =(AY31*5900+BA31*3400+BB31*300+$AZ$26*AX31)/AX31 -> 33.378109
A32: 301~500份 | B32: 301 | C32: =K32 -> 0 | D32: 0.2 | E32: =E55-0.1 -> 0.9 | F32: =F55 -> 1.1 | G32: =(C32*5900+E32*3400+F32*300+$D$26*B32)/B32 -> 14.262458 | J32: 301 | K32: =S32 -> 0 | L32: 0.2 | M32: =E32+0.1 -> 1 | N32: =N55 -> 1.2 | O32: =(K32*5900+M32*3400+N32*300+$L$26*J32)/J32 -> 16.491694 | R32: 301 | S32: 0 | T32: 0.2 | U32: =M32+0.1 -> 1.1 | V32: =V55 -> 1.3 | W32: =(S32*5900+U32*3400+V32*300+$T$26*R32)/R32 -> 18.72093 | Z32: 301 | AA32: =S32 -> 0 | AB32: 0.2 | AC32: =U32+0.1 -> 1.2 | AD32: =AD55 -> 1.4 | AE32: =(AA32*5900+AC32*3400+AD32*300+$AB$26*Z32)/Z32 -> 20.950166 | AH32: 301 | AI32: =S32 -> 0 | AJ32: 0.2 | AK32: =AC32+0.1 -> 1.3 | AL32: =AL55 -> 1.5 | AM32: =(AI32*5900+AK32*3400+AL32*300+$AJ$26*AH32)/AH32 -> 23.179402 | AP32: 301 | AQ32: =AI32 -> 0 | AR32: 0.2 | AS32: =AK32+0.1 -> 1.4 | AT32: =AT55 -> 1.6 | AU32: =(AQ32*5900+AS32*3400+AT32*300+$AR$26*AP32)/AP32 -> 25.408638 | AX32: 301 | AY32: =AQ32 -> 0 | AZ32: 0.2 | BA32: =AS32+0.1 -> 1.5 | BB32: =BB55 -> 1.7 | BC32: =(AY32*5900+BA32*3400+BB32*300+$AZ$26*AX32)/AX32 -> 27.637874
A33: 501~700份 | B33: 501 | C33: =K33 -> 0 | D33: 0.2 | E33: =E56-0.1 -> 1.2 | F33: =F56 -> 1.2 | G33: =(C33*5900+E33*3400+F33*300+$D$26*B33)/B33 -> 11.862275 | J33: 501 | K33: =S33 -> 0 | L33: 0.2 | M33: =E33+0.1 -> 1.3 | N33: =N56 -> 1.3 | O33: =(K33*5900+M33*3400+N33*300+$L$26*J33)/J33 -> 13.600798 | R33: 501 | S33: =S56-0.1 -> 0 | T33: 0.2 | U33: =M33+0.1 -> 1.4 | V33: =V56 -> 1.4 | W33: =(S33*5900+U33*3400+V33*300+$T$26*R33)/R33 -> 15.339321 | Z33: 501 | AA33: =S33 -> 0 | AB33: 0.2 | AC33: =U33+0.1 -> 1.5 | AD33: =AD56 -> 1.5 | AE33: =(AA33*5900+AC33*3400+AD33*300+$AB$26*Z33)/Z33 -> 17.077844 | AH33: 501 | AI33: =S33 -> 0 | AJ33: 0.2 | AK33: =AC33+0.1 -> 1.6 | AL33: =AL56 -> 1.6 | AM33: =(AI33*5900+AK33*3400+AL33*300+$AJ$26*AH33)/AH33 -> 18.816367 | AP33: 501 | AQ33: =AI33 -> 0 | AR33: 0.2 | AS33: =AK33+0.1 -> 1.7 | AT33: =AT56 -> 1.7 | AU33: =(AQ33*5900+AS33*3400+AT33*300+$AR$26*AP33)/AP33 -> 20.55489 | AX33: 501 | AY33: =AQ33 -> 0 | AZ33: 0.2 | BA33: =AS33+0.1 -> 1.8 | BB33: =BB56 -> 1.8 | BC33: =(AY33*5900+BA33*3400+BB33*300+$AZ$26*AX33)/AX33 -> 22.293413
A34: 701~900份 | B34: 701 | C34: =K34 -> 0.1 | D34: 0.2 | E34: =E57-0.1 -> 1.4 | F34: =F57 -> 1.3 | G34: =(C34*5900+E34*3400+F34*300+$D$26*B34)/B34 -> 11.188302 | J34: 701 | K34: =S34 -> 0.1 | L34: 0.2 | M34: =E34+0.1 -> 1.5 | N34: =N57 -> 1.4 | O34: =(K34*5900+M34*3400+N34*300+$L$26*J34)/J34 -> 12.71612 | R34: 701 | S34: =S57 -> 0.1 | T34: 0.2 | U34: =M34+0.1 -> 1.6 | V34: =V57 -> 1.5 | W34: =(S34*5900+U34*3400+V34*300+$T$26*R34)/R34 -> 14.243937 | Z34: 701 | AA34: =S34 -> 0.1 | AB34: 0.2 | AC34: =U34+0.1 -> 1.7 | AD34: =AD57 -> 1.6 | AE34: =(AA34*5900+AC34*3400+AD34*300+$AB$26*Z34)/Z34 -> 15.771755 | AH34: 701 | AI34: =S34 -> 0.1 | AJ34: 0.2 | AK34: =AC34+0.1 -> 1.8 | AL34: =AL57 -> 1.7 | AM34: =(AI34*5900+AK34*3400+AL34*300+$AJ$26*AH34)/AH34 -> 17.299572 | AP34: 701 | AQ34: =AI34 -> 0.1 | AR34: 0.2 | AS34: =AK34+0.1 -> 1.9 | AT34: =AT57 -> 1.8 | AU34: =(AQ34*5900+AS34*3400+AT34*300+$AR$26*AP34)/AP34 -> 18.827389 | AX34: 701 | AY34: =AQ34 -> 0.1 | AZ34: 0.2 | BA34: =AS34+0.1 -> 2 | BB34: =BB57 -> 1.9 | BC34: =(AY34*5900+BA34*3400+BB34*300+$AZ$26*AX34)/AX34 -> 20.355207
A35: 901~1000份 | B35: 901 | C35: =K35 -> 0 | D35: 0.3 | E35: =E58-0.1 -> 1.7 | F35: =F58 -> 1.3 | G35: =(C35*5900+E35*3400+F35*300+$D$26*B35)/B35 -> 9.8479467 | J35: 901 | K35: =S35 -> 0 | L35: 0.3 | M35: =E35+0.1 -> 1.8 | N35: =N58 -> 1.4 | O35: =(K35*5900+M35*3400+N35*300+$L$26*J35)/J35 -> 11.258602 | R35: 901 | S35: =S58-0.1 -> 0 | T35: 0.3 | U35: =M35+0.1 -> 1.9 | V35: =V58 -> 1.5 | W35: =(S35*5900+U35*3400+V35*300+$T$26*R35)/R35 -> 12.669256 | Z35: 901 | AA35: =S35 -> 0 | AB35: 0.3 | AC35: =U35+0.1 -> 2 | AD35: =AD58 -> 1.6 | AE35: =(AA35*5900+AC35*3400+AD35*300+$AB$26*Z35)/Z35 -> 14.079911 | AH35: 901 | AI35: =S35 -> 0 | AJ35: 0.3 | AK35: =AC35+0.1 -> 2.1 | AL35: =AL58 -> 1.7 | AM35: =(AI35*5900+AK35*3400+AL35*300+$AJ$26*AH35)/AH35 -> 15.490566 | AP35: 901 | AQ35: =AI35 -> 0 | AR35: 0.3 | AS35: =AK35+0.1 -> 2.2 | AT35: =AT58 -> 1.8 | AU35: =(AQ35*5900+AS35*3400+AT35*300+$AR$26*AP35)/AP35 -> 16.901221 | AX35: 901 | AY35: =AQ35 -> 0 | AZ35: 0.3 | BA35: =AS35+0.1 -> 2.3 | BB35: =BB58 -> 1.9 | BC35: =(AY35*5900+BA35*3400+BB35*300+$AZ$26*AX35)/AX35 -> 18.311876
A36: 1001~1200份 | B36: 1001 | C36: =K36 -> 0.1 | D36: 0.4 | E36: =E59-0.1 -> 1.9 | F36: =F59 -> 1.5 | G36: =(C36*5900+E36*3400+F36*300+$D$26*B36)/B36 -> 10.492507 | J36: 1001 | K36: =S36 -> 0.1 | L36: 0.4 | M36: =E36+0.1 -> 2 | N36: =N59 -> 1.6 | O36: =(K36*5900+M36*3400+N36*300+$L$26*J36)/J36 -> 11.862138 | R36: 1001 | S36: =S59-0.1 -> 0.1 | T36: 0.4 | U36: =M36+0.1 -> 2.1 | V36: =V59 -> 1.7 | W36: =(S36*5900+U36*3400+V36*300+$T$26*R36)/R36 -> 13.231768 | Z36: 1001 | AA36: =S36 -> 0.1 | AB36: 0.4 | AC36: =U36+0.1 -> 2.2 | AD36: =AD59 -> 1.8 | AE36: =(AA36*5900+AC36*3400+AD36*300+$AB$26*Z36)/Z36 -> 14.601399 | AH36: 1001 | AI36: =S36 -> 0.1 | AJ36: 0.4 | AK36: =AC36+0.1 -> 2.3 | AL36: =AL59 -> 1.9 | AM36: =(AI36*5900+AK36*3400+AL36*300+$AJ$26*AH36)/AH36 -> 15.971029 | AP36: 1001 | AQ36: =AI36 -> 0.1 | AR36: 0.4 | AS36: =AK36+0.1 -> 2.4 | AT36: =AT59 -> 2 | AU36: =(AQ36*5900+AS36*3400+AT36*300+$AR$26*AP36)/AP36 -> 17.340659 | AX36: 1001 | AY36: =AQ36 -> 0.1 | AZ36: 0.4 | BA36: =AS36+0.1 -> 2.5 | BB36: =BB59 -> 2.1 | BC36: =(AY36*5900+BA36*3400+BB36*300+$AZ$26*AX36)/AX36 -> 18.71029
A37: 1201~1400份 | B37: 1201 | C37: =K37 -> 0.1 | D37: 0.5 | E37: =E60-0.1 -> 2 | F37: =F60 -> 1.7 | G37: =(C37*5900+E37*3400+F37*300+$D$26*B37)/B37 -> 9.5778518 | J37: 1201 | K37: =S37 -> 0.1 | L37: 0.5 | M37: =E37+0.1 -> 2.1 | N37: =N60 -> 1.8 | O37: =(K37*5900+M37*3400+N37*300+$L$26*J37)/J37 -> 10.885928 | R37: 1201 | S37: =S60-0.1 -> 0.1 | T37: 0.5 | U37: =M37+0.1 -> 2.2 | V37: =V60 -> 1.9 | W37: =(S37*5900+U37*3400+V37*300+$T$26*R37)/R37 -> 12.194005 | Z37: 1201 | AA37: =S37 -> 0.1 | AB37: 0.5 | AC37: =U37+0.1 -> 2.3 | AD37: =AD60 -> 2 | AE37: =(AA37*5900+AC37*3400+AD37*300+$AB$26*Z37)/Z37 -> 13.502082 | AH37: 1201 | AI37: =S37 -> 0.1 | AJ37: 0.5 | AK37: =AC37+0.1 -> 2.4 | AL37: =AL60 -> 2.1 | AM37: =(AI37*5900+AK37*3400+AL37*300+$AJ$26*AH37)/AH37 -> 14.810158 | AP37: 1201 | AQ37: =AI37 -> 0.1 | AR37: 0.5 | AS37: =AK37+0.1 -> 2.5 | AT37: =AT60 -> 2.2 | AU37: =(AQ37*5900+AS37*3400+AT37*300+$AR$26*AP37)/AP37 -> 16.118235 | AX37: 1201 | AY37: =AQ37 -> 0.1 | AZ37: 0.5 | BA37: =AS37+0.1 -> 2.6 | BB37: =BB60 -> 2.3 | BC37: =(AY37*5900+BA37*3400+BB37*300+$AZ$26*AX37)/AX37 -> 17.426311
A38: 1401~1600份 | B38: 1401 | C38: =K38 -> 0.1 | D38: 0.5 | E38: =E61-0.1 -> 2.1 | F38: =F61 -> 1.8 | G38: =(C38*5900+E38*3400+F38*300+$D$26*B38)/B38 -> 8.9029265 | J38: 1401 | K38: =S38 -> 0.1 | L38: 0.5 | M38: =E38+0.1 -> 2.2 | N38: =N61 -> 1.9 | O38: =(K38*5900+M38*3400+N38*300+$L$26*J38)/J38 -> 10.167024 | R38: 1401 | S38: =S61-0.1 -> 0.1 | T38: 0.5 | U38: =M38+0.1 -> 2.3 | V38: =V61 -> 2 | W38: =(S38*5900+U38*3400+V38*300+$T$26*R38)/R38 -> 11.431121 | Z38: 1401 | AA38: =S38 -> 0.1 | AB38: 0.5 | AC38: =U38+0.1 -> 2.4 | AD38: =AD61 -> 2.1 | AE38: =(AA38*5900+AC38*3400+AD38*300+$AB$26*Z38)/Z38 -> 12.695218 | AH38: 1401 | AI38: =S38 -> 0.1 | AJ38: 0.5 | AK38: =AC38+0.1 -> 2.5 | AL38: =AL61 -> 2.2 | AM38: =(AI38*5900+AK38*3400+AL38*300+$AJ$26*AH38)/AH38 -> 13.959315 | AP38: 1401 | AQ38: =AI38 -> 0.1 | AR38: 0.5 | AS38: =AK38+0.1 -> 2.6 | AT38: =AT61 -> 2.3 | AU38: =(AQ38*5900+AS38*3400+AT38*300+$AR$26*AP38)/AP38 -> 15.223412 | AX38: 1401 | AY38: =AQ38 -> 0.1 | AZ38: 0.5 | BA38: =AS38+0.1 -> 2.7 | BB38: =BB61 -> 2.4 | BC38: =(AY38*5900+BA38*3400+BB38*300+$AZ$26*AX38)/AX38 -> 16.487509
A39: 1601~1800份 | B39: 1601 | C39: =K39 -> 0.1 | D39: 0.6 | E39: =E62-0.1 -> 2.3 | F39: =F62 -> 1.8 | G39: =(C39*5900+E39*3400+F39*300+$D$26*B39)/B39 -> 8.5902561 | J39: 1601 | K39: =S39 -> 0.1 | L39: 0.6 | M39: =E39+0.1 -> 2.4 | N39: =N62 -> 1.9 | O39: =(K39*5900+M39*3400+N39*300+$L$26*J39)/J39 -> 9.8213616 | R39: 1601 | S39: =S62-0.1 -> 0.1 | T39: 0.6 | U39: =M39+0.1 -> 2.5 | V39: =V62 -> 2 | W39: =(S39*5900+U39*3400+V39*300+$T$26*R39)/R39 -> 11.052467 | Z39: 1601 | AA39: =S39 -> 0.1 | AB39: 0.6 | AC39: =U39+0.1 -> 2.6 | AD39: =AD62 -> 2.1 | AE39: =(AA39*5900+AC39*3400+AD39*300+$AB$26*Z39)/Z39 -> 12.283573 | AH39: 1601 | AI39: =S39 -> 0.1 | AJ39: 0.6 | AK39: =AC39+0.1 -> 2.7 | AL39: =AL62 -> 2.2 | AM39: =(AI39*5900+AK39*3400+AL39*300+$AJ$26*AH39)/AH39 -> 13.514678 | AP39: 1601 | AQ39: =AI39 -> 0.1 | AR39: 0.6 | AS39: =AK39+0.1 -> 2.8 | AT39: =AT62 -> 2.3 | AU39: =(AQ39*5900+AS39*3400+AT39*300+$AR$26*AP39)/AP39 -> 14.745784 | AX39: 1601 | AY39: =AQ39 -> 0.1 | AZ39: 0.6 | BA39: =AS39+0.1 -> 2.9 | BB39: =BB62 -> 2.4 | BC39: =(AY39*5900+BA39*3400+BB39*300+$AZ$26*AX39)/AX39 -> 15.976889
A40: 1801~2000份 | B40: 1801 | C40: =K40 -> 0.1 | D40: 0.6 | E40: =E63-0.1 -> 2.5 | F40: =F63 -> 1.8 | G40: =(C40*5900+E40*3400+F40*300+$D$26*B40)/B40 -> 8.3470294 | J40: 1801 | K40: =S40 -> 0.1 | L40: 0.6 | M40: =E40+0.1 -> 2.6 | N40: =N63 -> 1.9 | O40: =(K40*5900+M40*3400+N40*300+$L$26*J40)/J40 -> 9.5524708 | R40: 1801 | S40: =S63-0.1 -> 0.1 | T40: 0.6 | U40: =M40+0.1 -> 2.7 | V40: =V63 -> 2 | W40: =(S40*5900+U40*3400+V40*300+$T$26*R40)/R40 -> 10.757912 | Z40: 1801 | AA40: =S40 -> 0.1 | AB40: 0.6 | AC40: =U40+0.1 -> 2.8 | AD40: =AD63 -> 2.1 | AE40: =(AA40*5900+AC40*3400+AD40*300+$AB$26*Z40)/Z40 -> 11.963354 | AH40: 1801 | AI40: =S40 -> 0.1 | AJ40: 0.6 | AK40: =AC40+0.1 -> 2.9 | AL40: =AL63 -> 2.2 | AM40: =(AI40*5900+AK40*3400+AL40*300+$AJ$26*AH40)/AH40 -> 13.168795 | AP40: 1801 | AQ40: =AI40 -> 0.1 | AR40: 0.6 | AS40: =AK40+0.1 -> 3 | AT40: =AT63 -> 2.3 | AU40: =(AQ40*5900+AS40*3400+AT40*300+$AR$26*AP40)/AP40 -> 14.374237 | AX40: 1801 | AY40: =AQ40 -> 0.1 | AZ40: 0.6 | BA40: =AS40+0.1 -> 3.1 | BB40: =BB63 -> 2.4 | BC40: =(AY40*5900+BA40*3400+BB40*300+$AZ$26*AX40)/AX40 -> 15.579678
A41: 2001~2200份 | B41: 2001 | C41: =K41 -> 0.2 | D41: 0.7 | E41: =E64-0.1 -> 2.7 | F41: =F64 -> 2 | G41: =(C41*5900+E41*3400+F41*300+$D$26*B41)/B41 -> 8.4772614 | J41: 2001 | K41: =S41 -> 0.2 | L41: 0.7 | M41: =E41+0.1 -> 2.8 | N41: =N64 -> 2.1 | O41: =(K41*5900+M41*3400+N41*300+$L$26*J41)/J41 -> 9.6621689 | R41: 2001 | S41: =S64-0.1 -> 0.2 | T41: 0.7 | U41: =M41+0.1 -> 2.9 | V41: =V64 -> 2.2 | W41: =(S41*5900+U41*3400+V41*300+$T$26*R41)/R41 -> 10.847076 | Z41: 2001 | AA41: =S41 -> 0.2 | AB41: 0.7 | AC41: =U41+0.1 -> 3 | AD41: =AD64 -> 2.3 | AE41: =(AA41*5900+AC41*3400+AD41*300+$AB$26*Z41)/Z41 -> 12.031984 | AH41: 2001 | AI41: =S41 -> 0.2 | AJ41: 0.7 | AK41: =AC41+0.1 -> 3.1 | AL41: =AL64 -> 2.4 | AM41: =(AI41*5900+AK41*3400+AL41*300+$AJ$26*AH41)/AH41 -> 13.216892 | AP41: 2001 | AQ41: =AI41 -> 0.2 | AR41: 0.7 | AS41: =AK41+0.1 -> 3.2 | AT41: =AT64 -> 2.5 | AU41: =(AQ41*5900+AS41*3400+AT41*300+$AR$26*AP41)/AP41 -> 14.401799 | AX41: 2001 | AY41: =AQ41 -> 0.2 | AZ41: 0.7 | BA41: =AS41+0.1 -> 3.3 | BB41: =BB64 -> 2.6 | BC41: =(AY41*5900+BA41*3400+BB41*300+$AZ$26*AX41)/AX41 -> 15.586707
A42: 2201~2400份 | B42: 2201 | C42: =K42 -> 0.2 | D42: 0.7 | E42: =E65-0.1 -> 2.9 | F42: =F65 -> 2 | G42: =(C42*5900+E42*3400+F42*300+$D$26*B42)/B42 -> 8.2885052 | J42: 2201 | K42: =S42 -> 0.2 | L42: 0.7 | M42: =E42+0.1 -> 3 | N42: =N65 -> 2.1 | O42: =(K42*5900+M42*3400+N42*300+$L$26*J42)/J42 -> 9.4566106 | R42: 2201 | S42: =S65-0.1 -> 0.2 | T42: 0.7 | U42: =M42+0.1 -> 3.1 | V42: =V65 -> 2.2 | W42: =(S42*5900+U42*3400+V42*300+$T$26*R42)/R42 -> 10.624716 | Z42: 2201 | AA42: =S42 -> 0.2 | AB42: 0.7 | AC42: =U42+0.1 -> 3.2 | AD42: =AD65 -> 2.3 | AE42: =(AA42*5900+AC42*3400+AD42*300+$AB$26*Z42)/Z42 -> 11.792821 | AH42: 2201 | AI42: =S42 -> 0.2 | AJ42: 0.7 | AK42: =AC42+0.1 -> 3.3 | AL42: =AL65 -> 2.4 | AM42: =(AI42*5900+AK42*3400+AL42*300+$AJ$26*AH42)/AH42 -> 12.960927 | AP42: 2201 | AQ42: =AI42 -> 0.2 | AR42: 0.7 | AS42: =AK42+0.1 -> 3.4 | AT42: =AT65 -> 2.5 | AU42: =(AQ42*5900+AS42*3400+AT42*300+$AR$26*AP42)/AP42 -> 14.129032 | AX42: 2201 | AY42: =AQ42 -> 0.2 | AZ42: 0.7 | BA42: =AS42+0.1 -> 3.5 | BB42: =BB65 -> 2.6 | BC42: =(AY42*5900+BA42*3400+BB42*300+$AZ$26*AX42)/AX42 -> 15.297138
A43: 2401~2600份 | B43: 2401 | C43: =K43 -> 0.2 | D43: 0.8 | E43: =E66-0.1 -> 3 | F43: =F66 -> 2 | G43: =(C43*5900+E43*3400+F43*300+$D$26*B43)/B43 -> 7.9895877 | J43: 2401 | K43: =S43 -> 0.2 | L43: 0.8 | M43: =E43+0.1 -> 3.1 | N43: =N66 -> 2.1 | O43: =(K43*5900+M43*3400+N43*300+$L$26*J43)/J43 -> 9.1436901 | R43: 2401 | S43: =S66-0.1 -> 0.2 | T43: 0.8 | U43: =M43+0.1 -> 3.2 | V43: =V66 -> 2.2 | W43: =(S43*5900+U43*3400+V43*300+$T$26*R43)/R43 -> 10.297793 | Z43: 2401 | AA43: =S43 -> 0.2 | AB43: 0.8 | AC43: =U43+0.1 -> 3.3 | AD43: =AD66 -> 2.3 | AE43: =(AA43*5900+AC43*3400+AD43*300+$AB$26*Z43)/Z43 -> 11.451895 | AH43: 2401 | AI43: =S43 -> 0.2 | AJ43: 0.8 | AK43: =AC43+0.1 -> 3.4 | AL43: =AL66 -> 2.4 | AM43: =(AI43*5900+AK43*3400+AL43*300+$AJ$26*AH43)/AH43 -> 12.605998 | AP43: 2401 | AQ43: =AI43 -> 0.2 | AR43: 0.8 | AS43: =AK43+0.1 -> 3.5 | AT43: =AT66 -> 2.5 | AU43: =(AQ43*5900+AS43*3400+AT43*300+$AR$26*AP43)/AP43 -> 13.7601 | AX43: 2401 | AY43: =AQ43 -> 0.2 | AZ43: 0.8 | BA43: =AS43+0.1 -> 3.6 | BB43: =BB66 -> 2.6 | BC43: =(AY43*5900+BA43*3400+BB43*300+$AZ$26*AX43)/AX43 -> 14.914202
A44: 2601~2800份 | B44: 2601 | C44: =K44 -> 0.3 | D44: 0.8 | E44: =E67-0.1 -> 3.1 | F44: =F67 -> 2 | G44: =(C44*5900+E44*3400+F44*300+$D$26*B44)/B44 -> 7.9634756 | J44: 2601 | K44: =S44 -> 0.3 | L44: 0.8 | M44: =E44+0.1 -> 3.2 | N44: =N67 -> 2.1 | O44: =(K44*5900+M44*3400+N44*300+$L$26*J44)/J44 -> 9.1057286 | R44: 2601 | S44: =S67-0.1 -> 0.3 | T44: 0.8 | U44: =M44+0.1 -> 3.3 | V44: =V67 -> 2.2 | W44: =(S44*5900+U44*3400+V44*300+$T$26*R44)/R44 -> 10.247982 | Z44: 2601 | AA44: =S44 -> 0.3 | AB44: 0.8 | AC44: =U44+0.1 -> 3.4 | AD44: =AD67 -> 2.3 | AE44: =(AA44*5900+AC44*3400+AD44*300+$AB$26*Z44)/Z44 -> 11.390235 | AH44: 2601 | AI44: =S44 -> 0.3 | AJ44: 0.8 | AK44: =AC44+0.1 -> 3.5 | AL44: =AL67 -> 2.4 | AM44: =(AI44*5900+AK44*3400+AL44*300+$AJ$26*AH44)/AH44 -> 12.532488 | AP44: 2601 | AQ44: =AI44 -> 0.3 | AR44: 0.8 | AS44: =AK44+0.1 -> 3.6 | AT44: =AT67 -> 2.5 | AU44: =(AQ44*5900+AS44*3400+AT44*300+$AR$26*AP44)/AP44 -> 13.67474 | AX44: 2601 | AY44: =AQ44 -> 0.3 | AZ44: 0.8 | BA44: =AS44+0.1 -> 3.7 | BB44: =BB67 -> 2.6 | BC44: =(AY44*5900+BA44*3400+BB44*300+$AZ$26*AX44)/AX44 -> 14.816993
A45: 2801~3000份 | B45: 2801 | C45: =K45 -> 0.3 | D45: 0.8 | E45: =E68-0.1 -> 3.5 | F45: =F68 -> 2 | G45: =(C45*5900+E45*3400+F45*300+$D$26*B45)/B45 -> 8.0946091 | J45: 2801 | K45: =S45 -> 0.3 | L45: 0.8 | M45: =E45+0.1 -> 3.6 | N45: =N68 -> 2.1 | O45: =(K45*5900+M45*3400+N45*300+$L$26*J45)/J45 -> 9.2267047 | R45: 2801 | S45: 0.3 | T45: 0.8 | U45: =M45+0.1 -> 3.7 | V45: =V68 -> 2.2 | W45: =(S45*5900+U45*3400+V45*300+$T$26*R45)/R45 -> 10.3588 | Z45: 2801 | AA45: =S45 -> 0.3 | AB45: 0.8 | AC45: =U45+0.1 -> 3.8 | AD45: =AD68 -> 2.3 | AE45: =(AA45*5900+AC45*3400+AD45*300+$AB$26*Z45)/Z45 -> 11.490896 | AH45: 2801 | AI45: =S45 -> 0.3 | AJ45: 0.8 | AK45: =AC45+0.1 -> 3.9 | AL45: =AL68 -> 2.4 | AM45: =(AI45*5900+AK45*3400+AL45*300+$AJ$26*AH45)/AH45 -> 12.622992 | AP45: 2801 | AQ45: =AI45 -> 0.3 | AR45: 0.8 | AS45: =AK45+0.1 -> 4 | AT45: =AT68 -> 2.5 | AU45: =(AQ45*5900+AS45*3400+AT45*300+$AR$26*AP45)/AP45 -> 13.755087 | AX45: 2801 | AY45: =AQ45 -> 0.3 | AZ45: 0.8 | BA45: =AS45+0.1 -> 4.1 | BB45: =BB68 -> 2.6 | BC45: =(AY45*5900+BA45*3400+BB45*300+$AZ$26*AX45)/AX45 -> 14.887183
B47: 人群难度 | C47: 三级难度 | J47: 人群难度 | L47: 三级难度 | R47: 人群难度 | T47: 三级难度 | Z47: 人群难度 | AB47: 三级难度 | AH47: 人群难度 | AJ47: 三级难度 | AP47: 人群难度 | AR47: 三级难度 | AX47: 人群难度 | AZ47: 三级难度
B48: 问卷难度 | C48: 20题以内 | J48: 问卷难度 | L48: 21~30题 | R48: 问卷难度 | T48: 31~40题 | W48: 13 | Z48: 问卷难度 | AB48: 41~50题 | AH48: 问卷难度 | AJ48: 51~60 | AP48: 问卷难度 | AR48: 61~70 | AX48: 问卷难度 | AZ48: 71~80
B49: 单价 | D49: 5 | G49: =AVERAGE(G53:G68) -> 13.46597 | J49: 单价 | L49: 6 | O49: =AVERAGE(O53:O68) -> 15.173778 | R49: 单价 | T49: 7 | W49: =AVERAGE(W53:W68) -> 16.834416 | X49: =AVERAGE(X53:X68) -> 11.888836 | Z49: 单价 | AB49: 8 | AE49: =AVERAGE(AE53:AE68) -> 18.495054 | AH49: 单价 | AJ49: 9 | AM49: =AVERAGE(AM53:AM68) -> 20.155692 | AP49: 单价 | AR49: 10 | AU49: =AVERAGE(AU53:AU68) -> 21.81633 | AX49: 单价 | AZ49: 11 | BC49: =AVERAGE(BC53:BC68) -> 23.476968 | BE49: =AVERAGE(BC49,AU49,AM49,AE49,W49,O49,G49) -> 18.488315 | BF49: =BE49-AVERAGE(AZ49,AR49,AJ49,AB49,T49,L49,D49) -> 10.488315
B50: 份数 | C50: P5 | D50: P4 | E50: P3 | F50: 实习生 | G50: 成本 | H50: 上限 | J50: 份数 | K50: P5 | L50: P4 | M50: P3 | N50: 实习生 | R50: 份数 | S50: P5 | T50: P4 | U50: P3 | V50: 实习生 | W50: 成本 | Z50: 份数 | AA50: P5 | AB50: P4 | AC50: P3 | AD50: 实习生 | AH50: 份数 | AI50: P5 | AJ50: P4 | AK50: P3 | AL50: 实习生 | AP50: 份数 | AQ50: P5 | AR50: P4 | AS50: P3 | AT50: 实习生 | AX50: 份数 | AY50: P5 | AZ50: P4 | BA50: P3 | BB50: 实习生
B51: 0 | C51: =K51 -> 0 | D51: 0 | E51: 0 | F51: 0 | G51: =(C51*7200+E51*3100+F51*300+B51*$D$49)/B51 -> #DIV/0! | J51: 0 | K51: =S51 -> 0 | L51: 0 | M51: 0 | N51: 0 | O51: =(K51*7200+M51*3100+N51*300+J51*$L$49)/J51 -> #DIV/0! | R51: 0 | S51: 0 | T51: 0 | U51: 0 | V51: 0 | Z51: 0 | AA51: =S51 -> 0 | AB51: =T51*1.02 -> 0 | AC51: =U51+0.1 -> 0.1 | AD51: =V51+0.1 -> 0.1 | AH51: 0 | AI51: =S51 -> 0 | AJ51: 0 | AK51: =AC51+0.1 -> 0.2 | AL51: =AD51+0.1 -> 0.2 | AM51: =(AI51*7200+AK51*3100+AL51*300+AH51*$AJ$49)/AH51 -> #DIV/0! | AP51: 0 | AQ51: =S51 -> 0 | AR51: 0 | AS51: =AK51+0.1 -> 0.3 | AT51: =AL51+0.1 -> 0.3 | AU51: =(AQ51*7200+AS51*3100+AT51*300+AP51*$AR$49)/AP51 -> #DIV/0! | AX51: 0 | AY51: =S51 -> 0 | AZ51: 0 | BA51: =AS51+0.1 -> 0.4 | BB51: =AT51+0.1 -> 0.4 | BC51: =(AY51*5900+BA51*3400+BB51*300+AX51*$AZ$49)/AX51 -> #DIV/0!
A52: 100份及以下 | B52: 1 | C52: 0 | D52: 0.2 | E52: 0.5 | F52: 0.6 | G52: =(C52*5900+E52*3400+F52*300+$D$49*B52)/B52 -> 1885 | J52: 1 | K52: =K53 -> 0 | L52: =L53 -> 0.2 | M52: =M53 -> 0.6 | N52: 0.7 | O52: =(K52*5900+M52*3400+N52*300+J52*$L$49)/J52 -> 2256 | R52: 1 | S52: =S53 -> 0 | T52: =T53 -> 1 | U52: =U53 -> 0.7 | V52: 0.8 | W52: =(S52*5900+U52*3400+V52*300+$T$49*R52)/R52 -> 2627 | Z52: 1 | AA52: =S52 -> 0 | AB52: =T52*1.02 -> 1.02 | AC52: =U52+0.1 -> 0.8 | AD52: =V52+0.1 -> 0.9 | AE52: =(AA52*5900+AC52*3400+AD52*300+Z52*$AB$49)/Z52 -> 2998 | AH52: 1 | AI52: =S52 -> 0 | AJ52: 1.222 | AK52: 0.9 | AL52: 1 | AM52: =(AI52*5900+AK52*3400+AL52*300+$AJ$49*AH52)/AH52 -> 3369 | AP52: 1 | AQ52: =S52 -> 0 | AR52: 1.322 | AS52: 1 | AT52: 1.1 | AU52: =(AQ52*5900+AS52*3400+AT52*300+$AR$49*AP52)/AP52 -> 3740 | AX52: 1 | AY52: =S52 -> 0 | AZ52: 1.322 | BA52: 1.1 | BB52: 1.2 | BC52: =(AY52*5900+BA52*3400+BB52*300+$AZ$49*AX52)/AX52 -> 4111
A53: 101~200份 | B53: 101 | C53: =K53 -> 0 | D53: 0.2 | E53: =U53-0.2 -> 0.5 | F53: =N53-0.1 -> 0.6 | G53: =(C53*5900+E53*3400+F53*300+$D$49*B53)/B53 -> 23.613861 | J53: 101 | K53: =S53 -> 0 | L53: 0.2 | M53: =U53-0.1 -> 0.6 | N53: =V53-0.1 -> 0.7 | O53: =(K53*5900+M53*3400+N53*300+J53*$L$49)/J53 -> 28.277228 | R53: 101 | S53: 0 | T53: 1 | U53: 0.7 | V53: 0.8 | W53: =(S53*5900+U53*3400+V53*300+$T$49*R53)/R53 -> 32.940594 | X53: =(S53*5900+U53*3400+V53*1200)/R53 -> 33.069307 | Z53: 101 | AA53: =S53 -> 0 | AB53: =T53*1.02 -> 1.02 | AC53: =U53+0.1 -> 0.8 | AD53: =V53+0.1 -> 0.9 | AE53: =(AA53*5900+AC53*3400+AD53*300+Z53*$AB$49)/Z53 -> 37.60396 | AH53: 101 | AI53: =S53 -> 0 | AJ53: =AB53+0.1 -> 1.12 | AK53: =AC53+0.1 -> 0.9 | AL53: =AD53+0.1 -> 1 | AM53: =(AI53*5900+AK53*3400+AL53*300+$AJ$49*AH53)/AH53 -> 42.267327 | AP53: 101 | AQ53: =S53 -> 0 | AR53: =AJ53+0.1 -> 1.22 | AS53: =AK53+0.1 -> 1 | AT53: =AL53+0.1 -> 1.1 | AU53: =(AQ53*5900+AS53*3400+AT53*300+$AR$49*AP53)/AP53 -> 46.930693 | AX53: 101 | AY53: =S53 -> 0 | AZ53: =AR53 -> 1.22 | BA53: =AS53+0.1 -> 1.1 | BB53: =AT53+0.1 -> 1.2 | BC53: =(AY53*5900+BA53*3400+BB53*300+$AZ$49*AX53)/AX53 -> 51.594059
A54: 201~300份 | B54: 201 | C54: =K54 -> 0 | D54: 0.2 | E54: =U54-0.2 -> 0.8 | F54: =N54-0.1 -> 1 | G54: =(C54*5900+E54*3400+F54*300+$D$49*B54)/B54 -> 20.024876 | J54: 201 | K54: =S54 -> 0 | L54: 0.2 | M54: =U54-0.1 -> 0.9 | N54: =V54-0.1 -> 1.1 | O54: =(K54*5900+M54*3400+N54*300+J54*$L$49)/J54 -> 22.865672 | R54: 201 | S54: 0 | T54: 1.3 | U54: 1 | V54: 1.2 | W54: =(S54*5900+U54*3400+V54*300+$T$49*R54)/R54 -> 25.706468 | X54: =(S54*5900+U54*3400+V54*1200)/R54 -> 24.079602 | Z54: 201 | AA54: =S54 -> 0 | AB54: =T54*1.02 -> 1.326 | AC54: =U54+0.1 -> 1.1 | AD54: =V54+0.1 -> 1.3 | AE54: =(AA54*5900+AC54*3400+AD54*300+Z54*$AB$49)/Z54 -> 28.547264 | AH54: 201 | AI54: =S54 -> 0 | AJ54: =AB54+0.1 -> 1.426 | AK54: =AC54+0.1 -> 1.2 | AL54: =AD54+0.1 -> 1.4 | AM54: =(AI54*5900+AK54*3400+AL54*300+$AJ$49*AH54)/AH54 -> 31.38806 | AP54: 201 | AQ54: =S54 -> 0 | AR54: =AJ54+0.1 -> 1.526 | AS54: =AK54+0.1 -> 1.3 | AT54: =AL54+0.1 -> 1.5 | AU54: =(AQ54*5900+AS54*3400+AT54*300+$AR$49*AP54)/AP54 -> 34.228856 | AX54: 201 | AY54: =S54 -> 0 | AZ54: =AR54 -> 1.526 | BA54: =AS54+0.1 -> 1.4 | BB54: =AT54+0.1 -> 1.6 | BC54: =(AY54*5900+BA54*3400+BB54*300+$AZ$49*AX54)/AX54 -> 37.069652
A55: 301~500份 | B55: 301 | C55: =K55 -> 0 | D55: 0.2 | E55: =U55-0.2 -> 1 | F55: =N55-0.1 -> 1.1 | G55: =(C55*5900+E55*3400+F55*300+$D$49*B55)/B55 -> 17.392027 | J55: 301 | K55: =S55 -> 0 | L55: 0.2 | M55: =U55-0.1 -> 1.1 | N55: =V55-0.1 -> 1.2 | O55: =(K55*5900+M55*3400+N55*300+J55*$L$49)/J55 -> 19.621262 | R55: 301 | S55: 0 | T55: 1.5 | U55: 1.2 | V55: 1.3 | W55: =(S55*5900+U55*3400+V55*300+$T$49*R55)/R55 -> 21.850498 | X55: =(S55*5900+U55*3400+V55*1200)/R55 -> 18.737542 | Z55: 301 | AA55: =S55 -> 0 | AB55: =T55*1.02 -> 1.53 | AC55: =U55+0.1 -> 1.3 | AD55: =V55+0.1 -> 1.4 | AE55: =(AA55*5900+AC55*3400+AD55*300+Z55*$AB$49)/Z55 -> 24.079734 | AH55: 301 | AI55: =S55 -> 0 | AJ55: =AB55+0.1 -> 1.63 | AK55: =AC55+0.1 -> 1.4 | AL55: =AD55+0.1 -> 1.5 | AM55: =(AI55*5900+AK55*3400+AL55*300+$AJ$49*AH55)/AH55 -> 26.30897 | AP55: 301 | AQ55: =S55 -> 0 | AR55: =AJ55+0.1 -> 1.73 | AS55: =AK55+0.1 -> 1.5 | AT55: =AL55+0.1 -> 1.6 | AU55: =(AQ55*5900+AS55*3400+AT55*300+$AR$49*AP55)/AP55 -> 28.538206 | AX55: 301 | AY55: =S55 -> 0 | AZ55: =AR55 -> 1.73 | BA55: =AS55+0.1 -> 1.6 | BB55: =AT55+0.1 -> 1.7 | BC55: =(AY55*5900+BA55*3400+BB55*300+$AZ$49*AX55)/AX55 -> 30.767442
A56: 501~700份 | B56: 501 | C56: =K56 -> 0.1 | D56: 0.3 | E56: =U56-0.2 -> 1.3 | F56: =N56-0.1 -> 1.2 | G56: =(C56*5900+E56*3400+F56*300+$D$49*B56)/B56 -> 15.718563 | J56: 501 | K56: =S56 -> 0.1 | L56: 0.3 | M56: =U56-0.1 -> 1.4 | N56: =V56-0.1 -> 1.3 | O56: =(K56*5900+M56*3400+N56*300+J56*$L$49)/J56 -> 17.457086 | R56: 501 | S56: 0.1 | T56: 1.8 | U56: 1.5 | V56: 1.4 | W56: =(S56*5900+U56*3400+V56*300+$T$49*R56)/R56 -> 19.195609 | X56: =(S56*5900+U56*3400+V56*1200)/R56 -> 14.710579 | Z56: 501 | AA56: =S56 -> 0.1 | AB56: =T56*1.02 -> 1.836 | AC56: =U56+0.1 -> 1.6 | AD56: =V56+0.1 -> 1.5 | AE56: =(AA56*5900+AC56*3400+AD56*300+Z56*$AB$49)/Z56 -> 20.934132 | AH56: 501 | AI56: =S56 -> 0.1 | AJ56: =AB56+0.1 -> 1.936 | AK56: =AC56+0.1 -> 1.7 | AL56: =AD56+0.1 -> 1.6 | AM56: =(AI56*5900+AK56*3400+AL56*300+$AJ$49*AH56)/AH56 -> 22.672655 | AP56: 501 | AQ56: =S56 -> 0.1 | AR56: =AJ56+0.1 -> 2.036 | AS56: =AK56+0.1 -> 1.8 | AT56: =AL56+0.1 -> 1.7 | AU56: =(AQ56*5900+AS56*3400+AT56*300+$AR$49*AP56)/AP56 -> 24.411178 | AX56: 501 | AY56: =S56 -> 0.1 | AZ56: =AR56 -> 2.036 | BA56: =AS56+0.1 -> 1.9 | BB56: =AT56+0.1 -> 1.8 | BC56: =(AY56*5900+BA56*3400+BB56*300+$AZ$49*AX56)/AX56 -> 26.149701
A57: 701~900份 | B57: 701 | C57: =K57 -> 0.1 | D57: 0.3 | E57: =U57-0.2 -> 1.5 | F57: =N57-0.1 -> 1.3 | G57: =(C57*5900+E57*3400+F57*300+$D$49*B57)/B57 -> 13.673324 | J57: 701 | K57: =S57 -> 0.1 | L57: 0.3 | M57: =U57-0.1 -> 1.6 | N57: =V57-0.1 -> 1.4 | O57: =(K57*5900+M57*3400+N57*300+J57*$L$49)/J57 -> 15.201141 | R57: 701 | S57: 0.1 | T57: 2 | U57: 1.7 | V57: 1.5 | W57: =(S57*5900+U57*3400+V57*300+$T$49*R57)/R57 -> 16.728959 | X57: =(S57*5900+U57*3400+V57*1200)/R57 -> 11.654779 | Z57: 701 | AA57: =S57 -> 0.1 | AB57: =T57*1.02 -> 2.04 | AC57: =U57+0.1 -> 1.8 | AD57: =V57+0.1 -> 1.6 | AE57: =(AA57*5900+AC57*3400+AD57*300+Z57*$AB$49)/Z57 -> 18.256776 | AH57: 701 | AI57: =S57 -> 0.1 | AJ57: =AB57+0.1 -> 2.14 | AK57: =AC57+0.1 -> 1.9 | AL57: =AD57+0.1 -> 1.7 | AM57: =(AI57*5900+AK57*3400+AL57*300+$AJ$49*AH57)/AH57 -> 19.784593 | AP57: 701 | AQ57: =S57 -> 0.1 | AR57: =AJ57+0.1 -> 2.24 | AS57: =AK57+0.1 -> 2 | AT57: =AL57+0.1 -> 1.8 | AU57: =(AQ57*5900+AS57*3400+AT57*300+$AR$49*AP57)/AP57 -> 21.312411 | AX57: 701 | AY57: =S57 -> 0.1 | AZ57: =AR57 -> 2.24 | BA57: =AS57+0.1 -> 2.1 | BB57: =AT57+0.1 -> 1.9 | BC57: =(AY57*5900+BA57*3400+BB57*300+$AZ$49*AX57)/AX57 -> 22.840228
A58: 901~1000份 | B58: 901 | C58: =K58 -> 0.1 | D58: 0.4 | E58: 1.8 | F58: =N58-0.1 -> 1.3 | G58: =(C58*5900+E58*3400+F58*300+$D$49*B58)/B58 -> 12.880133 | J58: 901 | K58: =S58 -> 0.1 | L58: 0.4 | M58: 2.1 | N58: =V58-0.1 -> 1.4 | O58: =(K58*5900+M58*3400+N58*300+J58*$L$49)/J58 -> 15.045505 | R58: 901 | S58: 0.1 | T58: 2.1 | U58: 2.2 | V58: 1.5 | W58: =(S58*5900+U58*3400+V58*300+$T$49*R58)/R58 -> 16.45616 | X58: =(S58*5900+U58*3400+V58*1200)/R58 -> 10.954495 | Z58: 901 | AA58: =S58 -> 0.1 | AB58: =T58*1.02 -> 2.142 | AC58: =U58+0.1 -> 2.3 | AD58: =V58+0.1 -> 1.6 | AE58: =(AA58*5900+AC58*3400+AD58*300+Z58*$AB$49)/Z58 -> 17.866815 | AH58: 901 | AI58: =S58 -> 0.1 | AJ58: =AB58+0.1 -> 2.242 | AK58: =AC58+0.1 -> 2.4 | AL58: =AD58+0.1 -> 1.7 | AM58: =(AI58*5900+AK58*3400+AL58*300+$AJ$49*AH58)/AH58 -> 19.277469 | AP58: 901 | AQ58: =S58 -> 0.1 | AR58: =AJ58+0.1 -> 2.342 | AS58: =AK58+0.1 -> 2.5 | AT58: =AL58+0.1 -> 1.8 | AU58: =(AQ58*5900+AS58*3400+AT58*300+$AR$49*AP58)/AP58 -> 20.688124 | AX58: 901 | AY58: =S58 -> 0.1 | AZ58: =AR58 -> 2.342 | BA58: =AS58+0.1 -> 2.6 | BB58: =AT58+0.1 -> 1.9 | BC58: =(AY58*5900+BA58*3400+BB58*300+$AZ$49*AX58)/AX58 -> 22.098779
A59: 1001~1200份 | B59: 1001 | C59: =K59 -> 0.2 | D59: 0.4 | E59: 2 | F59: =N59-0.1 -> 1.5 | G59: =(C59*5900+E59*3400+F59*300+$D$49*B59)/B59 -> 13.421578 | J59: 1001 | K59: =S59 -> 0.2 | L59: 0.4 | M59: =U59-0.1 -> 2.1 | N59: =V59-0.1 -> 1.6 | O59: =(K59*5900+M59*3400+N59*300+J59*$L$49)/J59 -> 14.791209 | R59: 1001 | S59: 0.2 | T59: 2.3 | U59: 2.2 | V59: 1.7 | W59: =(S59*5900+U59*3400+V59*300+$T$49*R59)/R59 -> 16.160839 | X59: =(S59*5900+U59*3400+V59*1200)/R59 -> 10.689311 | Z59: 1001 | AA59: =S59 -> 0.2 | AB59: =T59*1.02 -> 2.346 | AC59: =U59+0.1 -> 2.3 | AD59: =V59+0.1 -> 1.8 | AE59: =(AA59*5900+AC59*3400+AD59*300+Z59*$AB$49)/Z59 -> 17.53047 | AH59: 1001 | AI59: =S59 -> 0.2 | AJ59: =AB59+0.1 -> 2.446 | AK59: =AC59+0.1 -> 2.4 | AL59: =AD59+0.1 -> 1.9 | AM59: =(AI59*5900+AK59*3400+AL59*300+$AJ$49*AH59)/AH59 -> 18.9001 | AP59: 1001 | AQ59: =S59 -> 0.2 | AR59: =AJ59+0.1 -> 2.546 | AS59: =AK59+0.1 -> 2.5 | AT59: =AL59+0.1 -> 2 | AU59: =(AQ59*5900+AS59*3400+AT59*300+$AR$49*AP59)/AP59 -> 20.26973 | AX59: 1001 | AY59: =S59 -> 0.2 | AZ59: =AR59 -> 2.546 | BA59: =AS59+0.1 -> 2.6 | BB59: =AT59+0.1 -> 2.1 | BC59: =(AY59*5900+BA59*3400+BB59*300+$AZ$49*AX59)/AX59 -> 21.639361
A60: 1201~1400份 | B60: 1201 | C60: =K60 -> 0.2 | D60: 0.5 | E60: =U60-0.2 -> 2.1 | F60: =N60-0.1 -> 1.7 | G60: =(C60*5900+E60*3400+F60*300+$D$49*B60)/B60 -> 12.352206 | J60: 1201 | K60: =S60 -> 0.2 | L60: 0.5 | M60: =U60-0.1 -> 2.2 | N60: =V60-0.1 -> 1.8 | O60: =(K60*5900+M60*3400+N60*300+J60*$L$49)/J60 -> 13.660283 | R60: 1201 | S60: 0.2 | T60: 2.4 | U60: 2.3 | V60: 1.9 | W60: =(S60*5900+U60*3400+V60*300+$T$49*R60)/R60 -> 14.96836 | X60: =(S60*5900+U60*3400+V60*1200)/R60 -> 9.3921732 | Z60: 1201 | AA60: =S60 -> 0.2 | AB60: =T60*1.02 -> 2.448 | AC60: =U60+0.1 -> 2.4 | AD60: =V60+0.1 -> 2 | AE60: =(AA60*5900+AC60*3400+AD60*300+Z60*$AB$49)/Z60 -> 16.276436 | AH60: 1201 | AI60: =S60 -> 0.2 | AJ60: =AB60+0.1 -> 2.548 | AK60: =AC60+0.1 -> 2.5 | AL60: =AD60+0.1 -> 2.1 | AM60: =(AI60*5900+AK60*3400+AL60*300+$AJ$49*AH60)/AH60 -> 17.584513 | AP60: 1201 | AQ60: =S60 -> 0.2 | AR60: =AJ60+0.1 -> 2.648 | AS60: =AK60+0.1 -> 2.6 | AT60: =AL60+0.1 -> 2.2 | AU60: =(AQ60*5900+AS60*3400+AT60*300+$AR$49*AP60)/AP60 -> 18.89259 | AX60: 1201 | AY60: =S60 -> 0.2 | AZ60: =AR60 -> 2.648 | BA60: =AS60+0.1 -> 2.7 | BB60: =AT60+0.1 -> 2.3 | BC60: =(AY60*5900+BA60*3400+BB60*300+$AZ$49*AX60)/AX60 -> 20.200666
A61: 1401~1600份 | B61: 1401 | C61: =K61 -> 0.2 | D61: 0.5 | E61: =U61-0.2 -> 2.2 | F61: =N61-0.1 -> 1.8 | G61: =(C61*5900+E61*3400+F61*300+$D$49*B61)/B61 -> 11.566738 | J61: 1401 | K61: =S61 -> 0.2 | L61: 0.5 | M61: =U61-0.1 -> 2.3 | N61: =V61-0.1 -> 1.9 | O61: =(K61*5900+M61*3400+N61*300+J61*$L$49)/J61 -> 12.830835 | R61: 1401 | S61: 0.2 | T61: 3 | U61: 2.4 | V61: 2 | W61: =(S61*5900+U61*3400+V61*300+$T$49*R61)/R61 -> 14.094932 | X61: =(S61*5900+U61*3400+V61*1200)/R61 -> 8.3797288 | Z61: 1401 | AA61: =S61 -> 0.2 | AB61: =T61*1.02 -> 3.06 | AC61: =U61+0.1 -> 2.5 | AD61: =V61+0.1 -> 2.1 | AE61: =(AA61*5900+AC61*3400+AD61*300+Z61*$AB$49)/Z61 -> 15.359029 | AH61: 1401 | AI61: =S61 -> 0.2 | AJ61: =AB61+0.1 -> 3.16 | AK61: =AC61+0.1 -> 2.6 | AL61: =AD61+0.1 -> 2.2 | AM61: =(AI61*5900+AK61*3400+AL61*300+$AJ$49*AH61)/AH61 -> 16.623126 | AP61: 1401 | AQ61: =S61 -> 0.2 | AR61: =AJ61+0.1 -> 3.26 | AS61: =AK61+0.1 -> 2.7 | AT61: =AL61+0.1 -> 2.3 | AU61: =(AQ61*5900+AS61*3400+AT61*300+$AR$49*AP61)/AP61 -> 17.887223 | AX61: 1401 | AY61: =S61 -> 0.2 | AZ61: =AR61 -> 3.26 | BA61: =AS61+0.1 -> 2.8 | BB61: =AT61+0.1 -> 2.4 | BC61: =(AY61*5900+BA61*3400+BB61*300+$AZ$49*AX61)/AX61 -> 19.15132
A62: 1601~1800份 | B62: 1601 | C62: =K62 -> 0.2 | D62: 0.6 | E62: =U62-0.2 -> 2.4 | F62: =N62-0.1 -> 1.8 | G62: =(C62*5900+E62*3400+F62*300+$D$49*B62)/B62 -> 11.171143 | J62: 1601 | K62: =S62 -> 0.2 | L62: 0.6 | M62: =U62-0.1 -> 2.5 | N62: =V62-0.1 -> 1.9 | O62: =(K62*5900+M62*3400+N62*300+J62*$L$49)/J62 -> 12.402249 | R62: 1601 | S62: 0.2 | T62: 3.19 | U62: 2.6 | V62: 2 | W62: =(S62*5900+U62*3400+V62*300+$T$49*R62)/R62 -> 13.633354 | X62: =(S62*5900+U62*3400+V62*1200)/R62 -> 7.7576515 | Z62: 1601 | AA62: =S62 -> 0.2 | AB62: =T62*1.02 -> 3.2538 | AC62: =U62+0.1 -> 2.7 | AD62: =V62+0.1 -> 2.1 | AE62: =(AA62*5900+AC62*3400+AD62*300+Z62*$AB$49)/Z62 -> 14.86446 | AH62: 1601 | AI62: =S62 -> 0.2 | AJ62: =AB62+0.1 -> 3.3538 | AK62: =AC62+0.1 -> 2.8 | AL62: =AD62+0.1 -> 2.2 | AM62: =(AI62*5900+AK62*3400+AL62*300+$AJ$49*AH62)/AH62 -> 16.095565 | AP62: 1601 | AQ62: =S62 -> 0.2 | AR62: =AJ62+0.1 -> 3.4538 | AS62: =AK62+0.1 -> 2.9 | AT62: =AL62+0.1 -> 2.3 | AU62: =(AQ62*5900+AS62*3400+AT62*300+$AR$49*AP62)/AP62 -> 17.326671 | AX62: 1601 | AY62: =S62 -> 0.2 | AZ62: =AR62 -> 3.4538 | BA62: =AS62+0.1 -> 3 | BB62: =AT62+0.1 -> 2.4 | BC62: =(AY62*5900+BA62*3400+BB62*300+$AZ$49*AX62)/AX62 -> 18.557776
A63: 1801~2000份 | B63: 1801 | C63: =K63 -> 0.2 | D63: 0.6 | E63: =U63-0.2 -> 2.6 | F63: =N63-0.1 -> 1.8 | G63: =(C63*5900+E63*3400+F63*300+$D$49*B63)/B63 -> 10.863409 | J63: 1801 | K63: =S63 -> 0.2 | L63: 0.6 | M63: =U63-0.1 -> 2.7 | N63: =V63-0.1 -> 1.9 | O63: =(K63*5900+M63*3400+N63*300+J63*$L$49)/J63 -> 12.068851 | R63: 1801 | S63: 0.2 | T63: 3.52 | U63: 2.8 | V63: 2 | W63: =(S63*5900+U63*3400+V63*300+$T$49*R63)/R63 -> 13.274292 | X63: =(S63*5900+U63*3400+V63*1200)/R63 -> 7.2737368 | Z63: 1801 | AA63: =S63 -> 0.2 | AB63: =T63*1.02 -> 3.5904 | AC63: =U63+0.1 -> 2.9 | AD63: =V63+0.1 -> 2.1 | AE63: =(AA63*5900+AC63*3400+AD63*300+Z63*$AB$49)/Z63 -> 14.479733 | AH63: 1801 | AI63: =S63 -> 0.2 | AJ63: =AB63+0.1 -> 3.6904 | AK63: =AC63+0.1 -> 3 | AL63: =AD63+0.1 -> 2.2 | AM63: =(AI63*5900+AK63*3400+AL63*300+$AJ$49*AH63)/AH63 -> 15.685175 | AP63: 1801 | AQ63: =S63 -> 0.2 | AR63: =AJ63+0.1 -> 3.7904 | AS63: =AK63+0.1 -> 3.1 | AT63: =AL63+0.1 -> 2.3 | AU63: =(AQ63*5900+AS63*3400+AT63*300+$AR$49*AP63)/AP63 -> 16.890616 | AX63: 1801 | AY63: =S63 -> 0.2 | AZ63: =AR63 -> 3.7904 | BA63: =AS63+0.1 -> 3.2 | BB63: =AT63+0.1 -> 2.4 | BC63: =(AY63*5900+BA63*3400+BB63*300+$AZ$49*AX63)/AX63 -> 18.096058
A64: 2001~2200份 | B64: 2001 | C64: =K64 -> 0.3 | D64: 0.7 | E64: =U64-0.2 -> 2.8 | F64: =N64-0.1 -> 2 | G64: =(C64*5900+E64*3400+F64*300+$D$49*B64)/B64 -> 10.942029 | J64: 2001 | K64: =S64 -> 0.3 | L64: 0.7 | M64: =U64-0.1 -> 2.9 | N64: =V64-0.1 -> 2.1 | O64: =(K64*5900+M64*3400+N64*300+J64*$L$49)/J64 -> 12.126937 | R64: 2001 | S64: 0.3 | T64: 3.74 | U64: 3 | V64: 2.2 | W64: =(S64*5900+U64*3400+V64*300+$T$49*R64)/R64 -> 13.311844 | X64: =(S64*5900+U64*3400+V64*1200)/R64 -> 7.3013493 | Z64: 2001 | AA64: =S64 -> 0.3 | AB64: =T64*1.02 -> 3.8148 | AC64: =U64+0.1 -> 3.1 | AD64: =V64+0.1 -> 2.3 | AE64: =(AA64*5900+AC64*3400+AD64*300+Z64*$AB$49)/Z64 -> 14.496752 | AH64: 2001 | AI64: =S64 -> 0.3 | AJ64: =AB64+0.1 -> 3.9148 | AK64: =AC64+0.1 -> 3.2 | AL64: =AD64+0.1 -> 2.4 | AM64: =(AI64*5900+AK64*3400+AL64*300+$AJ$49*AH64)/AH64 -> 15.681659 | AP64: 2001 | AQ64: =S64 -> 0.3 | AR64: =AJ64+0.1 -> 4.0148 | AS64: =AK64+0.1 -> 3.3 | AT64: =AL64+0.1 -> 2.5 | AU64: =(AQ64*5900+AS64*3400+AT64*300+$AR$49*AP64)/AP64 -> 16.866567 | AX64: 2001 | AY64: =S64 -> 0.3 | AZ64: =AR64 -> 4.0148 | BA64: =AS64+0.1 -> 3.4 | BB64: =AT64+0.1 -> 2.6 | BC64: =(AY64*5900+BA64*3400+BB64*300+$AZ$49*AX64)/AX64 -> 18.051474
A65: 2201~2400份 | B65: 2201 | C65: =K65 -> 0.3 | D65: 0.7 | E65: =U65-0.2 -> 3 | F65: =N65-0.1 -> 2 | G65: =(C65*5900+E65*3400+F65*300+$D$49*B65)/B65 -> 10.71104 | J65: 2201 | K65: =S65 -> 0.3 | L65: 0.7 | M65: =U65-0.1 -> 3.1 | N65: =V65-0.1 -> 2.1 | O65: =(K65*5900+M65*3400+N65*300+J65*$L$49)/J65 -> 11.879146 | R65: 2201 | S65: 0.3 | T65: 4.07 | U65: 3.2 | V65: 2.2 | W65: =(S65*5900+U65*3400+V65*300+$T$49*R65)/R65 -> 13.047251 | X65: =(S65*5900+U65*3400+V65*1200)/R65 -> 6.9468423 | Z65: 2201 | AA65: =S65 -> 0.3 | AB65: =T65*1.02 -> 4.1514 | AC65: =U65+0.1 -> 3.3 | AD65: =V65+0.1 -> 2.3 | AE65: =(AA65*5900+AC65*3400+AD65*300+Z65*$AB$49)/Z65 -> 14.215357 | AH65: 2201 | AI65: =S65 -> 0.3 | AJ65: =AB65+0.1 -> 4.2514 | AK65: =AC65+0.1 -> 3.4 | AL65: =AD65+0.1 -> 2.4 | AM65: =(AI65*5900+AK65*3400+AL65*300+$AJ$49*AH65)/AH65 -> 15.383462 | AP65: 2201 | AQ65: =S65 -> 0.3 | AR65: =AJ65+0.1 -> 4.3514 | AS65: =AK65+0.1 -> 3.5 | AT65: =AL65+0.1 -> 2.5 | AU65: =(AQ65*5900+AS65*3400+AT65*300+$AR$49*AP65)/AP65 -> 16.551567 | AX65: 2201 | AY65: =S65 -> 0.3 | AZ65: =AR65 -> 4.3514 | BA65: =AS65+0.1 -> 3.6 | BB65: =AT65+0.1 -> 2.6 | BC65: =(AY65*5900+BA65*3400+BB65*300+$AZ$49*AX65)/AX65 -> 17.719673
A66: 2401~2600份 | B66: 2401 | C66: =K66 -> 0.3 | D66: 0.8 | E66: =U66-0.2 -> 3.1 | F66: =N66-0.1 -> 2 | G66: =(C66*5900+E66*3400+F66*300+$D$49*B66)/B66 -> 10.376926 | J66: 2401 | K66: =S66 -> 0.3 | L66: 0.8 | M66: =U66-0.1 -> 3.2 | N66: =V66-0.1 -> 2.1 | O66: =(K66*5900+M66*3400+N66*300+J66*$L$49)/J66 -> 11.531029 | R66: 2401 | S66: 0.3 | T66: 4.29 | U66: 3.3 | V66: 2.2 | W66: =(S66*5900+U66*3400+V66*300+$T$49*R66)/R66 -> 12.685131 | X66: =(S66*5900+U66*3400+V66*1200)/R66 -> 6.5097876 | Z66: 2401 | AA66: =S66 -> 0.3 | AB66: =T66*1.02 -> 4.3758 | AC66: =U66+0.1 -> 3.4 | AD66: =V66+0.1 -> 2.3 | AE66: =(AA66*5900+AC66*3400+AD66*300+Z66*$AB$49)/Z66 -> 13.839234 | AH66: 2401 | AI66: =S66 -> 0.3 | AJ66: =AB66+0.1 -> 4.4758 | AK66: =AC66+0.1 -> 3.5 | AL66: =AD66+0.1 -> 2.4 | AM66: =(AI66*5900+AK66*3400+AL66*300+$AJ$49*AH66)/AH66 -> 14.993336 | AP66: 2401 | AQ66: =S66 -> 0.3 | AR66: =AJ66+0.1 -> 4.5758 | AS66: =AK66+0.1 -> 3.6 | AT66: =AL66+0.1 -> 2.5 | AU66: =(AQ66*5900+AS66*3400+AT66*300+$AR$49*AP66)/AP66 -> 16.147439 | AX66: 2401 | AY66: =S66 -> 0.3 | AZ66: =AR66 -> 4.5758 | BA66: =AS66+0.1 -> 3.7 | BB66: =AT66+0.1 -> 2.6 | BC66: =(AY66*5900+BA66*3400+BB66*300+$AZ$49*AX66)/AX66 -> 17.301541
A67: 2601~2800份 | B67: 2601 | C67: =K67 -> 0.4 | D67: 0.8 | E67: =U67-0.2 -> 3.2 | F67: =N67-0.1 -> 2 | G67: =(C67*5900+E67*3400+F67*300+$D$49*B67)/B67 -> 10.32103 | J67: 2601 | K67: =S67 -> 0.4 | L67: 0.8 | M67: =U67-0.1 -> 3.3 | N67: =V67-0.1 -> 2.1 | O67: =(K67*5900+M67*3400+N67*300+J67*$L$49)/J67 -> 11.463283 | R67: 2601 | S67: 0.4 | T67: 4.51 | U67: 3.4 | V67: 2.2 | W67: =(S67*5900+U67*3400+V67*300+$T$49*R67)/R67 -> 12.605536 | X67: =(S67*5900+U67*3400+V67*1200)/R67 -> 6.366782 | Z67: 2601 | AA67: =S67 -> 0.4 | AB67: =T67*1.02 -> 4.6002 | AC67: =U67+0.1 -> 3.5 | AD67: =V67+0.1 -> 2.3 | AE67: =(AA67*5900+AC67*3400+AD67*300+Z67*$AB$49)/Z67 -> 13.747789 | AH67: 2601 | AI67: =S67 -> 0.4 | AJ67: =AB67+0.1 -> 4.7002 | AK67: =AC67+0.1 -> 3.6 | AL67: =AD67+0.1 -> 2.4 | AM67: =(AI67*5900+AK67*3400+AL67*300+$AJ$49*AH67)/AH67 -> 14.890042 | AP67: 2601 | AQ67: =S67 -> 0.4 | AR67: =AJ67+0.1 -> 4.8002 | AS67: =AK67+0.1 -> 3.7 | AT67: =AL67+0.1 -> 2.5 | AU67: =(AQ67*5900+AS67*3400+AT67*300+$AR$49*AP67)/AP67 -> 16.032295 | AX67: 2601 | AY67: =S67 -> 0.4 | AZ67: =AR67 -> 4.8002 | BA67: =AS67+0.1 -> 3.8 | BB67: =AT67+0.1 -> 2.6 | BC67: =(AY67*5900+BA67*3400+BB67*300+$AZ$49*AX67)/AX67 -> 17.174548
A68: 2801~3000份 | B68: 2801 | C68: =K68 -> 0.4 | D68: 0.8 | E68: =U68-0.2 -> 3.6 | F68: =N68-0.1 -> 2 | G68: =(C68*5900+E68*3400+F68*300+$D$49*B68)/B68 -> 10.426633 | J68: 2801 | K68: =S68 -> 0.4 | L68: 0.8 | M68: =U68-0.1 -> 3.7 | N68: =V68-0.1 -> 2.1 | O68: =(K68*5900+M68*3400+N68*300+J68*$L$49)/J68 -> 11.558729 | R68: 2801 | S68: 0.4 | T68: 4.62 | U68: 3.8 | V68: 2.2 | W68: =(S68*5900+U68*3400+V68*300+$T$49*R68)/R68 -> 12.690825 | X68: =(S68*5900+U68*3400+V68*1200)/R68 -> 6.3977151 | Z68: 2801 | AA68: =S68 -> 0.4 | AB68: =T68*1.02 -> 4.7124 | AC68: =U68+0.1 -> 3.9 | AD68: =V68+0.1 -> 2.3 | AE68: =(AA68*5900+AC68*3400+AD68*300+Z68*$AB$49)/Z68 -> 13.82292 | AH68: 2801 | AI68: =S68 -> 0.4 | AJ68: =AB68+0.1 -> 4.8124 | AK68: =AC68+0.1 -> 4 | AL68: =AD68+0.1 -> 2.4 | AM68: =(AI68*5900+AK68*3400+AL68*300+$AJ$49*AH68)/AH68 -> 14.955016 | AP68: 2801 | AQ68: =S68 -> 0.4 | AR68: =AJ68+0.1 -> 4.9124 | AS68: =AK68+0.1 -> 4.1 | AT68: =AL68+0.1 -> 2.5 | AU68: =(AQ68*5900+AS68*3400+AT68*300+$AR$49*AP68)/AP68 -> 16.087112 | AX68: 2801 | AY68: =S68 -> 0.4 | AZ68: =AR68 -> 4.9124 | BA68: =AS68+0.1 -> 4.2 | BB68: =AT68+0.1 -> 2.6 | BC68: =(AY68*5900+BA68*3400+BB68*300+$AZ$49*AX68)/AX68 -> 17.219207
B70: 人群难度 | C70: 四级难度 | J70: 人群难度 | L70: 四级难度 | R70: 人群难度 | T70: 四级难度 | Z70: 人群难度 | AB70: 四级难度 | AH70: 人群难度 | AJ70: 四级难度 | AP70: 人群难度 | AR70: 四级难度 | AX70: 人群难度 | AZ70: 四级难度
B71: 问卷难度 | C71: 20题以内 | J71: 问卷难度 | L71: 21~30题 | R71: 问卷难度 | T71: 31~40题 | Z71: 问卷难度 | AB71: 41~50题 | AH71: 问卷难度 | AJ71: 51~60 | AP71: 问卷难度 | AR71: 61~70 | AX71: 问卷难度 | AZ71: 71~80
B72: 单价 | D72: 7 | G72: =AVERAGE(G76:G91) -> 16.435352 | J72: 单价 | L72: 8.5 | O72: =AVERAGE(O76:O91) -> 18.739225 | R72: 单价 | T72: 10 | W72: =AVERAGE(W76:W91) -> 20.899863 | Z72: 单价 | AB72: 11.5 | AE72: =AVERAGE(AE76:AE91) -> 23.434323 | AH72: 单价 | AJ72: 13 | AM72: =AVERAGE(AM76:AM91) -> 25.594961 | AP72: 单价 | AR72: 14.5 | AU72: =AVERAGE(AU76:AU91) -> 27.755599 | AX72: 单价 | AZ72: 16 | BC72: =AVERAGE(BC76:BC91) -> 30.09418 | BE72: =AVERAGE(BC72,AU72,AM72,AE72,W72,O72,G72) -> 23.279072 | BF72: =BE72-AVERAGE(AZ72,AR72,AJ72,AB72,T72,L72,D72) -> 11.779072
B73: 份数 | C73: P5 | D73: P4 | E73: P3 | F73: 实习生 | G73: 成本 | H73: 上限 | J73: 份数 | K73: P5 | L73: P4 | M73: P3 | N73: 实习生 | R73: 份数 | S73: P5 | T73: P4 | U73: P3 | V73: 实习生 | W73: 成本 | Z73: 份数 | AB73: P4 | AC73: P3 | AD73: 实习生 | AH73: 份数 | AJ73: P4 | AK73: P3 | AL73: 实习生 | AP73: 份数 | AQ73: P5 | AR73: P4 | AS73: P3 | AT73: 实习生 | AX73: 份数 | AY73: P5 | AZ73: P4 | BA73: P3 | BB73: 实习生
B74: 0 | C74: =S74 -> 0 | D74: 0 | E74: 0 | F74: 0 | G74: =(C74*5900+E74*3400+F74*300+B74*$D$72)/B74 -> #DIV/0! | J74: 0 | K74: =S74 -> 0 | L74: 0 | M74: 0 | N74: =F74+0.1 -> 0.1 | O74: =(K74*5900+M74*3400+N74*300+J74*$L$72)/J74 -> #DIV/0! | R74: 0 | S74: =S51 -> 0 | T74: 0 | U74: 0 | V74: =N74+0.1 -> 0.2 | W74: =(S74*5900+U74*3400+V74*300+R74*$T$72)/R74 -> #DIV/0! | Z74: 0 | AA74: =S74*1.1 -> 0 | AB74: 0 | AC74: 0 | AD74: 0 | AE74: =(AA74*5900+AC74*3400+AD74*300+Z74*$AB$72)/Z74 -> #DIV/0! | AH74: 0 | AI74: =AA74 -> 0 | AJ74: 0 | AK74: 0 | AL74: 0 | AM74: =(AI74*5900+AK74*2300+AL74*300+AH74*$AJ$72)/AH74 -> #DIV/0! | AP74: 0 | AQ74: =AI74 -> 0 | AR74: 0 | AS74: 0 | AT74: 0 | AU74: =(AQ74*5900+AS74*2300+AT74*300+AP74*$AR$72)/AP74 -> #DIV/0! | AX74: 0 | AY74: =AQ74 -> 0 | AZ74: 0 | BA74: 0 | BB74: 0 | BC74: =(AY74*7200+BA74*3100+BB74*300+AX74*$AZ$72)/AX74 -> #DIV/0!
B75: 1 | C75: =C76 -> 0 | D75: =D76 -> 0.2 | E75: =E76 -> 0.56 | F75: =F76 -> 0.8 | G75: =(C75*5900+E75*3400+F75*300+B75*$D$72)/B75 -> 2151 | J75: 1 | K75: =K76 -> 0 | L75: =L76 -> 0.2 | M75: =M76 -> 0.644 | N75: =N76 -> 0.9 | O75: =(K75*5900+M75*3400+N75*300+$L$72*J75)/J75 -> 2468.1 | R75: 1 | S75: =S76 -> 0 | T75: =T76 -> 0.2 | U75: =U76 -> 0.744 | V75: =V76 -> 1 | W75: =(S75*5900+U75*3400+V75*300+$T$72*R75)/R75 -> 2839.6 | Z75: 1 | AA75: =AA76 -> 0 | AB75: =AB76 -> 0.3 | AC75: =AC76 -> 0.894 | AD75: =AD76 -> 1.1 | AE75: =(AA75*5900+AC75*3400+AD75*300+Z75*$AB$72)/Z75 -> 3381.1 | AH75: 1 | AI75: =AA75 -> 0 | AJ75: =AJ76 -> 0.4 | AK75: =AK76 -> 0.994 | AL75: =AL76 -> 1.2 | AM75: =(AI75*5900+AK75*3400+AL75*300+AH75*$AJ$72)/AH75 -> 3752.6 | AP75: 1 | AQ75: =AI75 -> 0 | AR75: =AR76 -> 0.5 | AS75: =AS76 -> 1.094 | AT75: =AT76 -> 1.3 | AU75: =(AQ75*5900+AS75*3400+AT75*300+$AR$72*AP75)/AP75 -> 4124.1 | AX75: 1 | AY75: =AQ75 -> 0 | AZ75: =AZ76 -> 0.5 | BA75: =AS75+0.1 -> 1.194 | BB75: =AT75+0.1 -> 1.4 | BC75: =(AY75*5900+BA75*3400+BB75*300+$AZ$72*AX75)/AX75 -> 4495.6
B76: 101 | C76: =S76 -> 0 | D76: 0.2 | E76: =E53*1.12 -> 0.56 | F76: =F53+0.2 -> 0.8 | G76: =(C76*5900+E76*3400+F76*300+B76*$D$72)/B76 -> 28.227723 | J76: 101 | K76: =S76 -> 0 | L76: 0.2 | M76: =E76*1.15 -> 0.644 | N76: =F76+0.1 -> 0.9 | O76: =(K76*5900+M76*3400+N76*300+$L$72*J76)/J76 -> 32.852475 | R76: 101 | S76: =S53 -> 0 | T76: 0.2 | U76: =M76+0.1 -> 0.744 | V76: =N76+0.1 -> 1 | W76: =(S76*5900+U76*3400+V76*300+$T$72*R76)/R76 -> 38.015842 | Z76: 101 | AA76: =S76*1.1 -> 0 | AB76: 0.3 | AC76: =U76+0.15 -> 0.894 | AD76: =V76+0.1 -> 1.1 | AE76: =(AA76*5900+AC76*3400+AD76*300+Z76*$AB$72)/Z76 -> 44.862376 | AH76: 101 | AI76: =AA76 -> 0 | AJ76: =AB76+0.1 -> 0.4 | AK76: =AC76+0.1 -> 0.994 | AL76: =AD76+0.1 -> 1.2 | AM76: =(AI76*5900+AK76*3400+AL76*300+AH76*$AJ$72)/AH76 -> 50.025743 | AP76: 101 | AQ76: =AI76 -> 0 | AR76: =AJ76+0.1 -> 0.5 | AS76: =AK76+0.1 -> 1.094 | AT76: =AL76+0.1 -> 1.3 | AU76: =(AQ76*5900+AS76*3400+AT76*300+$AR$72*AP76)/AP76 -> 55.189109 | AX76: 101 | AY76: =AQ76 -> 0 | AZ76: =AR76 -> 0.5 | BA76: =AS76+0.1 -> 1.194 | BB76: =AT76+0.1 -> 1.4 | BC76: =(AY76*5900+BA76*3400+BB76*300+$AZ$72*AX76)/AX76 -> 60.352475
B77: 201 | C77: =S77 -> 0 | D77: 0.2 | E77: =E54*1.12 -> 0.896 | F77: =F54+0.2 -> 1.2 | G77: =(C77*5900+E77*3400+F77*300+B77*$D$72)/B77 -> 23.947264 | J77: 201 | K77: =S77 -> 0 | L77: 0.2 | M77: =E77*1.15 -> 1.0304 | N77: =F77+0.1 -> 1.3 | O77: =(K77*5900+M77*3400+N77*300+$L$72*J77)/J77 -> 27.86995 | R77: 201 | S77: =S54 -> 0 | T77: 0.2 | U77: =M77+0.1 -> 1.1304 | V77: =N77+0.1 -> 1.4 | W77: =(S77*5900+U77*3400+V77*300+$T$72*R77)/R77 -> 31.210746 | Z77: 201 | AA77: =S77*1.1 -> 0 | AB77: 0.3 | AC77: =U77+0.15 -> 1.2804 | AD77: =V77+0.1 -> 1.5 | AE77: =(AA77*5900+AC77*3400+AD77*300+Z77*$AB$72)/Z77 -> 35.397313 | AH77: 201 | AI77: =AA77 -> 0 | AJ77: =AB77+0.1 -> 0.4 | AK77: =AC77+0.1 -> 1.3804 | AL77: =AD77+0.1 -> 1.6 | AM77: =(AI77*5900+AK77*3400+AL77*300+AH77*$AJ$72)/AH77 -> 38.738109 | AP77: 201 | AQ77: =AI77 -> 0 | AR77: =AJ77+0.1 -> 0.5 | AS77: =AK77+0.1 -> 1.4804 | AT77: =AL77+0.1 -> 1.7 | AU77: =(AQ77*5900+AS77*3400+AT77*300+$AR$72*AP77)/AP77 -> 42.078905 | AX77: 201 | AY77: =AQ77 -> 0 | AZ77: =AR77 -> 0.5 | BA77: =AS77+0.1 -> 1.5804 | BB77: =AT77+0.1 -> 1.8 | BC77: =(AY77*5900+BA77*3400+BB77*300+$AZ$72*AX77)/AX77 -> 45.419701
B78: 301 | C78: =S78 -> 0 | D78: 0.2 | E78: =E55*1.12 -> 1.12 | F78: =F55+0.2 -> 1.3 | G78: =(C78*5900+E78*3400+F78*300+B78*$D$72)/B78 -> 20.946844 | J78: 301 | K78: =S78 -> 0 | L78: 0.2 | M78: =E78*1.15 -> 1.288 | N78: =F78+0.1 -> 1.4 | O78: =(K78*5900+M78*3400+N78*300+$L$72*J78)/J78 -> 24.444186 | R78: 301 | S78: =S55 -> 0 | T78: 0.2 | U78: =M78+0.1 -> 1.388 | V78: =N78+0.1 -> 1.5 | W78: =(S78*5900+U78*3400+V78*300+$T$72*R78)/R78 -> 27.173422 | Z78: 301 | AA78: =S78*1.1 -> 0 | AB78: 0.3 | AC78: =U78+0.15 -> 1.538 | AD78: =V78+0.1 -> 1.6 | AE78: =(AA78*5900+AC78*3400+AD78*300+Z78*$AB$72)/Z78 -> 30.467442 | AH78: 301 | AI78: =AA78 -> 0 | AJ78: =AB78+0.1 -> 0.4 | AK78: =AC78+0.1 -> 1.638 | AL78: =AD78+0.1 -> 1.7 | AM78: =(AI78*5900+AK78*3400+AL78*300+AH78*$AJ$72)/AH78 -> 33.196678 | AP78: 301 | AQ78: =AI78 -> 0 | AR78: =AJ78+0.1 -> 0.5 | AS78: =AK78+0.1 -> 1.738 | AT78: =AL78+0.1 -> 1.8 | AU78: =(AQ78*5900+AS78*3400+AT78*300+$AR$72*AP78)/AP78 -> 35.925914 | AX78: 301 | AY78: =AQ78 -> 0 | AZ78: =AR78 -> 0.5 | BA78: =AS78+0.1 -> 1.838 | BB78: =AT78+0.1 -> 1.9 | BC78: =(AY78*5900+BA78*3400+BB78*300+$AZ$72*AX78)/AX78 -> 38.65515
B79: 501 | C79: =S79 -> 0.1 | D79: 0.3 | E79: =E56*1.12 -> 1.456 | F79: =F56+0.2 -> 1.4 | G79: =(C79*5900+E79*3400+F79*300+B79*$D$72)/B79 -> 18.897006 | J79: 501 | K79: =S79 -> 0.1 | L79: 0.3 | M79: =E79*1.15 -> 1.6744 | N79: =F79+0.1 -> 1.5 | O79: =(K79*5900+M79*3400+N79*300+$L$72*J79)/J79 -> 21.939042 | R79: 501 | S79: =S56 -> 0.1 | T79: 0.3 | U79: =M79+0.1 -> 1.7744 | V79: =N79+0.1 -> 1.6 | W79: =(S79*5900+U79*3400+V79*300+$T$72*R79)/R79 -> 24.177565 | Z79: 501 | AA79: =S79*1.1 -> 0.11 | AB79: 0.3 | AC79: =U79+0.15 -> 1.9244 | AD79: =V79+0.1 -> 1.7 | AE79: =(AA79*5900+AC79*3400+AD79*300+Z79*$AB$72)/Z79 -> 26.873174 | AH79: 501 | AI79: =AA79 -> 0.11 | AJ79: =AB79+0.1 -> 0.4 | AK79: =AC79+0.1 -> 2.0244 | AL79: =AD79+0.1 -> 1.8 | AM79: =(AI79*5900+AK79*3400+AL79*300+AH79*$AJ$72)/AH79 -> 29.111697 | AP79: 501 | AQ79: =AI79 -> 0.11 | AR79: =AJ79+0.1 -> 0.5 | AS79: =AK79+0.1 -> 2.1244 | AT79: =AL79+0.1 -> 1.9 | AU79: =(AQ79*5900+AS79*3400+AT79*300+$AR$72*AP79)/AP79 -> 31.35022 | AX79: 501 | AY79: =AQ79 -> 0.11 | AZ79: =AR79 -> 0.5 | BA79: =AS79+0.1 -> 2.2244 | BB79: =AT79+0.1 -> 2 | BC79: =(AY79*5900+BA79*3400+BB79*300+$AZ$72*AX79)/AX79 -> 33.588743
B80: 701 | C80: =S80 -> 0.1 | D80: 0.3 | E80: =E57*1.12 -> 1.68 | F80: =F57+0.2 -> 1.5 | G80: =(C80*5900+E80*3400+F80*300+B80*$D$72)/B80 -> 16.631954 | J80: 701 | K80: =S80 -> 0.1 | L80: 0.3 | M80: =E80*1.15 -> 1.932 | N80: =F80+0.1 -> 1.6 | O80: =(K80*5900+M80*3400+N80*300+$L$72*J80)/J80 -> 19.397004 | R80: 701 | S80: =S57 -> 0.1 | T80: 0.3 | U80: =M80+0.1 -> 2.032 | V80: =N80+0.1 -> 1.7 | W80: =(S80*5900+U80*3400+V80*300+$T$72*R80)/R80 -> 21.424822 | Z80: 701 | AA80: =S80*1.1 -> 0.11 | AB80: 0.3 | AC80: =U80+0.15 -> 2.182 | AD80: =V80+0.1 -> 1.8 | AE80: =(AA80*5900+AC80*3400+AD80*300+Z80*$AB$72)/Z80 -> 23.779315 | AH80: 701 | AI80: =AA80 -> 0.11 | AJ80: =AB80+0.1 -> 0.4 | AK80: =AC80+0.1 -> 2.282 | AL80: =AD80+0.1 -> 1.9 | AM80: =(AI80*5900+AK80*3400+AL80*300+AH80*$AJ$72)/AH80 -> 25.807133 | AP80: 701 | AQ80: =AI80 -> 0.11 | AR80: =AJ80+0.1 -> 0.5 | AS80: =AK80+0.1 -> 2.382 | AT80: =AL80+0.1 -> 2 | AU80: =(AQ80*5900+AS80*3400+AT80*300+$AR$72*AP80)/AP80 -> 27.83495 | AX80: 701 | AY80: =AQ80 -> 0.11 | AZ80: =AR80 -> 0.5 | BA80: =AS80+0.2 -> 2.582 | BB80: =AT80+0.1 -> 2.1 | BC80: =(AY80*5900+BA80*3400+BB80*300+$AZ$72*AX80)/AX80 -> 30.347789
B81: 901 | C81: =S81 -> 0.1 | D81: 0.4 | E81: =E58*1.12 -> 2.016 | F81: =F58+0.2 -> 1.5 | G81: =(C81*5900+E81*3400+F81*300+B81*$D$72)/B81 -> 15.76182 | J81: 901 | K81: =S81 -> 0.1 | L81: 0.4 | M81: 2.1 | N81: =F81+0.1 -> 1.6 | O81: =(K81*5900+M81*3400+N81*300+$L$72*J81)/J81 -> 17.612098 | R81: 901 | S81: =S58 -> 0.1 | T81: 0.4 | U81: =M81+0.1 -> 2.2 | V81: =N81+0.1 -> 1.7 | W81: =(S81*5900+U81*3400+V81*300+$T$72*R81)/R81 -> 19.522752 | Z81: 901 | AA81: =S81*1.1 -> 0.11 | AB81: 0.4 | AC81: =U81+0.15 -> 2.35 | AD81: =V81+0.1 -> 1.8 | AE81: =(AA81*5900+AC81*3400+AD81*300+Z81*$AB$72)/Z81 -> 21.687569 | AH81: 901 | AI81: =AA81 -> 0.11 | AJ81: =AB81+0.1 -> 0.5 | AK81: =AC81+0.1 -> 2.45 | AL81: =AD81+0.1 -> 1.9 | AM81: =(AI81*5900+AK81*3400+AL81*300+AH81*$AJ$72)/AH81 -> 23.598224 | AP81: 901 | AQ81: =AI81 -> 0.11 | AR81: =AJ81+0.1 -> 0.6 | AS81: =AK81+0.1 -> 2.55 | AT81: =AL81+0.1 -> 2 | AU81: =(AQ81*5900+AS81*3400+AT81*300+$AR$72*AP81)/AP81 -> 25.508879 | AX81: 901 | AY81: =AQ81 -> 0.11 | AZ81: =AR81 -> 0.6 | BA81: =AS81+0.2 -> 2.75 | BB81: =AT81+0.1 -> 2.1 | BC81: =(AY81*5900+BA81*3400+BB81*300+$AZ$72*AX81)/AX81 -> 27.796892
B82: 1001 | C82: =S82 -> 0.2 | D82: 0.4 | E82: =E59*1.12 -> 2.24 | F82: =F59+0.2 -> 1.7 | G82: =(C82*5900+E82*3400+F82*300+B82*$D$72)/B82 -> 16.296703 | J82: 1001 | K82: =S82 -> 0.2 | L82: 0.4 | M82: =E82+0.1 -> 2.34 | N82: =F82+0.1 -> 1.8 | O82: =(K82*5900+M82*3400+N82*300+$L$72*J82)/J82 -> 18.166334 | R82: 1001 | S82: =S59 -> 0.2 | T82: 0.4 | U82: =M82+0.1 -> 2.44 | V82: =N82+0.1 -> 1.9 | W82: =(S82*5900+U82*3400+V82*300+$T$72*R82)/R82 -> 20.035964 | Z82: 1001 | AA82: =S82*1.1 -> 0.22 | AB82: 0.4 | AC82: =U82+0.15 -> 2.59 | AD82: =V82+0.1 -> 2 | AE82: =(AA82*5900+AC82*3400+AD82*300+Z82*$AB$72)/Z82 -> 22.193307 | AH82: 1001 | AI82: =AA82 -> 0.22 | AJ82: =AB82+0.1 -> 0.5 | AK82: =AC82+0.1 -> 2.69 | AL82: =AD82+0.1 -> 2.1 | AM82: =(AI82*5900+AK82*3400+AL82*300+AH82*$AJ$72)/AH82 -> 24.062937 | AP82: 1001 | AQ82: =AI82 -> 0.22 | AR82: =AJ82+0.1 -> 0.6 | AS82: =AK82+0.1 -> 2.79 | AT82: =AL82+0.1 -> 2.2 | AU82: =(AQ82*5900+AS82*3400+AT82*300+$AR$72*AP82)/AP82 -> 25.932567 | AX82: 1001 | AY82: =AQ82 -> 0.22 | AZ82: =AR82 -> 0.6 | BA82: =AS82+0.2 -> 2.99 | BB82: =AT82+0.1 -> 2.3 | BC82: =(AY82*5900+BA82*3400+BB82*300+$AZ$72*AX82)/AX82 -> 28.141858
B83: 1201 | C83: =S83 -> 0.2 | D83: 0.5 | E83: =E60*1.12 -> 2.352 | F83: =F60+0.2 -> 1.9 | G83: =(C83*5900+E83*3400+F83*300+B83*$D$72)/B83 -> 15.11557 | J83: 1201 | K83: =S83 -> 0.2 | L83: 0.5 | M83: =E83+0.1 -> 2.452 | N83: =F83+0.1 -> 2 | O83: =(K83*5900+M83*3400+N83*300+$L$72*J83)/J83 -> 16.923647 | R83: 1201 | S83: =S60 -> 0.2 | T83: 0.5 | U83: =M83+0.1 -> 2.552 | V83: =N83+0.1 -> 2.1 | W83: =(S83*5900+U83*3400+V83*300+$T$72*R83)/R83 -> 18.731724 | Z83: 1201 | AA83: =S83*1.1 -> 0.22 | AB83: 0.5 | AC83: =U83+0.15 -> 2.702 | AD83: =V83+0.1 -> 2.2 | AE83: =(AA83*5900+AC83*3400+AD83*300+Z83*$AB$72)/Z83 -> 20.7796 | AH83: 1201 | AI83: =AA83 -> 0.22 | AJ83: =AB83+0.1 -> 0.6 | AK83: =AC83+0.1 -> 2.802 | AL83: =AD83+0.1 -> 2.3 | AM83: =(AI83*5900+AK83*3400+AL83*300+AH83*$AJ$72)/AH83 -> 22.587677 | AP83: 1201 | AQ83: =AI83 -> 0.22 | AR83: =AJ83+0.1 -> 0.7 | AS83: =AK83+0.1 -> 2.902 | AT83: =AL83+0.1 -> 2.4 | AU83: =(AQ83*5900+AS83*3400+AT83*300+$AR$72*AP83)/AP83 -> 24.395754 | AX83: 1201 | AY83: =AQ83 -> 0.22 | AZ83: =AR83 -> 0.7 | BA83: =AS83+0.2 -> 3.102 | BB83: =AT83+0.1 -> 2.5 | BC83: =(AY83*5900+BA83*3400+BB83*300+$AZ$72*AX83)/AX83 -> 26.486928
B84: 1401 | C84: =S84 -> 0.2 | D84: 0.5 | E84: =E61*1.12 -> 2.464 | F84: =F61+0.2 -> 2 | G84: =(C84*5900+E84*3400+F84*300+B84*$D$72)/B84 -> 14.25025 | J84: 1401 | K84: =S84 -> 0.2 | L84: 0.5 | M84: =E84+0.1 -> 2.564 | N84: =F84+0.1 -> 2.1 | O84: =(K84*5900+M84*3400+N84*300+$L$72*J84)/J84 -> 16.014347 | R84: 1401 | S84: =S61 -> 0.2 | T84: 0.5 | U84: =M84+0.1 -> 2.664 | V84: =N84+0.1 -> 2.2 | W84: =(S84*5900+U84*3400+V84*300+$T$72*R84)/R84 -> 17.778444 | Z84: 1401 | AA84: =S84*1.1 -> 0.22 | AB84: 0.5 | AC84: =U84+0.15 -> 2.814 | AD84: =V84+0.1 -> 2.3 | AE84: =(AA84*5900+AC84*3400+AD84*300+Z84*$AB$72)/Z84 -> 19.748108 | AH84: 1401 | AI84: =AA84 -> 0.22 | AJ84: =AB84+0.1 -> 0.6 | AK84: =AC84+0.1 -> 2.914 | AL84: =AD84+0.1 -> 2.4 | AM84: =(AI84*5900+AK84*3400+AL84*300+AH84*$AJ$72)/AH84 -> 21.512206 | AP84: 1401 | AQ84: =AI84 -> 0.22 | AR84: =AJ84+0.1 -> 0.7 | AS84: =AK84+0.1 -> 3.014 | AT84: =AL84+0.1 -> 2.5 | AU84: =(AQ84*5900+AS84*3400+AT84*300+$AR$72*AP84)/AP84 -> 23.276303 | AX84: 1401 | AY84: =AQ84 -> 0.22 | AZ84: =AR84 -> 0.7 | BA84: =AS84+0.2 -> 3.214 | BB84: =AT84+0.1 -> 2.6 | BC84: =(AY84*5900+BA84*3400+BB84*300+$AZ$72*AX84)/AX84 -> 25.283084
B85: 1601 | C85: =S85 -> 0.2 | D85: 0.6 | E85: =E62*1.12 -> 2.688 | F85: =F62+0.2 -> 2 | G85: =(C85*5900+E85*3400+F85*300+B85*$D$72)/B85 -> 13.820237 | J85: 1601 | K85: =S85 -> 0.2 | L85: 0.6 | M85: =E85+0.1 -> 2.788 | N85: =F85+0.1 -> 2.1 | O85: =(K85*5900+M85*3400+N85*300+$L$72*J85)/J85 -> 15.551343 | R85: 1601 | S85: =S62 -> 0.2 | T85: 0.6 | U85: =M85+0.1 -> 2.888 | V85: =N85+0.1 -> 2.2 | W85: =(S85*5900+U85*3400+V85*300+$T$72*R85)/R85 -> 17.282448 | Z85: 1601 | AA85: =S85*1.1 -> 0.22 | AB85: 0.6 | AC85: =U85+0.15 -> 3.038 | AD85: =V85+0.1 -> 2.3 | AE85: =(AA85*5900+AC85*3400+AD85*300+Z85*$AB$72)/Z85 -> 19.193442 | AH85: 1601 | AI85: =AA85 -> 0.22 | AJ85: =AB85+0.1 -> 0.7 | AK85: =AC85+0.1 -> 3.138 | AL85: =AD85+0.1 -> 2.4 | AM85: =(AI85*5900+AK85*3400+AL85*300+AH85*$AJ$72)/AH85 -> 20.924547 | AP85: 1601 | AQ85: =AI85 -> 0.22 | AR85: =AJ85+0.1 -> 0.8 | AS85: =AK85+0.1 -> 3.238 | AT85: =AL85+0.1 -> 2.5 | AU85: =(AQ85*5900+AS85*3400+AT85*300+$AR$72*AP85)/AP85 -> 22.655653 | AX85: 1601 | AY85: =AQ85 -> 0.22 | AZ85: =AR85 -> 0.8 | BA85: =AS85+0.2 -> 3.438 | BB85: =AT85+0.1 -> 2.6 | BC85: =(AY85*5900+BA85*3400+BB85*300+$AZ$72*AX85)/AX85 -> 24.599126
B86: 1801 | C86: =S86 -> 0.2 | D86: 0.6 | E86: =E63*1.12 -> 2.912 | F86: =F63+0.2 -> 2 | G86: =(C86*5900+E86*3400+F86*300+B86*$D$72)/B86 -> 13.48573 | J86: 1801 | K86: =S86 -> 0.2 | L86: 0.6 | M86: =E86+0.1 -> 3.012 | N86: =F86+0.1 -> 2.1 | O86: =(K86*5900+M86*3400+N86*300+$L$72*J86)/J86 -> 15.191172 | R86: 1801 | S86: =S63 -> 0.2 | T86: 0.6 | U86: =M86+0.1 -> 3.112 | V86: =N86+0.1 -> 2.2 | W86: =(S86*5900+U86*3400+V86*300+$T$72*R86)/R86 -> 16.896613 | Z86: 1801 | AA86: =S86*1.1 -> 0.22 | AB86: 0.6 | AC86: =U86+0.15 -> 3.262 | AD86: =V86+0.1 -> 2.3 | AE86: =(AA86*5900+AC86*3400+AD86*300+Z86*$AB$72)/Z86 -> 18.761966 | AH86: 1801 | AI86: =AA86 -> 0.22 | AJ86: =AB86+0.1 -> 0.7 | AK86: =AC86+0.1 -> 3.362 | AL86: =AD86+0.1 -> 2.4 | AM86: =(AI86*5900+AK86*3400+AL86*300+AH86*$AJ$72)/AH86 -> 20.467407 | AP86: 1801 | AQ86: =AI86 -> 0.22 | AR86: =AJ86+0.1 -> 0.8 | AS86: =AK86+0.1 -> 3.462 | AT86: =AL86+0.1 -> 2.5 | AU86: =(AQ86*5900+AS86*3400+AT86*300+$AR$72*AP86)/AP86 -> 22.172848 | AX86: 1801 | AY86: =AQ86 -> 0.22 | AZ86: =AR86 -> 0.8 | BA86: =AS86+0.2 -> 3.662 | BB86: =AT86+0.1 -> 2.6 | BC86: =(AY86*5900+BA86*3400+BB86*300+$AZ$72*AX86)/AX86 -> 24.067074
B87: 2001 | C87: =S87 -> 0.3 | D87: 0.7 | E87: =E64*1.12 -> 3.136 | F87: =F64+0.2 -> 2.2 | G87: =(C87*5900+E87*3400+F87*300+B87*$D$72)/B87 -> 13.542929 | J87: 2001 | K87: =S87 -> 0.3 | L87: 0.7 | M87: =E87+0.1 -> 3.236 | N87: =F87+0.1 -> 2.3 | O87: =(K87*5900+M87*3400+N87*300+$L$72*J87)/J87 -> 15.227836 | R87: 2001 | S87: =S64 -> 0.3 | T87: 0.7 | U87: =M87+0.1 -> 3.336 | V87: =N87+0.1 -> 2.4 | W87: =(S87*5900+U87*3400+V87*300+$T$72*R87)/R87 -> 16.912744 | Z87: 2001 | AA87: =S87*1.1 -> 0.33 | AB87: 0.7 | AC87: =U87+0.15 -> 3.486 | AD87: =V87+0.1 -> 2.5 | AE87: =(AA87*5900+AC87*3400+AD87*300+Z87*$AB$72)/Z87 -> 18.771064 | AH87: 2001 | AI87: =AA87 -> 0.33 | AJ87: =AB87+0.1 -> 0.8 | AK87: =AC87+0.1 -> 3.586 | AL87: =AD87+0.1 -> 2.6 | AM87: =(AI87*5900+AK87*3400+AL87*300+AH87*$AJ$72)/AH87 -> 20.455972 | AP87: 2001 | AQ87: =AI87 -> 0.33 | AR87: =AJ87+0.1 -> 0.9 | AS87: =AK87+0.1 -> 3.686 | AT87: =AL87+0.1 -> 2.7 | AU87: =(AQ87*5900+AS87*3400+AT87*300+$AR$72*AP87)/AP87 -> 22.14088 | AX87: 2001 | AY87: =AQ87 -> 0.33 | AZ87: =AR87 -> 0.9 | BA87: =AS87+0.2 -> 3.886 | BB87: =AT87+0.1 -> 2.8 | BC87: =(AY87*5900+BA87*3400+BB87*300+$AZ$72*AX87)/AX87 -> 23.995702
B88: 2201 | C88: =S88 -> 0.3 | D88: 0.7 | E88: =E65*1.12 -> 3.36 | F88: =F65+0.2 -> 2.2 | G88: =(C88*5900+E88*3400+F88*300+B88*$D$72)/B88 -> 13.294412 | J88: 2201 | K88: =S88 -> 0.3 | L88: 0.7 | M88: =E88+0.1 -> 3.46 | N88: =F88+0.1 -> 2.3 | O88: =(K88*5900+M88*3400+N88*300+$L$72*J88)/J88 -> 14.962517 | R88: 2201 | S88: =S65 -> 0.3 | T88: 0.7 | U88: =M88+0.1 -> 3.56 | V88: =N88+0.1 -> 2.4 | W88: =(S88*5900+U88*3400+V88*300+$T$72*R88)/R88 -> 16.630622 | Z88: 2201 | AA88: =S88*1.1 -> 0.33 | AB88: 0.7 | AC88: =U88+0.15 -> 3.71 | AD88: =V88+0.1 -> 2.5 | AE88: =(AA88*5900+AC88*3400+AD88*300+Z88*$AB$72)/Z88 -> 18.456383 | AH88: 2201 | AI88: =AA88 -> 0.33 | AJ88: =AB88+0.1 -> 0.8 | AK88: =AC88+0.1 -> 3.81 | AL88: =AD88+0.1 -> 2.6 | AM88: =(AI88*5900+AK88*3400+AL88*300+AH88*$AJ$72)/AH88 -> 20.124489 | AP88: 2201 | AQ88: =AI88 -> 0.33 | AR88: =AJ88+0.1 -> 0.9 | AS88: =AK88+0.1 -> 3.91 | AT88: =AL88+0.1 -> 2.7 | AU88: =(AQ88*5900+AS88*3400+AT88*300+$AR$72*AP88)/AP88 -> 21.792594 | AX88: 2201 | AY88: =AQ88 -> 0.33 | AZ88: =AR88 -> 0.9 | BA88: =AS88+0.2 -> 4.11 | BB88: =AT88+0.1 -> 2.8 | BC88: =(AY88*5900+BA88*3400+BB88*300+$AZ$72*AX88)/AX88 -> 23.615175
B89: 2401 | C89: =S89 -> 0.3 | D89: 0.8 | E89: =E66*1.12 -> 3.472 | F89: =F66+0.2 -> 2.2 | G89: =(C89*5900+E89*3400+F89*300+B89*$D$72)/B89 -> 12.928696 | J89: 2401 | K89: =S89 -> 0.3 | L89: 0.8 | M89: =E89+0.1 -> 3.572 | N89: =F89+0.1 -> 2.3 | O89: =(K89*5900+M89*3400+N89*300+$L$72*J89)/J89 -> 14.582799 | R89: 2401 | S89: =S66 -> 0.3 | T89: 0.8 | U89: =M89+0.1 -> 3.672 | V89: =N89+0.1 -> 2.4 | W89: =(S89*5900+U89*3400+V89*300+$T$72*R89)/R89 -> 16.236901 | Z89: 2401 | AA89: =S89*1.1 -> 0.33 | AB89: 0.8 | AC89: =U89+0.15 -> 3.822 | AD89: =V89+0.1 -> 2.5 | AE89: =(AA89*5900+AC89*3400+AD89*300+Z89*$AB$72)/Z89 -> 18.035527 | AH89: 2401 | AI89: =AA89 -> 0.33 | AJ89: =AB89+0.1 -> 0.9 | AK89: =AC89+0.1 -> 3.922 | AL89: =AD89+0.1 -> 2.6 | AM89: =(AI89*5900+AK89*3400+AL89*300+AH89*$AJ$72)/AH89 -> 19.689629 | AP89: 2401 | AQ89: =AI89 -> 0.33 | AR89: =AJ89+0.1 -> 1 | AS89: =AK89+0.1 -> 4.022 | AT89: =AL89+0.1 -> 2.7 | AU89: =(AQ89*5900+AS89*3400+AT89*300+$AR$72*AP89)/AP89 -> 21.343732 | AX89: 2401 | AY89: =AQ89 -> 0.33 | AZ89: =AR89 -> 1 | BA89: =AS89+0.2 -> 4.222 | BB89: =AT89+0.1 -> 2.8 | BC89: =(AY89*5900+BA89*3400+BB89*300+$AZ$72*AX89)/AX89 -> 23.139442
B90: 2601 | C90: =S90 -> 0.4 | D90: 0.8 | E90: =E67*1.12 -> 3.584 | F90: =F67+0.2 -> 2.2 | G90: =(C90*5900+E90*3400+F90*300+B90*$D$72)/B90 -> 12.846059 | J90: 2601 | K90: =S90 -> 0.4 | L90: 0.8 | M90: =E90+0.1 -> 3.684 | N90: =F90+0.1 -> 2.3 | O90: =(K90*5900+M90*3400+N90*300+$L$72*J90)/J90 -> 14.488312 | R90: 2601 | S90: =S67 -> 0.4 | T90: 0.8 | U90: =M90+0.1 -> 3.784 | V90: =N90+0.1 -> 2.4 | W90: =(S90*5900+U90*3400+V90*300+$T$72*R90)/R90 -> 16.130565 | Z90: 2601 | AA90: =S90*1.1 -> 0.44 | AB90: 0.8 | AC90: =U90+0.15 -> 3.934 | AD90: =V90+0.1 -> 2.5 | AE90: =(AA90*5900+AC90*3400+AD90*300+Z90*$AB$72)/Z90 -> 17.928912 | AH90: 2601 | AI90: =AA90 -> 0.44 | AJ90: =AB90+0.1 -> 0.9 | AK90: =AC90+0.1 -> 4.034 | AL90: =AD90+0.1 -> 2.6 | AM90: =(AI90*5900+AK90*3400+AL90*300+AH90*$AJ$72)/AH90 -> 19.571165 | AP90: 2601 | AQ90: =AI90 -> 0.44 | AR90: =AJ90+0.1 -> 1 | AS90: =AK90+0.1 -> 4.134 | AT90: =AL90+0.1 -> 2.7 | AU90: =(AQ90*5900+AS90*3400+AT90*300+$AR$72*AP90)/AP90 -> 21.213418 | AX90: 2601 | AY90: =AQ90 -> 0.44 | AZ90: =AR90 -> 1 | BA90: =AS90+0.2 -> 4.334 | BB90: =AT90+0.1 -> 2.8 | BC90: =(AY90*5900+BA90*3400+BB90*300+$AZ$72*AX90)/AX90 -> 22.98639
B91: 2801 | C91: =S91 -> 0.4 | D91: 0.8 | E91: =E68*1.12 -> 4.032 | F91: =F68+0.2 -> 2.2 | G91: =(C91*5900+E91*3400+F91*300+B91*$D$72)/B91 -> 12.972438 | J91: 2801 | K91: =S91 -> 0.4 | L91: 0.8 | M91: =E91+0.1 -> 4.132 | N91: =F91+0.1 -> 2.3 | O91: =(K91*5900+M91*3400+N91*300+$L$72*J91)/J91 -> 14.604534 | R91: 2801 | S91: =S68 -> 0.4 | T91: 0.8 | U91: =M91+0.1 -> 4.232 | V91: =N91+0.1 -> 2.4 | W91: =(S91*5900+U91*3400+V91*300+$T$72*R91)/R91 -> 16.23663 | Z91: 2801 | AA91: =S91*1.1 -> 0.44 | AB91: 0.8 | AC91: =U91+0.15 -> 4.382 | AD91: =V91+0.1 -> 2.5 | AE91: =(AA91*5900+AC91*3400+AD91*300+Z91*$AB$72)/Z91 -> 18.013674 | AH91: 2801 | AI91: =AA91 -> 0.44 | AJ91: =AB91+0.1 -> 0.9 | AK91: =AC91+0.1 -> 4.482 | AL91: =AD91+0.1 -> 2.6 | AM91: =(AI91*5900+AK91*3400+AL91*300+AH91*$AJ$72)/AH91 -> 19.645769 | AP91: 2801 | AQ91: =AI91 -> 0.44 | AR91: =AJ91+0.1 -> 1 | AS91: =AK91+0.1 -> 4.582 | AT91: =AL91+0.1 -> 2.7 | AU91: =(AQ91*5900+AS91*3400+AT91*300+$AR$72*AP91)/AP91 -> 21.277865 | AX91: 2801 | AY91: =AQ91 -> 0.44 | AZ91: =AR91 -> 1 | BA91: =AS91+0.2 -> 4.782 | BB91: =AT91+0.1 -> 2.8 | BC91: =(AY91*5900+BA91*3400+BB91*300+$AZ$72*AX91)/AX91 -> 23.031346
B93: 人群难度 | C93: 五级难度 | J93: 人群难度 | L93: 五级难度 | R93: 人群难度 | T93: 五级难度 | Z93: 人群难度 | AB93: 五级难度 | AH93: 人群难度 | AJ93: 五级难度 | AP93: 人群难度 | AR93: 五级难度 | AX93: 人群难度 | AZ93: 五级难度
B94: 问卷难度 | C94: 20题以内 | J94: 问卷难度 | L94: 21~30题 | R94: 问卷难度 | T94: 31~40题 | Z94: 问卷难度 | AB94: 41~50题 | AH94: 问卷难度 | AJ94: 51~60 | AP94: 问卷难度 | AR94: 61~70 | AX94: 问卷难度 | AZ94: 71~80
B95: 单价 | D95: 10 | G95: =AVERAGE(G99:G114) -> 20.478375 | J95: 单价 | L95: 12 | O95: =AVERAGE(O99:O114) -> 23.139013 | R95: 单价 | T95: 14 | W95: =AVERAGE(W99:W114) -> 25.799651 | Z95: 单价 | AB95: 16 | AE95: =AVERAGE(AE99:AE114) -> 28.460289 | AH95: 单价 | AJ95: 18 | AM95: =AVERAGE(AM99:AM114) -> 31.120927 | AP95: 单价 | AR95: 20 | AU95: =AVERAGE(AU99:AU114) -> 33.781565 | AX95: 单价 | AZ95: 22 | BC95: =AVERAGE(BC99:BC114) -> 36.388638 | BE95: =AVERAGE(BC95,AU95,AM95,AE95,W95,O95,G95) -> 28.452637 | BF95: =BE95-AVERAGE(AZ95,AR95,AJ95,AB95,T95,L95,D95) -> 12.452637
B96: 份数 | C96: P5 | D96: P4 | E96: P3 | F96: 实习生 | G96: 成本 | J96: 份数 | K96: P5 | L96: P4 | M96: P3 | N96: 实习生 | O96: 成本 | R96: 份数 | S96: P5 | T96: P4 | U96: P3 | V96: 实习生 | W96: 成本 | Z96: 份数 | AA96: P5 | AB96: P4 | AC96: P3 | AD96: 实习生 | AH96: 份数 | AI96: P5 | AJ96: P4 | AK96: P3 | AL96: 实习生 | AP96: 份数 | AR96: P4 | AS96: P3 | AT96: 实习生 | AX96: 份数 | AZ96: P4 | BA96: P3 | BB96: 实习生
B97: 0 | C97: 0 | D97: 0 | E97: 0 | F97: =F74+0.1 -> 0.1 | G97: =(C97*5900+E97*3400+F97*300+B97*$D$95)/B97 -> #DIV/0! | J97: 0 | K97: 0 | L97: 0 | M97: 0 | N97: =F97+0.1 -> 0.2 | O97: =(K97*5900+M97*3400+N97*300+J97*$L$95)/J97 -> #DIV/0! | R97: 0 | S97: 0 | T97: 0 | U97: 0 | V97: =N97+0.1 -> 0.3 | W97: =(S97*5900+U97*3400+V97*300+R97*$T$95)/R97 -> #DIV/0! | Z97: 0 | AA97: =S97 -> 0 | AB97: 0 | AC97: 0 | AD97: =V97+0.1 -> 0.4 | AE97: =(AA97*5900+AC97*3400+AD97*300+Z97*$AB$95)/Z97 -> #DIV/0! | AH97: 0 | AI97: =AA97 -> 0 | AJ97: 0 | AK97: 0 | AL97: =AD97+0.1 -> 0.5 | AM97: =(AI97*5900+AK97*3400+AL97*300+AH97*$AJ$95)/AH97 -> #DIV/0! | AP97: 0 | AQ97: =AR97/2 -> 0 | AR97: 0 | AS97: 0 | AT97: =AL97+0.1 -> 0.6 | AU97: =(AQ97*5900+AS97*3400+AT97*300+AP97*$AR$95)/AP97 -> #DIV/0! | AX97: 0 | AY97: =AQ97 -> 0 | AZ97: 0 | BA97: 0 | BB97: 0 | BC97: =(AY97*5900+BA97*3400+BB97*300+AX97*$AZ$95)/AX97 -> #DIV/0!
B98: 1 | C98: 0 | D98: =D99 -> 0.3 | E98: =E99 -> 0.66 | F98: =F99 -> 0.9 | G98: =(C98*5900+E98*3400+F98*300+$D$95*B98)/B98 -> 2524 | J98: 1 | K98: 0 | L98: =L99 -> 0.3 | M98: =M99 -> 0.76 | N98: =N99 -> 1 | O98: =(K98*5900+M98*3400+N98*300+J98*$L$95)/J98 -> 2896 | R98: 1 | S98: 0 | T98: =T99 -> 0.3 | U98: =U99 -> 0.86 | V98: =V99 -> 1.1 | W98: =(S98*5900+U98*3400+V98*300+R98*$T$95)/R98 -> 3268 | Z98: 1 | AA98: =S98 -> 0 | AB98: =AB99 -> 0.4 | AC98: =AC99 -> 0.96 | AD98: =AD99 -> 1.2 | AE98: =(AA98*5900+AC98*3400+AD98*300+Z98*$AB$95)/Z98 -> 3640 | AH98: 1 | AI98: =AA98 -> 0 | AJ98: =AJ99 -> 0.5 | AK98: =AK99 -> 1.06 | AL98: =AL99 -> 1.3 | AM98: =(AI98*5900+AK98*3400+AL98*300+$AJ$95*AH98)/AH98 -> 4012 | AP98: 1 | AQ98: =AI98 -> 0 | AR98: =AR99 -> 0.6 | AS98: =AS99 -> 1.16 | AT98: =AT99 -> 1.4 | AU98: =(AQ98*5900+AS98*3400+AT98*300+$AR$95*AP98)/AP98 -> 4384 | AX98: 1 | AY98: =AQ98 -> 0 | AZ98: =AZ99 -> 0.6 | BA98: =BA99 -> 1.26 | BB98: =BB99 -> 1.4 | BC98: =(AY98*5900+BA98*3400+BB98*300+AX98*$AZ$95)/AX98 -> 4726
B99: 101 | C99: 0 | D99: 0.3 | E99: =E76+0.1 -> 0.66 | F99: =F76+0.1 -> 0.9 | G99: =(C99*5900+E99*3400+F99*300+$D$95*B99)/B99 -> 34.891089 | J99: 101 | K99: 0 | L99: 0.3 | M99: =E99+0.1 -> 0.76 | N99: =F99+0.1 -> 1 | O99: =(K99*5900+M99*3400+N99*300+J99*$L$95)/J99 -> 40.554455 | R99: 101 | S99: 0 | T99: =T76+0.1 -> 0.3 | U99: =M99+0.1 -> 0.86 | V99: =N99+0.1 -> 1.1 | W99: =(S99*5900+U99*3400+V99*300+R99*$T$95)/R99 -> 46.217822 | Z99: 101 | AA99: =S99 -> 0 | AB99: =AB76+0.1 -> 0.4 | AC99: =U99+0.1 -> 0.96 | AD99: =V99+0.1 -> 1.2 | AE99: =(AA99*5900+AC99*3400+AD99*300+Z99*$AB$95)/Z99 -> 51.881188 | AH99: 101 | AI99: =AA99 -> 0 | AJ99: =AB99+0.1 -> 0.5 | AK99: =AC99+0.1 -> 1.06 | AL99: =AD99+0.1 -> 1.3 | AM99: =(AI99*5900+AK99*3400+AL99*300+$AJ$95*AH99)/AH99 -> 57.544554 | AP99: 101 | AQ99: =AI99 -> 0 | AR99: =AJ99+0.1 -> 0.6 | AS99: =AK99+0.1 -> 1.16 | AT99: =AL99+0.1 -> 1.4 | AU99: =(AQ99*5900+AS99*3400+AT99*300+$AR$95*AP99)/AP99 -> 63.207921 | AX99: 101 | AY99: =AQ99 -> 0 | AZ99: =AR99 -> 0.6 | BA99: =AS99+0.1 -> 1.26 | BB99: =AT99 -> 1.4 | BC99: =(AY99*5900+BA99*3400+BB99*300+AX99*$AZ$95)/AX99 -> 68.574257
B100: 201 | C100: 0 | D100: 0.3 | E100: =E77+0.1 -> 0.996 | F100: =F77+0.1 -> 1.3 | G100: =(C100*5900+E100*3400+F100*300+$D$95*B100)/B100 -> 28.78806 | J100: 201 | K100: 0 | L100: 0.3 | M100: =E100+0.1 -> 1.096 | N100: =F100+0.1 -> 1.4 | O100: =(K100*5900+M100*3400+N100*300+J100*$L$95)/J100 -> 32.628856 | R100: 201 | S100: 0 | T100: =T77+0.1 -> 0.3 | U100: =M100+0.1 -> 1.196 | V100: =N100+0.1 -> 1.5 | W100: =(S100*5900+U100*3400+V100*300+R100*$T$95)/R100 -> 36.469652 | Z100: 201 | AA100: =S100 -> 0 | AB100: =AB77+0.1 -> 0.4 | AC100: =U100+0.1 -> 1.296 | AD100: =V100+0.1 -> 1.6 | AE100: =(AA100*5900+AC100*3400+AD100*300+Z100*$AB$95)/Z100 -> 40.310448 | AH100: 201 | AI100: =AA100 -> 0 | AJ100: =AB100+0.1 -> 0.5 | AK100: =AC100+0.1 -> 1.396 | AL100: =AD100+0.1 -> 1.7 | AM100: =(AI100*5900+AK100*3400+AL100*300+$AJ$95*AH100)/AH100 -> 44.151244 | AP100: 201 | AQ100: =AI100 -> 0 | AR100: =AJ100+0.1 -> 0.6 | AS100: =AK100+0.1 -> 1.496 | AT100: =AL100+0.1 -> 1.8 | AU100: =(AQ100*5900+AS100*3400+AT100*300+$AR$95*AP100)/AP100 -> 47.99204 | AX100: 201 | AY100: =AQ100 -> 0 | AZ100: =AR100 -> 0.6 | BA100: =AS100+0.1 -> 1.596 | BB100: =AT100 -> 1.8 | BC100: =(AY100*5900+BA100*3400+BB100*300+AX100*$AZ$95)/AX100 -> 51.683582
B101: 301 | C101: 0 | D101: 0.3 | E101: =E78+0.1 -> 1.22 | F101: =F78+0.1 -> 1.4 | G101: =(C101*5900+E101*3400+F101*300+$D$95*B101)/B101 -> 25.17608 | J101: 301 | K101: 0 | L101: 0.3 | M101: =E101+0.1 -> 1.32 | N101: =F101+0.1 -> 1.5 | O101: =(K101*5900+M101*3400+N101*300+J101*$L$95)/J101 -> 28.405316 | R101: 301 | S101: 0 | T101: =T78+0.1 -> 0.3 | U101: =M101+0.1 -> 1.42 | V101: =N101+0.1 -> 1.6 | W101: =(S101*5900+U101*3400+V101*300+R101*$T$95)/R101 -> 31.634551 | Z101: 301 | AA101: =S101 -> 0 | AB101: =AB78+0.1 -> 0.4 | AC101: =U101+0.1 -> 1.52 | AD101: =V101+0.1 -> 1.7 | AE101: =(AA101*5900+AC101*3400+AD101*300+Z101*$AB$95)/Z101 -> 34.863787 | AH101: 301 | AI101: =AA101 -> 0 | AJ101: =AB101+0.1 -> 0.5 | AK101: =AC101+0.1 -> 1.62 | AL101: =AD101+0.1 -> 1.8 | AM101: =(AI101*5900+AK101*3400+AL101*300+$AJ$95*AH101)/AH101 -> 38.093023 | AP101: 301 | AQ101: =AI101 -> 0 | AR101: =AJ101+0.1 -> 0.6 | AS101: =AK101+0.1 -> 1.72 | AT101: =AL101+0.1 -> 1.9 | AU101: =(AQ101*5900+AS101*3400+AT101*300+$AR$95*AP101)/AP101 -> 41.322259 | AX101: 301 | AY101: =AQ101 -> 0 | AZ101: =AR101 -> 0.6 | BA101: =AS101+0.1 -> 1.82 | BB101: =AT101 -> 1.9 | BC101: =(AY101*5900+BA101*3400+BB101*300+AX101*$AZ$95)/AX101 -> 44.451827
B102: 501 | C102: =S102 -> 0.2 | D102: 0.4 | E102: =E79+0.1 -> 1.556 | F102: =F79+0.1 -> 1.5 | G102: =(C102*5900+E102*3400+F102*300+$D$95*B102)/B102 -> 23.813174 | J102: 501 | K102: =S102 -> 0.2 | L102: 0.4 | M102: =E102+0.1 -> 1.656 | N102: =F102+0.1 -> 1.6 | O102: =(K102*5900+M102*3400+N102*300+J102*$L$95)/J102 -> 26.551697 | R102: 501 | S102: =S79+0.1 -> 0.2 | T102: =T79+0.1 -> 0.4 | U102: =M102+0.1 -> 1.756 | V102: =N102+0.1 -> 1.7 | W102: =(S102*5900+U102*3400+V102*300+R102*$T$95)/R102 -> 29.29022 | Z102: 501 | AA102: =S102 -> 0.2 | AB102: =AB79+0.2 -> 0.5 | AC102: =U102+0.1 -> 1.856 | AD102: =V102+0.1 -> 1.8 | AE102: =(AA102*5900+AC102*3400+AD102*300+Z102*$AB$95)/Z102 -> 32.028743 | AH102: 501 | AI102: =AA102 -> 0.2 | AJ102: =AB102+0.1 -> 0.6 | AK102: =AC102+0.1 -> 1.956 | AL102: =AD102+0.1 -> 1.9 | AM102: =(AI102*5900+AK102*3400+AL102*300+$AJ$95*AH102)/AH102 -> 34.767265 | AP102: 501 | AQ102: =AI102 -> 0.2 | AR102: =AJ102+0.1 -> 0.7 | AS102: =AK102+0.1 -> 2.056 | AT102: =AL102+0.1 -> 2 | AU102: =(AQ102*5900+AS102*3400+AT102*300+$AR$95*AP102)/AP102 -> 37.505788 | AX102: 501 | AY102: =AQ102 -> 0.2 | AZ102: =AR102 -> 0.7 | BA102: =AS102+0.1 -> 2.156 | BB102: =AT102 -> 2 | BC102: =(AY102*5900+BA102*3400+BB102*300+AX102*$AZ$95)/AX102 -> 40.184431
B103: 701 | C103: =S103 -> 0.2 | D103: 0.4 | E103: =E80+0.1 -> 1.78 | F103: =F80+0.1 -> 1.6 | G103: =(C103*5900+E103*3400+F103*300+$D$95*B103)/B103 -> 21.001427 | J103: 701 | K103: =S103 -> 0.2 | L103: 0.4 | M103: =E103+0.1 -> 1.88 | N103: =F103+0.1 -> 1.7 | O103: =(K103*5900+M103*3400+N103*300+J103*$L$95)/J103 -> 23.529244 | R103: 701 | S103: =S80+0.1 -> 0.2 | T103: =T80+0.1 -> 0.4 | U103: =M103+0.1 -> 1.98 | V103: =N103+0.1 -> 1.8 | W103: =(S103*5900+U103*3400+V103*300+R103*$T$95)/R103 -> 26.057061 | Z103: 701 | AA103: =S103 -> 0.2 | AB103: =AB80+0.2 -> 0.5 | AC103: =U103+0.1 -> 2.08 | AD103: =V103+0.1 -> 1.9 | AE103: =(AA103*5900+AC103*3400+AD103*300+Z103*$AB$95)/Z103 -> 28.584879 | AH103: 701 | AI103: =AA103 -> 0.2 | AJ103: =AB103+0.1 -> 0.6 | AK103: =AC103+0.1 -> 2.18 | AL103: =AD103+0.1 -> 2 | AM103: =(AI103*5900+AK103*3400+AL103*300+$AJ$95*AH103)/AH103 -> 31.112696 | AP103: 701 | AQ103: =AI103 -> 0.2 | AR103: =AJ103+0.1 -> 0.7 | AS103: =AK103+0.1 -> 2.28 | AT103: =AL103+0.1 -> 2.1 | AU103: =(AQ103*5900+AS103*3400+AT103*300+$AR$95*AP103)/AP103 -> 33.640514 | AX103: 701 | AY103: =AQ103 -> 0.2 | AZ103: =AR103 -> 0.7 | BA103: =AS103+0.1 -> 2.38 | BB103: =AT103 -> 2.1 | BC103: =(AY103*5900+BA103*3400+BB103*300+AX103*$AZ$95)/AX103 -> 36.125535
B104: 901 | C104: =S104 -> 0.2 | D104: 0.5 | E104: =E81+0.1 -> 2.116 | F104: =F81+0.1 -> 1.6 | G104: =(C104*5900+E104*3400+F104*300+$D$95*B104)/B104 -> 19.827303 | J104: 901 | K104: =S104 -> 0.2 | L104: 0.5 | M104: =E104+0.1 -> 2.216 | N104: =F104+0.1 -> 1.7 | O104: =(K104*5900+M104*3400+N104*300+J104*$L$95)/J104 -> 22.237958 | R104: 901 | S104: =S81+0.1 -> 0.2 | T104: =T81+0.1 -> 0.5 | U104: =M104+0.1 -> 2.316 | V104: =N104+0.1 -> 1.8 | W104: =(S104*5900+U104*3400+V104*300+R104*$T$95)/R104 -> 24.648613 | Z104: 901 | AA104: =S104 -> 0.2 | AB104: =AB81+0.2 -> 0.6 | AC104: =U104+0.1 -> 2.416 | AD104: =V104+0.1 -> 1.9 | AE104: =(AA104*5900+AC104*3400+AD104*300+Z104*$AB$95)/Z104 -> 27.059267 | AH104: 901 | AI104: =AA104 -> 0.2 | AJ104: =AB104+0.1 -> 0.7 | AK104: =AC104+0.1 -> 2.516 | AL104: =AD104+0.1 -> 2 | AM104: =(AI104*5900+AK104*3400+AL104*300+$AJ$95*AH104)/AH104 -> 29.469922 | AP104: 901 | AQ104: =AI104 -> 0.2 | AR104: =AJ104+0.1 -> 0.8 | AS104: =AK104+0.1 -> 2.616 | AT104: =AL104+0.1 -> 2.1 | AU104: =(AQ104*5900+AS104*3400+AT104*300+$AR$95*AP104)/AP104 -> 31.880577 | AX104: 901 | AY104: =AQ104 -> 0.2 | AZ104: =AR104 -> 0.8 | BA104: =AS104+0.1 -> 2.716 | BB104: =AT104 -> 2.1 | BC104: =(AY104*5900+BA104*3400+BB104*300+AX104*$AZ$95)/AX104 -> 34.257936
...

Sheet 【注】使用说明&目录
B3: 【UX】研究资源成本估算工具v1.0
C5: 一、使用说明
C6: 1. 此工具用于对“UX研究资源”的使用成本进行标准化估算，成本结构包含“资源中台人力+发包相关费用”； 2. 前台可根据产品的研究需求，在对应的资源模块下进行变量配置，从而会自动得出成本估算结果； 3. 会能够更精准的估算资源成本，以及对资源做精细化运营，此表对部分资源增加了“难度等级”判定，可跳转难度等级页查看定义标准； 4. 当前可能会出现需求场景未穷尽情况，若自身需求无法在表中匹配，则可联系资源中台进行人工评估（xiexin@corp.netease.com）； 【注】预估成本可作为项目预算的前置评估参考，实际成本建议与资源中台进行二次确认。
C11: 二、目录
C12: ① | D12: 【国内】研究资源成本估算
C13: ② | D13: 【海外】研究资源成本估算
C14: ③ | D14: 【国内】常规用户招募-难度等级评估
C15: ④ | D15: 【国内】特殊&小众用户招募-难度等级评估
C16: ⑤ | D16: 【国内】问卷调研-难度等级评估
C17: ⑥ | D17: 【概览】发包相关费用标准

Sheet 成本估算
N11: P5 | O11: 7200
N12: P3 | O12: 3000
N13: OP | O13: 1300
N14: 实习生 | O14: 300
M21: 国内

Sheet ①【国内】研究资源成本估算 (v1.0)
A1: 点击返回【使用说明&目录】
B2: 【UX】国内研究资源成本估算
A3: 玩家招募类 | B3: 1. 下表人力为预估值，实际可能会根据需求真实情况出现上、下浮动，对应职级人天投入浮动在0.5左右； 2. 下表估算人力包含“甄别/邀约”工作，若前台自主执行“甄别/邀约”，则估算的P3及实习生人力减少20%； 3. 50人以上玩家招募需求由资源中台人工评估成本。 4.特殊用户默认混合执行，小众用户默认P3单独执行 5.16人规模以上的招募需求，默认使用【混合执行】报价 6.人力估值新增测试时长作为相关系数
B4: 点击跳转【常规用户-难度等级说明表】
B5: 点击跳转【特殊&小众用户-难度等级说明表】
A6: 服务编号 | B6: 样本类型 | C6: 测试方式 | D6: 难度等级 | F6: 测试时长 | H6: 需求执行人 | I6: 测试样本量 | K6: 测试时长系数转化 | L6: P5 | M6: P3 | N6: OP | O6: 实习生 | P6: 执行人力单价 | Q6: P5 | R6: P3 | S6: OP | T6: 实习生 | W6: 人力投入合计 | X6: 玩家礼金合计 | Y6: 招募费用合计 （视情况应用） | Z6: 甄别费用合计 | AA6: 执行人力单价
A7: GT001 | B7: 常规用户 （普通游戏玩家，无身份/职业限制要求） | C7: 实验室测试/座谈会 （广/杭/沪地区） | D7: 右侧下拉选择 需求难度 | E7: 三级难度 | F7: 右侧手动输入 测试时长 （单位:小时) （0.5为区间输入） | G7: 3 | H7: 混合执行 | I7: 右侧手动输入 测试样本量 （单位:个) | J7: 50 | K7: =IF(G7<2,0.8,IF(G7<=4,1,IF(AND(G7>4,G7<6),1.05,1.08))) -> 1 | L7: =Q7*K7 -> 1.04 | M7: =R7*K7 -> 3.6 | N7: =S7*K7 -> 5.225 | O7: =T7*K7 -> 9.48 | P7: =AA7 -> 549.8 | Q7: {=LOOKUP(1,0/(('【国内】用户招募成本估算（完整版）'!$D$4:$D$82=H7)*('【国内】用户招募成本估算（完整版）'!$E$4:$E$82=E7)*('【国内】用户招募成本估算（完整版）'!$C$4:$C$82=C7)*('【国内】用户招募成本估算（完整版）'!$B$4:$B$82=$B$7)),'【国内】用户招募成本估算（完整版）'!$H$4:$H$82)} -> 1.04 | R7: {=LOOKUP(1,0/(('【国内】用户招募成本估算（完整版）'!$D$4:$D$82=H7)*('【国内】用户招募成本估算（完整版）'!$E$4:$E$82=E7)*('【国内】用户招募成本估算（完整版）'!$C$4:$C$82=C7)*('【国内】用户招募成本估算（完整版）'!$B$4:$B$82=$B$7)),'【国内】用户招募成本估算（完整版）'!$I$4:$I$82)} -> 3.6 | S7: {=LOOKUP(1,0/(('【国内】用户招募成本估算（完整版）'!$D$4:$D$82=H7)*('【国内】用户招募成本估算（完整版）'!$E$4:$E$82=E7)*('【国内】用户招募成本估算（完整版）'!$C$4:$C$82=C7)*('【国内】用户招募成本估算（完整版）'!$B$4:$B$82=$B$7)),'【国内】用户招募成本估算（完整版）'!$J$4:$J$82)} -> 5.225 | T7: {=LOOKUP(1,0/(('【国内】用户招募成本估算（完整版）'!$D$4:$D$82=H7)*('【国内】用户招募成本估算（完整版）'!$E$4:$E$82=E7)*('【国内】用户招募成本估算（完整版）'!$C$4:$C$82=C7)*('【国内】用户招募成本估算（完整版）'!$B$4:$B$82=$B$7)),'【国内】用户招募成本估算（完整版）'!$K$4:$K$82)} -> 9.48 | W7: =L7+M7+N7+O7 -> 19.345 | X7: =IF($E$7="一级难度",'【国内】用户招募成本估算（完整版）'!M4,IF($E$7="二级难度",'【国内】用户招募成本估算（完整版）'!M5,IF($E$7="三级难度",'【国内】用户招募成本估算（完整版）'!M6,IF($E$7="四级难度",'【国内】用户招募成本估算（完整版）'!M7,IF($E$7="五级难度",'【国内】用户招募成本估算（完整版）'!M8,IF($E$7="六级难度",'【国内】用户招募成本估算（完整版）'!#REF!)))))) -> 15000 | Y7: =IF($E$7="一级难度",'【国内】用户招募成本估算（完整版）'!N4,IF($E$7="二级难度",'【国内】用户招募成本估算（完整版）'!N5,IF($E$7="三级难度",'【国内】用户招募成本估算（完整版）'!N6,IF($E$7="四级难度",'【国内】用户招募成本估算（完整版）'!N7,IF($E$7="五级难度",'【国内】用户招募成本估算（完整版）'!N8,IF($E$7="六级难度",'【国内】用户招募成本估算（完整版）'!#REF!)))))) -> 2500 | Z7: =J7*20 -> 1000 | AA7: =(L7*5900+M7*3400+N7*1200+O7*300)/J7 -> 549.8 | AB7: =P7*J7 -> 27490
A8: GT002 | C8: 入户调研 （广/杭/沪地区） | E8: 三级难度 | G8: 1.5 | H8: OP单独执行 | J8: 10 | K8: =IF(G8<2,0.8,IF(G8<=4,1,IF(AND(G8>4,G8<6),1.05,1.08))) -> 0.8 | L8: =Q8*K8 -> 0 | M8: =R8*K8 -> 0 | N8: =S8*K8 -> 3.4048 | O8: =T8*K8 -> 2.72 | P8: =AA8 -> 490.176 | Q8: {=LOOKUP(1,0/(('【国内】用户招募成本估算（完整版）'!$D$4:$D$82=H8)*('【国内】用户招募成本估算（完整版）'!$E$4:$E$82=E8)*('【国内】用户招募成本估算（完整版）'!$C$4:$C$82=C8)*('【国内】用户招募成本估算（完整版）'!$B$4:$B$82=$B$7)),'【国内】用户招募成本估算（完整版）'!$H$4:$H$82)} -> 0 | R8: {=LOOKUP(1,0/(('【国内】用户招募成本估算（完整版）'!$D$4:$D$82=H8)*('【国内】用户招募成本估算（完整版）'!$E$4:$E$82=E8)*('【国内】用户招募成本估算（完整版）'!$C$4:$C$82=C8)*('【国内】用户招募成本估算（完整版）'!$B$4:$B$82=$B$7)),'【国内】用户招募成本估算（完整版）'!$I$4:$I$82)} -> 0 | S8: {=LOOKUP(1,0/(('【国内】用户招募成本估算（完整版）'!$D$4:$D$82=H8)*('【国内】用户招募成本估算（完整版）'!$E$4:$E$82=E8)*('【国内】用户招募成本估算（完整版）'!$C$4:$C$82=C8)*('【国内】用户招募成本估算（完整版）'!$B$4:$B$82=$B$7)),'【国内】用户招募成本估算（完整版）'!$J$4:$J$82)} -> 4.256 | T8: {=LOOKUP(1,0/(('【国内】用户招募成本估算（完整版）'!$D$4:$D$82=H8)*('【国内】用户招募成本估算（完整版）'!$E$4:$E$82=E8)*('【国内】用户招募成本估算（完整版）'!$C$4:$C$82=C8)*('【国内】用户招募成本估算（完整版）'!$B$4:$B$82=$B$7)),'【国内】用户招募成本估算（完整版）'!$K$4:$K$82)} -> 3.4 | W8: =L8+M8+N8+O8 -> 6.1248 | X8: =IF($E$8="一级难度",'【国内】用户招募成本估算（完整版）'!M19,IF($E$8="二级难度",'【国内】用户招募成本估算（完整版）'!M20,IF($E$8="三级难度",'【国内】用户招募成本估算（完整版）'!M21,IF($E$8="四级难度",'【国内】用户招募成本估算（完整版）'!M22,IF($E$8="五级难度",'【国内】用户招募成本估算（完整版）'!M23,IF($E$8="六级难度",'【国内】用户招募成本估算（完整版）'!#REF!)))))) -> 3000 | Y8: =IF($E$8="一级难度",'【国内】用户招募成本估算（完整版）'!N19,IF($E$8="二级难度",'【国内】用户招募成本估算（完整版）'!N20,IF($E$8="三级难度",'【国内】用户招募成本估算（完整版）'!N21,IF($E$8="四级难度",'【国内】用户招募成本估算（完整版）'!N22,IF($E$8="五级难度",'【国内】用户招募成本估算（完整版）'!N23,IF($E$8="六级难度",'【国内】用户招募成本估算（完整版）'!#REF!)))))) -> 600 | Z8: =J8*20 -> 200 | AA8: =(L8*5900+M8*3400+N8*1200+O8*300)/J8 -> 490.176
A9: GT003 | C9: 实验室测试/座谈会 （广/杭/沪以外地区） | E9: 三级难度 | G9: 3 | H9: P3单独执行 | J9: 20 | K9: 1 | L9: =Q9*K9 -> 0.22 | M9: =R9*K9 -> 2.99 | N9: =S9*K9 -> 0 | O9: =T9*K9 -> 3.3 | P9: =AA9 -> 622.7 | Q9: {=LOOKUP(1,0/(('【国内】用户招募成本估算（完整版）'!$D$4:$D$82=H9)*('【国内】用户招募成本估算（完整版）'!$E$4:$E$82=E9)*('【国内】用户招募成本估算（完整版）'!$C$4:$C$82=C9)*('【国内】用户招募成本估算（完整版）'!$B$4:$B$82=$B$7)),'【国内】用户招募成本估算（完整版）'!$H$4:$H$82)} -> 0.22 | R9: {=LOOKUP(1,0/(('【国内】用户招募成本估算（完整版）'!$D$4:$D$82=H9)*('【国内】用户招募成本估算（完整版）'!$E$4:$E$82=E9)*('【国内】用户招募成本估算（完整版）'!$C$4:$C$82=C9)*('【国内】用户招募成本估算（完整版）'!$B$4:$B$82=$B$7)),'【国内】用户招募成本估算（完整版）'!$I$4:$I$82)} -> 2.99 | S9: {=LOOKUP(1,0/(('【国内】用户招募成本估算（完整版）'!$D$4:$D$82=H9)*('【国内】用户招募成本估算（完整版）'!$E$4:$E$82=E9)*('【国内】用户招募成本估算（完整版）'!$C$4:$C$82=C9)*('【国内】用户招募成本估算（完整版）'!$B$4:$B$82=$B$7)),'【国内】用户招募成本估算（完整版）'!$J$4:$J$82)} -> 0 | T9: {=LOOKUP(1,0/(('【国内】用户招募成本估算（完整版）'!$D$4:$D$82=H9)*('【国内】用户招募成本估算（完整版）'!$E$4:$E$82=E9)*('【国内】用户招募成本估算（完整版）'!$C$4:$C$82=C9)*('【国内】用户招募成本估算（完整版）'!$B$4:$B$82=$B$7)),'【国内】用户招募成本估算（完整版）'!$K$4:$K$82)} -> 3.3 | W9: =L9+M9+N9+O9 -> 6.51 | X9: =IF($E$9="一级难度",'【国内】用户招募成本估算（完整版）'!M34,IF($E$9="二级难度",'【国内】用户招募成本估算（完整版）'!M35,IF($E$9="三级难度",'【国内】用户招募成本估算（完整版）'!M36,IF($E$9="四级难度",'【国内】用户招募成本估算（完整版）'!M37,IF($E$9="五级难度",'【国内】用户招募成本估算（完整版）'!M38,IF($E$9="六级难度",'【国内】用户招募成本估算（完整版）'!#REF!)))))) -> 6000 | Y9: =IF($E$9="一级难度",'【国内】用户招募成本估算（完整版）'!N34,IF($E$9="二级难度",'【国内】用户招募成本估算（完整版）'!N35,IF($E$9="三级难度",'【国内】用户招募成本估算（完整版）'!N36,IF($E$9="四级难度",'【国内】用户招募成本估算（完整版）'!N37,IF($E$9="五级难度",'【国内】用户招募成本估算（完整版）'!N38,IF($E$9="六级难度",'【国内】用户招募成本估算（完整版）'!#REF!)))))) -> 2000 | Z9: =J9*20 -> 400 | AA9: =(L9*5900+M9*3400+N9*1200+O9*300)/J9 -> 622.7
A10: GT004 | C10: 入户调研 （广/杭/沪以外地区） | E10: 三级难度 | G10: 2 | H10: P3单独执行 | J10: 20 | K10: 1 | L10: =Q10*K10 -> 0.22 | M10: =R10*K10 -> 3.12 | N10: =S10*K10 -> 0 | O10: =T10*K10 -> 3.9 | P10: =AA10 -> 653.8 | Q10: {=LOOKUP(1,0/(('【国内】用户招募成本估算（完整版）'!$D$4:$D$82=H10)*('【国内】用户招募成本估算（完整版）'!$E$4:$E$82=E10)*('【国内】用户招募成本估算（完整版）'!$C$4:$C$82=C10)*('【国内】用户招募成本估算（完整版）'!$B$4:$B$82=$B$7)),'【国内】用户招募成本估算（完整版）'!$H$4:$H$82)} -> 0.22 | R10: {=LOOKUP(1,0/(('【国内】用户招募成本估算（完整版）'!$D$4:$D$82=H10)*('【国内】用户招募成本估算（完整版）'!$E$4:$E$82=E10)*('【国内】用户招募成本估算（完整版）'!$C$4:$C$82=C10)*('【国内】用户招募成本估算（完整版）'!$B$4:$B$82=$B$7)),'【国内】用户招募成本估算（完整版）'!$I$4:$I$82)} -> 3.12 | S10: {=LOOKUP(1,0/(('【国内】用户招募成本估算（完整版）'!$D$4:$D$82=H10)*('【国内】用户招募成本估算（完整版）'!$E$4:$E$82=E10)*('【国内】用户招募成本估算（完整版）'!$C$4:$C$82=C10)*('【国内】用户招募成本估算（完整版）'!$B$4:$B$82=$B$7)),'【国内】用户招募成本估算（完整版）'!$J$4:$J$82)} -> 0 | T10: {=LOOKUP(1,0/(('【国内】用户招募成本估算（完整版）'!$D$4:$D$82=H10)*('【国内】用户招募成本估算（完整版）'!$E$4:$E$82=E10)*('【国内】用户招募成本估算（完整版）'!$C$4:$C$82=C10)*('【国内】用户招募成本估算（完整版）'!$B$4:$B$82=$B$7)),'【国内】用户招募成本估算（完整版）'!$K$4:$K$82)} -> 3.9 | W10: =L10+M10+N10+O10 -> 7.24 | X10: =IF($E$10="一级难度",'【国内】用户招募成本估算（完整版）'!M49,IF($E$10="二级难度",'【国内】用户招募成本估算（完整版）'!M50,IF($E$10="三级难度",'【国内】用户招募成本估算（完整版）'!M51,IF($E$10="四级难度",'【国内】用户招募成本估算（完整版）'!M52,IF($E$10="五级难度",'【国内】用户招募成本估算（完整版）'!M53,IF($E$10="六级难度",'【国内】用户招募成本估算（完整版）'!#REF!)))))) -> 6000 | Y10: =IF($E$10="一级难度",'【国内】用户招募成本估算（完整版）'!N49,IF($E$10="二级难度",'【国内】用户招募成本估算（完整版）'!N50,IF($E$10="三级难度",'【国内】用户招募成本估算（完整版）'!N51,IF($E$10="四级难度",'【国内】用户招募成本估算（完整版）'!N52,IF($E$10="五级难度",'【国内】用户招募成本估算（完整版）'!N53,IF($E$10="六级难度",'【国内】用户招募成本估算（完整版）'!#REF!)))))) -> 3000 | Z10: =J10*20 -> 400 | AA10: =(L10*5900+M10*3400+N10*1200+O10*300)/J10 -> 653.8
A11: GT005 | C11: 线上深访/测试 （不限城市） | E11: 四级难度 | G11: 1.5 | H11: 混合执行 | J11: 30 | K11: =IF(G11<2,0.8,IF(G11<=4,1,IF(AND(G11>4,G11<6),1.05,1.08))) -> 0.8 | L11: =Q11*K11 -> 0.416 | M11: =R11*K11 -> 1.6512 | N11: =S11*K11 -> 2.5880533 | O11: =T11*K11 -> 3.17952 | P11: =AA11 -> 404.26667 | Q11: {=LOOKUP(1,0/(('【国内】用户招募成本估算（完整版）'!$D$4:$D$82=H11)*('【国内】用户招募成本估算（完整版）'!$E$4:$E$82=E11)*('【国内】用户招募成本估算（完整版）'!$C$4:$C$82=C11)*('【国内】用户招募成本估算（完整版）'!$B$4:$B$82=$B$7)),'【国内】用户招募成本估算（完整版）'!$H$4:$H$82)} -> 0.52 | R11: {=LOOKUP(1,0/(('【国内】用户招募成本估算（完整版）'!$D$4:$D$82=H11)*('【国内】用户招募成本估算（完整版）'!$E$4:$E$82=E11)*('【国内】用户招募成本估算（完整版）'!$C$4:$C$82=C11)*('【国内】用户招募成本估算（完整版）'!$B$4:$B$82=$B$7)),'【国内】用户招募成本估算（完整版）'!$I$4:$I$82)} -> 2.064 | S11: {=LOOKUP(1,0/(('【国内】用户招募成本估算（完整版）'!$D$4:$D$82=H11)*('【国内】用户招募成本估算（完整版）'!$E$4:$E$82=E11)*('【国内】用户招募成本估算（完整版）'!$C$4:$C$82=C11)*('【国内】用户招募成本估算（完整版）'!$B$4:$B$82=$B$7)),'【国内】用户招募成本估算（完整版）'!$J$4:$J$82)} -> 3.2350667 | T11: {=LOOKUP(1,0/(('【国内】用户招募成本估算（完整版）'!$D$4:$D$82=H11)*('【国内】用户招募成本估算（完整版）'!$E$4:$E$82=E11)*('【国内】用户招募成本估算（完整版）'!$C$4:$C$82=C11)*('【国内】用户招募成本估算（完整版）'!$B$4:$B$82=$B$7)),'【国内】用户招募成本估算（完整版）'!$K$4:$K$82)} -> 3.9744 | W11: =L11+M11+N11+O11 -> 7.8347733 | X11: =IF($E$11="一级难度",'【国内】用户招募成本估算（完整版）'!M64,IF($E$11="二级难度",'【国内】用户招募成本估算（完整版）'!M65,IF($E$11="三级难度",'【国内】用户招募成本估算（完整版）'!M66,IF($E$11="四级难度",'【国内】用户招募成本估算（完整版）'!M67,IF($E$11="五级难度",'【国内】用户招募成本估算（完整版）'!M68,IF($E$11="六级难度",'【国内】用户招募成本估算（完整版）'!#REF!)))))) -> 3600 | Y11: =IF($E$11="一级难度",'【国内】用户招募成本估算（完整版）'!N64,IF($E$11="二级难度",'【国内】用户招募成本估算（完整版）'!N65,IF($E$11="三级难度",'【国内】用户招募成本估算（完整版）'!N66,IF($E$11="四级难度",'【国内】用户招募成本估算（完整版）'!N67,IF($E$11="五级难度",'【国内】用户招募成本估算（完整版）'!N68,IF($E$11="六级难度",'【国内】用户招募成本估算（完整版）'!#REF!)))))) -> 1500 | Z11: =J11*20 -> 600 | AA11: =(L11*5900+M11*3400+N11*1200+O11*300)/J11 -> 404.26667
A12: GT006 | C12: 保密性导量测试 （不限城市/100人起） | E12: 仅支持1~3级难度 | G12: 首日登录（2小时及以内） | H12: 混合执行 | J12: 100 | K12: / | L12: =Q12 -> 0.77 | M12: =R12 -> 3.4 | N12: =S12 -> 6.375 | O12: =T12 -> 6.8 | P12: =AA12 -> 257.93 | Q12: {=LOOKUP(1,1/(('【国内】用户招募成本估算（完整版）'!B79:B82=B7)*('【国内】用户招募成本估算（完整版）'!C79:C82=C12)*('【国内】用户招募成本估算（完整版）'!D79:D82=H12)*('【国内】用户招募成本估算（完整版）'!F79:F82=G12)),'【国内】用户招募成本估算（完整版）'!H79:H82)} -> 0.77 | R12: {=LOOKUP(1,1/(('【国内】用户招募成本估算（完整版）'!B79:B82=B7)*('【国内】用户招募成本估算（完整版）'!C79:C82=C12)*('【国内】用户招募成本估算（完整版）'!D79:D82=H12)),'【国内】用户招募成本估算（完整版）'!I79:I82)} -> 3.4 | S12: {=LOOKUP(1,1/(('【国内】用户招募成本估算（完整版）'!B79:B82=B7)*('【国内】用户招募成本估算（完整版）'!C79:C82=C12)*('【国内】用户招募成本估算（完整版）'!D79:D82=H12)),'【国内】用户招募成本估算（完整版）'!J79:J82)} -> 6.375 | T12: {=LOOKUP(1,1/(('【国内】用户招募成本估算（完整版）'!B79:B82=B7)*('【国内】用户招募成本估算（完整版）'!C79:C82=C12)*('【国内】用户招募成本估算（完整版）'!D79:D82=H12)),'【国内】用户招募成本估算（完整版）'!K79:K82)} -> 6.8 | W12: =L12+M12+N12+O12 -> 17.345 | X12: =IF($G$12="首日登录",'【国内】用户招募成本估算（完整版）'!M79,IF($G$12="三日登录",'【国内】用户招募成本估算（完整版）'!M80,IF($G$12="五日登录",'【国内】用户招募成本估算（完整版）'!M81,IF($G$12="七日登录",'【国内】用户招募成本估算（完整版）'!M82)))) -> FALSE | Z12: / | AA12: =(L12*5900+M12*3400+N12*1200+O12*300)/J12 -> 257.93
A13: GT007 | B13: 特殊用户 （KOL/主播/超R/地图作者等） | C13: 实验室测试/座谈会 （广/杭/沪本地需求） | E13: 三级难度 | G13: 2 | H13: 混合执行 | J13: 9 | K13: / | L13: =Q13 -> 0.2 | M13: =R13 -> 0.93235294 | N13: =S13 -> 2.6 | O13: =T13 -> 3.6 | P13: =AA13 -> 950 | Q13: {=LOOKUP(2,1/(('【国内】用户招募成本估算（完整版）'!D83:D90=H13)*('【国内】用户招募成本估算（完整版）'!E83:E90=E13)*('【国内】用户招募成本估算（完整版）'!C83:C90=C13)*('【国内】用户招募成本估算（完整版）'!B83:B90=B13)),'【国内】用户招募成本估算（完整版）'!H83:H90)} -> 0.2 | R13: {=LOOKUP(2,1/(('【国内】用户招募成本估算（完整版）'!D83:D90=H13)*('【国内】用户招募成本估算（完整版）'!E83:E90=E13)*('【国内】用户招募成本估算（完整版）'!C83:C90=C13)*('【国内】用户招募成本估算（完整版）'!B83:B90=B13)),'【国内】用户招募成本估算（完整版）'!I83:I90)} -> 0.93235294 | S13: {=LOOKUP(2,1/(('【国内】用户招募成本估算（完整版）'!D83:D90=H13)*('【国内】用户招募成本估算（完整版）'!E83:E90=E13)*('【国内】用户招募成本估算（完整版）'!C83:C90=C13)*('【国内】用户招募成本估算（完整版）'!B83:B90=B13)),'【国内】用户招募成本估算（完整版）'!J83:J90)} -> 2.6 | T13: {=LOOKUP(2,1/(('【国内】用户招募成本估算（完整版）'!D83:D90=H13)*('【国内】用户招募成本估算（完整版）'!E83:E90=E13)*('【国内】用户招募成本估算（完整版）'!C83:C90=C13)*('【国内】用户招募成本估算（完整版）'!B83:B90=B13)),'【国内】用户招募成本估算（完整版）'!K83:K90)} -> 3.6 | W13: =L13+M13+N13+O13 -> 7.3323529 | X13: =IF($E$13="一级难度",'【国内】用户招募成本估算（完整版）'!M83,IF($E$13="二级难度",'【国内】用户招募成本估算（完整版）'!M84,IF($E$13="三级难度",'【国内】用户招募成本估算（完整版）'!M85,IF($E$13="四级难度",'【国内】用户招募成本估算（完整版）'!M86)))) -> 9000 | Y13: =IF($E$13="一级难度",'【国内】用户招募成本估算（完整版）'!N83,IF($E$13="二级难度",'【国内】用户招募成本估算（完整版）'!N84,IF($E$13="三级难度",'【国内】用户招募成本估算（完整版）'!N85,IF($E$13="四级难度",'【国内】用户招募成本估算（完整版）'!N86)))) -> 1800 | Z13: =J13*30 -> 270 | AA13: =(L13*5900+M13*3400+N13*1200+O13*300)/J13 -> 950
A14: GT008 | C14: 线上深访/测试 （不限城市） | E14: 三级难度 | G14: 2 | H14: 混合执行 | J14: 7 | K14: / | L14: =Q14 -> 0.2 | M14: =R14 -> 0.56764706 | N14: =S14 -> 2.2 | O14: =T14 -> 3 | P14: =AA14 -> 950 | Q14: {=LOOKUP(2,1/(('【国内】用户招募成本估算（完整版）'!D84:D91=H14)*('【国内】用户招募成本估算（完整版）'!E84:E91=E14)*('【国内】用户招募成本估算（完整版）'!C84:C91=C14)*('【国内】用户招募成本估算（完整版）'!B84:B91=B13)),'【国内】用户招募成本估算（完整版）'!H84:H91)} -> 0.2 | R14: {=LOOKUP(2,1/(('【国内】用户招募成本估算（完整版）'!D84:D91=H14)*('【国内】用户招募成本估算（完整版）'!E84:E91=E14)*('【国内】用户招募成本估算（完整版）'!C84:C91=C14)*('【国内】用户招募成本估算（完整版）'!B84:B91=B13)),'【国内】用户招募成本估算（完整版）'!I84:I91)} -> 0.56764706 | S14: {=LOOKUP(2,1/(('【国内】用户招募成本估算（完整版）'!D84:D91=H14)*('【国内】用户招募成本估算（完整版）'!E84:E91=E14)*('【国内】用户招募成本估算（完整版）'!C84:C91=C14)*('【国内】用户招募成本估算（完整版）'!B84:B91=B13)),'【国内】用户招募成本估算（完整版）'!J84:J91)} -> 2.2 | T14: {=LOOKUP(2,1/(('【国内】用户招募成本估算（完整版）'!D83:D90=H14)*('【国内】用户招募成本估算（完整版）'!E83:E90=E14)*('【国内】用户招募成本估算（完整版）'!C83:C90=C14)*('【国内】用户招募成本估算（完整版）'!B83:B90=B13)),'【国内】用户招募成本估算（完整版）'!K83:K90)} -> 3 | W14: =L14+M14+N14+O14 -> 5.9676471 | X14: =IF($E$14="一级难度",'【国内】用户招募成本估算（完整版）'!M87,IF($E$14="二级难度",'【国内】用户招募成本估算（完整版）'!M88,IF($E$14="三级难度",'【国内】用户招募成本估算（完整版）'!M89,IF($E$14="四级难度",'【国内】用户招募成本估算（完整版）'!M90)))) -> 3500 | Y14: =IF($E$14="一级难度",'【国内】用户招募成本估算（完整版）'!N87,IF($E$14="二级难度",'【国内】用户招募成本估算（完整版）'!N88,IF($E$14="三级难度",'【国内】用户招募成本估算（完整版）'!N89,IF($E$14="四级难度",'【国内】用户招募成本估算（完整版）'!N90)))) -> 1400 | Z14: =J14*30 -> 210 | AA14: =(L14*5900+M14*3400+N14*1200+O14*300)/J14 -> 950
A15: GT009 | B15: 小众用户 （国内外籍/未成年/特定职业人群） | C15: 实验室测试/座谈会 （广/杭/沪本地需求） | E15: 二级难度 | G15: 2 | H15: P3单独执行 | J15: 10 | K15: / | L15: =Q15 -> 0.1725 | M15: =R15 -> 3.4653676 | N15: =S15 -> 0 | O15: =T15 -> 4 | P15: =AA15 -> 1400 | Q15: {=LOOKUP(2,1/(('【国内】用户招募成本估算（完整版）'!D91:D98=H15)*('【国内】用户招募成本估算（完整版）'!E91:E98=E15)*('【国内】用户招募成本估算（完整版）'!C91:C98=C15)*('【国内】用户招募成本估算（完整版）'!B91:B98=B15)),'【国内】用户招募成本估算（完整版）'!H91:H98)} -> 0.1725 | R15: {=LOOKUP(2,1/(('【国内】用户招募成本估算（完整版）'!D91:D98=H15)*('【国内】用户招募成本估算（完整版）'!E91:E98=E15)*('【国内】用户招募成本估算（完整版）'!C91:C98=C15)*('【国内】用户招募成本估算（完整版）'!B91:B98=B15)),'【国内】用户招募成本估算（完整版）'!I91:I98)} -> 3.4653676 | S15: {=LOOKUP(2,1/(('【国内】用户招募成本估算（完整版）'!D91:D98=H15)*('【国内】用户招募成本估算（完整版）'!E91:E98=E15)*('【国内】用户招募成本估算（完整版）'!C91:C98=C15)*('【国内】用户招募成本估算（完整版）'!B91:B98=B15)),'【国内】用户招募成本估算（完整版）'!J91:J98)} -> 0 | T15: {=LOOKUP(2,1/(('【国内】用户招募成本估算（完整版）'!D91:D98=H15)*('【国内】用户招募成本估算（完整版）'!E91:E98=E15)*('【国内】用户招募成本估算（完整版）'!C91:C98=C15)*('【国内】用户招募成本估算（完整版）'!B91:B98=B15)),'【国内】用户招募成本估算（完整版）'!K91:K98)} -> 4 | W15: =L15+M15+N15+O15 -> 7.6378676 | X15: =IF($E$15="一级难度",'【国内】用户招募成本估算（完整版）'!M91,IF($E$15="二级难度",'【国内】用户招募成本估算（完整版）'!M92,IF($E$15="三级难度",'【国内】用户招募成本估算（完整版）'!M93,IF($E$15="四级难度",'【国内】用户招募成本估算（完整版）'!M94)))) -> 4500 | Y15: =IF($E$15="一级难度",'【国内】用户招募成本估算（完整版）'!N91,IF($E$15="二级难度",'【国内】用户招募成本估算（完整版）'!N92,IF($E$15="三级难度",'【国内】用户招募成本估算（完整版）'!N93,IF($E$15="四级难度",'【国内】用户招募成本估算（完整版）'!N94)))) -> 3000 | Z15: =J15*30 -> 300 | AA15: =(L15*5900+M15*3400+N15*1200+O15*300)/J15 -> 1400
A16: GT010 | C16: 线上深访/测试 （不限城市） | E16: 四级难度 | G16: 6 | H16: P3单独执行 | J16: 10 | K16: / | L16: =Q16 -> 0.5 | M16: =R16 -> 4.0294118 | N16: =S16 -> 0 | O16: =T16 -> 4.5 | P16: =AA16 -> 1800 | Q16: {=LOOKUP(2,1/(('【国内】用户招募成本估算（完整版）'!D91:D98=H16)*('【国内】用户招募成本估算（完整版）'!E91:E98=E16)*('【国内】用户招募成本估算（完整版）'!C91:C98=C16)*('【国内】用户招募成本估算（完整版）'!B91:B98=B15)),'【国内】用户招募成本估算（完整版）'!H91:H98)} -> 0.5 | R16: {=LOOKUP(2,1/(('【国内】用户招募成本估算（完整版）'!D91:D98=H16)*('【国内】用户招募成本估算（完整版）'!E91:E98=E16)*('【国内】用户招募成本估算（完整版）'!C91:C98=C16)*('【国内】用户招募成本估算（完整版）'!B91:B98=B15)),'【国内】用户招募成本估算（完整版）'!I91:I98)} -> 4.0294118 | S16: {=LOOKUP(2,1/(('【国内】用户招募成本估算（完整版）'!D91:D98=H16)*('【国内】用户招募成本估算（完整版）'!E91:E98=E16)*('【国内】用户招募成本估算（完整版）'!C91:C98=C16)*('【国内】用户招募成本估算（完整版）'!B91:B98=B15)),'【国内】用户招募成本估算（完整版）'!J91:J98)} -> 0 | T16: {=LOOKUP(2,1/(('【国内】用户招募成本估算（完整版）'!D91:D98=H16)*('【国内】用户招募成本估算（完整版）'!E91:E98=E16)*('【国内】用户招募成本估算（完整版）'!C91:C98=C16)*('【国内】用户招募成本估算（完整版）'!B91:B98=B15)),'【国内】用户招募成本估算（完整版）'!K91:K980)} -> 4.5 | W16: =L16+M16+N16+O16 -> 9.0294118 | X16: =IF($E$16="一级难度",'【国内】用户招募成本估算（完整版）'!M95,IF($E$16="二级难度",'【国内】用户招募成本估算（完整版）'!M96,IF($E$16="三级难度",'【国内】用户招募成本估算（完整版）'!M97,IF($E$16="四级难度",'【国内】用户招募成本估算（完整版）'!M98)))) -> 11500 | Y16: =IF($E$16="一级难度",'【国内】用户招募成本估算（完整版）'!N95,IF($E$16="二级难度",'【国内】用户招募成本估算（完整版）'!N96,IF($E$16="三级难度",'【国内】用户招募成本估算（完整版）'!N97,IF($E$16="四级难度",'【国内】用户招募成本估算（完整版）'!N98)))) -> 4000 | Z16: =J16*30 -> 300 | AA16: =(L16*5900+M16*3400+N16*1200+O16*300)/J16 -> 1800
A17: 问卷调研类 | B17: 1. 下表人力为预估值，实际会根据需求执行情况出现上、下浮动，对应职级人天投入浮动在0.5左右； 2. 根据需求情况，会涉及使用外部供应商投放，若使用外部供应商，则人力投入缩减30%~60%，但对应问卷费用会视情况提升； 3. 3000份以上或60题以上问卷需求由资源中台人工评估成本。 4.OP单独执行仅限于三级以及三级以上的问卷回需求
B18: 点击跳转【问卷调研-难度等级说明表】
A19: 服务编号 | B19: 题目数量 | D19: 难度等级 | F19: 调研样本量 | H19: 需求执行人 | I19: 需求执行方式 | J19: P5 | K19: P3 | L19: OP | M19: 实习生 | N19: 人力投入合计 | O19: 执行人力单价(元） | P19: 问卷投放费用 | Q19: P5 | R19: P3 | S19: OP | T19: 实习生 | U19: 执行人力单价 | V19: 执行系数
A20: GT011 | B20: 20题及以内 | D20: 右侧下拉选择 需求难度 | E20: 一级难度 | F20: 右侧手动输入 调研样本量 （单位:份) | G20: 400 | H20: OP单独执行 | I20: 多渠道执行 | J20: =Q20*V20 -> 0 | K20: =R20*V20 -> 0 | L20: =S20*V20 -> 1.0416667 | M20: =T20*V20 -> 2.4 | N20: =J20+K20+L20+M20 -> 3.4416667 | O20: =U20 -> 4.925 | P20: {=LOOKUP(1,0/(('【国内】问卷投放成本估算（完整版）'!$C$4:$C$110=E20)*('【国内】问卷投放成本估算（完整版）'!$B$4:$B$110=H20)*('【国内】问卷投放成本估算（完整版）'!$D$4:$D$110=B20)),'【国内】问卷投放成本估算（完整版）'!$K$4:$K$10)} -> 800 | Q20: {=LOOKUP(2,1/(('【国内】问卷投放成本估算（完整版）'!$D2:$D129=B20)*('【国内】问卷投放成本估算（完整版）'!$C2:$C129=E20)*('【国内】问卷投放成本估算（完整版）'!$B2:$B129=H20)),'【国内】问卷投放成本估算（完整版）'!$F2:$F129)} -> 0 | R20: {=LOOKUP(2,1/(('【国内】问卷投放成本估算（完整版）'!$D$2:$D$129=B20)*('【国内】问卷投放成本估算（完整版）'!$C$2:$C$129=E20)*('【国内】问卷投放成本估算（完整版）'!$B$2:$B$129=H20)),'【国内】问卷投放成本估算（完整版）'!$G$2:$G$129)} -> 0 | S20: {=LOOKUP(2,1/(('【国内】问卷投放成本估算（完整版）'!$D$2:$D$129=B20)*('【国内】问卷投放成本估算（完整版）'!$C$2:$C$129=E20)*('【国内】问卷投放成本估算（完整版）'!$B$2:$B$129=H20)),'【国内】问卷投放成本估算（完整版）'!$H$2:$H$129)} -> 1.0416667 | T20: {=LOOKUP(2,1/(('【国内】问卷投放成本估算（完整版）'!$D$2:$D$129=B20)*('【国内】问卷投放成本估算（完整版）'!$C$2:$C$129=E20)*('【国内】问卷投放成本估算（完整版）'!$B$2:$B$129=H20)),'【国内】问卷投放成本估算（完整版）'!$I$2:$I$129)} -> 2.4 | U20: =(J20*5900+K20*3400+L20*1200+M20*300)/G20 -> 4.925 | V20: =IF(I20="单供应商渠道执行",IF(G20<500,(800-G20)/1000,0.5),IF(I20="单抖音渠道执行",0.6,IF(I20="多渠道执行",1,""))) -> 1
A21: GT012 | B21: 21-30题 | C21: 21~30题 | E21: 四级难度 | G21: 1000 | H21: OP单独执行 | I21: 多渠道执行 | J21: =Q21*V21 -> 0.54 | K21: =R21*V21 -> 0 | L21: =S21*V21 -> 3.1616667 | M21: =T21*V21 -> 4.1 | N21: =J21+K21+L21+M21 -> 7.8016667 | O21: =U21 -> 8.21 | P21: {=LOOKUP(1,0/(('【国内】问卷投放成本估算（完整版）'!$C$18:$C$129=E21)*('【国内】问卷投放成本估算（完整版）'!$B$18:$B$129=H21)*('【国内】问卷投放成本估算（完整版）'!$D$18:$D$129=B21)),'【国内】问卷投放成本估算（完整版）'!$K$18:$K$129)} -> 8500 | Q21: {=LOOKUP(2,1/(('【国内】问卷投放成本估算（完整版）'!$D2:$D129=B21)*('【国内】问卷投放成本估算（完整版）'!$C2:$C129=E21)*('【国内】问卷投放成本估算（完整版）'!$B2:$B129=H21)),'【国内】问卷投放成本估算（完整版）'!$F2:$F129)} -> 0.54 | R21: {=LOOKUP(2,1/(('【国内】问卷投放成本估算（完整版）'!$D$2:$D$129=B21)*('【国内】问卷投放成本估算（完整版）'!$C$2:$C$129=E21)*('【国内】问卷投放成本估算（完整版）'!$B$2:$B$129=H21)),'【国内】问卷投放成本估算（完整版）'!$G$2:$G$129)} -> 0 | S21: {=LOOKUP(2,1/(('【国内】问卷投放成本估算（完整版）'!$D$2:$D$129=B21)*('【国内】问卷投放成本估算（完整版）'!$C$2:$C$129=E21)*('【国内】问卷投放成本估算（完整版）'!$B$2:$B$129=H21)),'【国内】问卷投放成本估算（完整版）'!$H$2:$H$129)} -> 3.1616667 | T21: {=LOOKUP(2,1/(('【国内】问卷投放成本估算（完整版）'!$D$2:$D$129=B21)*('【国内】问卷投放成本估算（完整版）'!$C$2:$C$129=E21)*('【国内】问卷投放成本估算（完整版）'!$B$2:$B$129=H21)),'【国内】问卷投放成本估算（完整版）'!$I$2:$I$129)} -> 4.1 | U21: =(J21*5900+K21*3400+L21*1200+M21*300)/G21 -> 8.21 | V21: =IF(I21="单供应商渠道执行",IF(G21<500,(800-G21)/1000,0.5),IF(I21="单抖音渠道执行",0.6,IF(I21="多渠道执行",1,""))) -> 1
A22: GT013 | B22: 31~40题 | C22: 31~40题 | E22: 一级难度 | G22: 500 | H22: 混合执行 | I22: 多渠道执行 | J22: =Q22*V22 -> 0.1 | K22: =R22*V22 -> 0.28 | L22: =S22*V22 -> 0.61583333 | M22: =T22*V22 -> 1.43 | N22: =J22+K22+L22+M22 -> 2.4258333 | O22: =U22 -> 5.42 | P22: {=LOOKUP(1,0/(('【国内】问卷投放成本估算（完整版）'!$C$18:$C$129=E22)*('【国内】问卷投放成本估算（完整版）'!$B$18:$B$129=H22)*('【国内】问卷投放成本估算（完整版）'!$D$18:$D$129=B22)),'【国内】问卷投放成本估算（完整版）'!$K$18:$K$129)} -> 2000 | Q22: {=LOOKUP(2,1/(('【国内】问卷投放成本估算（完整版）'!$D2:$D129=B22)*('【国内】问卷投放成本估算（完整版）'!$C2:$C129=E22)*('【国内】问卷投放成本估算（完整版）'!$B2:$B129=H22)),'【国内】问卷投放成本估算（完整版）'!$F2:$F129)} -> 0.1 | R22: {=LOOKUP(2,1/(('【国内】问卷投放成本估算（完整版）'!$D$2:$D$129=B22)*('【国内】问卷投放成本估算（完整版）'!$C$2:$C$129=E22)*('【国内】问卷投放成本估算（完整版）'!$B$2:$B$129=H22)),'【国内】问卷投放成本估算（完整版）'!$G$2:$G$129)} -> 0.28 | S22: {=LOOKUP(2,1/(('【国内】问卷投放成本估算（完整版）'!$D$2:$D$129=B22)*('【国内】问卷投放成本估算（完整版）'!$C$2:$C$129=E22)*('【国内】问卷投放成本估算（完整版）'!$B$2:$B$129=H22)),'【国内】问卷投放成本估算（完整版）'!$H$2:$H$129)} -> 0.61583333 | T22: {=LOOKUP(2,1/(('【国内】问卷投放成本估算（完整版）'!$D$2:$D$129=B22)*('【国内】问卷投放成本估算（完整版）'!$C$2:$C$129=E22)*('【国内】问卷投放成本估算（完整版）'!$B$2:$B$129=H22)),'【国内】问卷投放成本估算（完整版）'!$I$2:$I$129)} -> 1.43 | U22: =(J22*5900+K22*3400+L22*1200+M22*300)/G22 -> 5.42 | V22: =IF(I22="单供应商渠道执行",IF(G22<500,(800-G22)/1000,0.5),IF(I22="单抖音渠道执行",0.6,IF(I22="多渠道执行",1,""))) -> 1
A23: GT014 | B23: 41~50题 | C23: 41~50题 | E23: 三级难度 | G23: 500 | H23: 混合执行 | I23: 多渠道执行 | J23: =Q23*V23 -> 0.1 | K23: =R23*V23 -> 0.52 | L23: =S23*V23 -> 1.6133333 | M23: =T23*V23 -> 1.82 | N23: =J23+K23+L23+M23 -> 4.0533333 | O23: =U23 -> 9.68 | P23: {=LOOKUP(1,0/(('【国内】问卷投放成本估算（完整版）'!$C$18:$C$129=E23)*('【国内】问卷投放成本估算（完整版）'!$B$18:$B$129=H23)*('【国内】问卷投放成本估算（完整版）'!$D$18:$D$129=B23)),'【国内】问卷投放成本估算（完整版）'!$K$18:$K$129)} -> 4000 | Q23: {=LOOKUP(2,1/(('【国内】问卷投放成本估算（完整版）'!$D2:$D129=B23)*('【国内】问卷投放成本估算（完整版）'!$C2:$C129=E23)*('【国内】问卷投放成本估算（完整版）'!$B2:$B129=H23)),'【国内】问卷投放成本估算（完整版）'!$F2:$F129)} -> 0.1 | R23: {=LOOKUP(2,1/(('【国内】问卷投放成本估算（完整版）'!$D$2:$D$129=B23)*('【国内】问卷投放成本估算（完整版）'!$C$2:$C$129=E23)*('【国内】问卷投放成本估算（完整版）'!$B$2:$B$129=H23)),'【国内】问卷投放成本估算（完整版）'!$G$2:$G$129)} -> 0.52 | S23: {=LOOKUP(2,1/(('【国内】问卷投放成本估算（完整版）'!$D$2:$D$129=B23)*('【国内】问卷投放成本估算（完整版）'!$C$2:$C$129=E23)*('【国内】问卷投放成本估算（完整版）'!$B$2:$B$129=H23)),'【国内】问卷投放成本估算（完整版）'!$H$2:$H$129)} -> 1.6133333 | T23: {=LOOKUP(2,1/(('【国内】问卷投放成本估算（完整版）'!$D$2:$D$129=B23)*('【国内】问卷投放成本估算（完整版）'!$C$2:$C$129=E23)*('【国内】问卷投放成本估算（完整版）'!$B$2:$B$129=H23)),'【国内】问卷投放成本估算（完整版）'!$I$2:$I$129)} -> 1.82 | U23: =(J23*5900+K23*3400+L23*1200+M23*300)/G23 -> 9.68 | V23: =IF(I23="单供应商渠道执行",IF(G23<500,(800-G23)/1000,0.5),IF(I23="单抖音渠道执行",0.6,IF(I23="多渠道执行",1,""))) -> 1
A24: GT015 | B24: 51~60题 | C24: 51~60题 | E24: 三级难度 | G24: 1000 | H24: 混合执行 | I24: 多渠道执行 | J24: =Q24*V24 -> 0.3 | K24: =R24*V24 -> 0.96 | L24: =S24*V24 -> 2.9691667 | M24: =T24*V24 -> 2.21 | N24: =J24+K24+L24+M24 -> 6.4391667 | O24: =U24 -> 9.26 | P24: {=LOOKUP(1,0/(('【国内】问卷投放成本估算（完整版）'!$C$18:$C$129=E24)*('【国内】问卷投放成本估算（完整版）'!$B$18:$B$129=H24)*('【国内】问卷投放成本估算（完整版）'!$D$18:$D$129=B24)),'【国内】问卷投放成本估算（完整版）'!$K$18:$K$129)} -> 9000 | Q24: {=LOOKUP(2,1/(('【国内】问卷投放成本估算（完整版）'!$D2:$D129=B24)*('【国内】问卷投放成本估算（完整版）'!$C2:$C129=E24)*('【国内】问卷投放成本估算（完整版）'!$B2:$B129=H24)),'【国内】问卷投放成本估算（完整版）'!$F2:$F129)} -> 0.3 | R24: {=LOOKUP(2,1/(('【国内】问卷投放成本估算（完整版）'!$D$2:$D$129=B24)*('【国内】问卷投放成本估算（完整版）'!$C$2:$C$129=E24)*('【国内】问卷投放成本估算（完整版）'!$B$2:$B$129=H24)),'【国内】问卷投放成本估算（完整版）'!$G$2:$G$129)} -> 0.96 | S24: {=LOOKUP(2,1/(('【国内】问卷投放成本估算（完整版）'!$D$2:$D$129=B24)*('【国内】问卷投放成本估算（完整版）'!$C$2:$C$129=E24)*('【国内】问卷投放成本估算（完整版）'!$B$2:$B$129=H24)),'【国内】问卷投放成本估算（完整版）'!$H$2:$H$129)} -> 2.9691667 | T24: {=LOOKUP(2,1/(('【国内】问卷投放成本估算（完整版）'!$D$2:$D$129=B24)*('【国内】问卷投放成本估算（完整版）'!$C$2:$C$129=E24)*('【国内】问卷投放成本估算（完整版）'!$B$2:$B$129=H24)),'【国内】问卷投放成本估算（完整版）'!$I$2:$I$129)} -> 2.21 | U24: =(J24*5900+K24*3400+L24*1200+M24*300)/G24 -> 9.26 | V24: =IF(I24="单供应商渠道执行",IF(G24<500,(800-G24)/1000,0.5),IF(I24="单抖音渠道执行",0.6,IF(I24="多渠道执行",1,""))) -> 1
A25: GT016 | B25: 61~70题 | E25: 六级难度 | G25: 500 | H25: 混合执行 | I25: 多渠道执行 | J25: =Q25*V25 -> 0.1 | K25: =R25*V25 -> 0.848 | L25: =S25*V25 -> 2.9623333 | M25: =T25*V25 -> 2.6 | N25: =J25+K25+L25+M25 -> 6.5103333 | O25: =U25 -> 15.616 | P25: {=LOOKUP(1,0/(('【国内】问卷投放成本估算（完整版）'!$C$18:$C$129=E25)*('【国内】问卷投放成本估算（完整版）'!$B$18:$B$129=H25)*('【国内】问卷投放成本估算（完整版）'!$D$18:$D$129=B25)),'【国内】问卷投放成本估算（完整版）'!$K$18:$K$129)} -> 11000 | Q25: {=LOOKUP(2,1/(('【国内】问卷投放成本估算（完整版）'!$D2:$D129=B25)*('【国内】问卷投放成本估算（完整版）'!$C2:$C129=E25)*('【国内】问卷投放成本估算（完整版）'!$B2:$B129=H25)),'【国内】问卷投放成本估算（完整版）'!$F2:$F129)} -> 0.1 | R25: {=LOOKUP(2,1/(('【国内】问卷投放成本估算（完整版）'!$D$2:$D$129=B25)*('【国内】问卷投放成本估算（完整版）'!$C$2:$C$129=E25)*('【国内】问卷投放成本估算（完整版）'!$B$2:$B$129=H25)),'【国内】问卷投放成本估算（完整版）'!$G$2:$G$129)} -> 0.848 | S25: {=LOOKUP(2,1/(('【国内】问卷投放成本估算（完整版）'!$D$2:$D$129=B25)*('【国内】问卷投放成本估算（完整版）'!$C$2:$C$129=E25)*('【国内】问卷投放成本估算（完整版）'!$B$2:$B$129=H25)),'【国内】问卷投放成本估算（完整版）'!$H$2:$H$129)} -> 2.9623333 | T25: {=LOOKUP(2,1/(('【国内】问卷投放成本估算（完整版）'!$D$2:$D$129=B25)*('【国内】问卷投放成本估算（完整版）'!$C$2:$C$129=E25)*('【国内】问卷投放成本估算（完整版）'!$B$2:$B$129=H25)),'【国内】问卷投放成本估算（完整版）'!$I$2:$I$129)} -> 2.6 | U25: =(J25*5900+K25*3400+L25*1200+M25*300)/G25 -> 15.616 | V25: =IF(I25="单供应商渠道执行",IF(G25<500,(800-G25)/1000,0.5),IF(I25="单抖音渠道执行",0.6,IF(I25="多渠道执行",1,""))) -> 1
A26: GT017 | B26: 71~80题 | E26: 三级难度 | G26: 2000 | H26: 混合执行 | I26: 多渠道执行 | J26: =Q26*V26 -> 0.4 | K26: =R26*V26 -> 1.92 | L26: =S26*V26 -> 2.4633333 | M26: =T26*V26 -> 3.12 | N26: =J26+K26+L26+M26 -> 7.9033333 | O26: =U26 -> 6.39 | P26: {=LOOKUP(1,0/(('【国内】问卷投放成本估算（完整版）'!$C$18:$C$129=E26)*('【国内】问卷投放成本估算（完整版）'!$B$18:$B$129=H26)*('【国内】问卷投放成本估算（完整版）'!$D$18:$D$129=B26)),'【国内】问卷投放成本估算（完整版）'!$K$18:$K$129)} -> 22000 | Q26: {=LOOKUP(2,1/(('【国内】问卷投放成本估算（完整版）'!$D2:$D129=B26)*('【国内】问卷投放成本估算（完整版）'!$C2:$C129=E26)*('【国内】问卷投放成本估算（完整版）'!$B2:$B129=H26)),'【国内】问卷投放成本估算（完整版）'!$F2:$F129)} -> 0.4 | R26: {=LOOKUP(2,1/(('【国内】问卷投放成本估算（完整版）'!$D$2:$D$129=B26)*('【国内】问卷投放成本估算（完整版）'!$C$2:$C$129=E26)*('【国内】问卷投放成本估算（完整版）'!$B$2:$B$129=H26)),'【国内】问卷投放成本估算（完整版）'!$G$2:$G$129)} -> 1.92 | S26: {=LOOKUP(2,1/(('【国内】问卷投放成本估算（完整版）'!$D$2:$D$129=B26)*('【国内】问卷投放成本估算（完整版）'!$C$2:$C$129=E26)*('【国内】问卷投放成本估算（完整版）'!$B$2:$B$129=H26)),'【国内】问卷投放成本估算（完整版）'!$H$2:$H$129)} -> 2.4633333 | T26: {=LOOKUP(2,1/(('【国内】问卷投放成本估算（完整版）'!$D$2:$D$129=B26)*('【国内】问卷投放成本估算（完整版）'!$C$2:$C$129=E26)*('【国内】问卷投放成本估算（完整版）'!$B$2:$B$129=H26)),'【国内】问卷投放成本估算（完整版）'!$I$2:$I$129)} -> 3.12 | U26: =(J26*5900+K26*3400+L26*1200+M26*300)/G26 -> 6.39 | V26: =IF(I26="单供应商渠道执行",IF(G26<500,(800-G26)/1000,0.5),IF(I26="单抖音渠道执行",0.6,IF(I26="多渠道执行",1,""))) -> 1
A27: CAA点击测试 | B27: 1. 下表人力含报告输出，若仅需原始数据，则P3/OP3人天对应-1； 2. 测试地区在可选范围以外，由资源中台评估测试可行性及成本； 3. 若同期测多个地区，则人力投入为总和的70%； 4. 超过20张素材的测试需求由资源中台人工评估成本。
A28: 服务编号 | B28: 测试地区 | D28: 素材类型 | F28: 素材数量 | H28: P5 | I28: OP3 | J28: 人力投入合计 | K28: 投放费用合计 | L28: 素材投放单价 （含费用金） | M28: 执行人力单价(元） | Q28: 执行人力单价(元） | R28: 转化系数
A29: GT018 | B29: 中国大陆 | D29: 视频 | F29: 右侧手动输入 素材数量 （单位:个) | G29: 5 | H29: =VLOOKUP($G$29,'【全球】CAA测试-数据源'!$C$5:$E$11,2,TRUE) -> 0.1 | I29: =VLOOKUP($G$29,'【全球】CAA测试-数据源'!$C$5:$E$11,3,TRUE) -> 1.7 | J29: =H29+I29 -> 1.8 | K29: =IF(D29="图片",G29*300,IF(D29="视频",G29*400)) -> 2000 | L29: =(H29*5900+I29*1200+K29)/G29 -> 926 | M29: =Q29 -> 526 | Q29: =(H29*5900+I29*1200)/G29 -> 526 | R29: =IF(G29<=5,(H29*5900+I29*1200)/560*G29,1) -> 23.482143
A30: GT019 | B30: 中国港澳台 | D30: 图片 | G30: 3 | H30: =VLOOKUP($G$30,'【全球】CAA测试-数据源'!$C$14:$E$20,2,TRUE) -> 0 | I30: =VLOOKUP($G$30,'【全球】CAA测试-数据源'!$C$14:$E$20,3,TRUE) -> 0.4 | J30: =H30+I30 -> 0.4 | K30: =IF(D30="图片",G30*600,IF(D30="视频",G30*800)) -> 1800 | L30: =(H30*5900+I30*1200+K30)/G30 -> 760 | M30: =Q30 -> 160 | Q30: =(H30*5900+I30*1200)/G30 -> 160
A31: GT020 | B31: 欧美地区 | D31: 图片 | G31: 3 | H31: =VLOOKUP($G$31,'【全球】CAA测试-数据源'!$J$6:$L$11,2,TRUE) -> 0 | I31: =VLOOKUP($G$31,'【全球】CAA测试-数据源'!$J$6:$L$11,3,TRUE) -> 0.4 | J31: =H31+I31 -> 0.4 | K31: =IF(D31="图片",G31*800,IF(D31="视频",G31*1000)) -> 2400 | L31: =(H31*5900+I31*1200+K31)/G31 -> 960 | M31: =Q31 -> 160 | Q31: =(H31*5900+I31*1200)/G31 -> 160
A32: GT021 | B32: 日韩地区 | D32: 图片 | G32: 3 | H32: =VLOOKUP($G$32,'【全球】CAA测试-数据源'!$J$15:$L$20,2,TRUE) -> 0 | I32: =VLOOKUP($G$32,'【全球】CAA测试-数据源'!$J$15:$L$20,3,TRUE) -> 0.4 | J32: =H32+I32 -> 0.4 | K32: =IF(D32="图片",G32*600,IF(D32="视频",G32*800)) -> 1800 | L32: =(H32*5900+I32*1200+K32)/G32 -> 760 | M32: =Q32 -> 160 | Q32: =(H32*5900+I32*1200)/G32 -> 160
A33: GT022 | B33: 东南亚地区 | D33: 图片 | G33: 3 | H33: =VLOOKUP($G$33,'【全球】CAA测试-数据源'!$C$24:$E$29,2,TRUE) -> 0 | I33: =VLOOKUP($G$33,'【全球】CAA测试-数据源'!$C$24:$E$29,3,TRUE) -> 0.4 | J33: =H33+I33 -> 0.4 | K33: =IF(D33="图片",G33*300,IF(D33="视频",G33*400)) -> 900 | L33: =(H33*5900+I33*1200+K33)/G33 -> 460 | M33: =Q33 -> 160 | Q33: =(H33*5900+I33*1200)/G33 -> 160
A34: 兼职人力 | B34: 1. 下表人力预估包含对兼职工作的跟进及质量把控，若仅需提供兼职人力对接，则对应人力缩减50%； 2. 若需使用兼职协助其他工作内容，则由资源中台人工评估成本。 注释：①工作难度：兼职协助完成1个有效样本执行的所需时间；②兼职工作量：需要兼职协助执行完成的有效样本数量。
A35: 服务编号 | B35: 工作类型 | D35: 工作难度 | F35: 兼职工作量 | H35: P3/OP3 | I35: 实习生 | J35: 人力投入合计 | K35: 兼职费用合计
A36: GT023 | B36: 甄别执行 | D36: 右侧下拉选择 兼职工作难度 | E36: 30min以内/样本 | F36: 右侧手动输入 兼职工作量 | G36: 200 | H36: =VLOOKUP($G$36,'【国内】兼职人力-数据源'!$B$5:$D$21,2,TRUE) -> 1.3 | I36: =VLOOKUP($G$36,'【国内】兼职人力-数据源'!$B$5:$D$21,3,TRUE) -> 0 | J36: =H36+I36 -> 1.3 | K36: =IF(E36="30min以内/样本",G36*2*'【国内】兼职人力-数据源'!E3,IF(E36="30~60min/样本",G36*'【国内】兼职人力-数据源'!E4)) -> 6400
A37: GT024 | B37: 电访执行 | E37: 30~60min/样本 | G37: 30 | H37: =VLOOKUP($G$37,'【国内】兼职人力-数据源'!$G$6:$I$22,2,TRUE) -> 0.7 | I37: =VLOOKUP($G$37,'【国内】兼职人力-数据源'!$G$6:$I$22,3,TRUE) -> 0 | J37: =H37+I37 -> 0.7 | K37: =IF(G37=0,0,IF(E37="10min及以内/样本",G37*1.5*'【国内】兼职人力-数据源'!J3+'【国内】兼职人力-数据源'!I3,IF(E37="10~30min/样本",G37*'【国内】兼职人力-数据源'!J4+'【国内】兼职人力-数据源'!I4,IF(E37="30~60min/样本",G37*'【国内】兼职人力-数据源'!J5+'【国内】兼职人力-数据源'!I5)))) -> 1180
A38: GT025 | B38: 街访执行 | E38: 10min以内/样本 | G38: 300 | H38: =VLOOKUP($G$38,'【国内】兼职人力-数据源'!B27:D44,2,TRUE) -> 2 | I38: =VLOOKUP($G$38,'【国内】兼职人力-数据源'!C27:E44,3,TRUE) -> 0 | J38: =H38+I38 -> 2 | K38: =IF(G38=0,0,IF(E38="10~30min/样本",G38*'【国内】兼职人力-数据源'!E25+'【国内】兼职人力-数据源'!D24,IF(E38="30~60min/样本",G38*'【国内】兼职人力-数据源'!E26+'【国内】兼职人力-数据源'!D25,IF(E38="10min以内/样本",G38*'【国内】兼职人力-数据源'!E24+'【国内】兼职人力-数据源'!D24)))) -> 4680
A39: GT026 | B39: 测试执行 | E39: 2~4H/样本 | G39: 6 | H39: =VLOOKUP($G$39,'【国内】兼职人力-数据源'!$G$28:$I$41,2,TRUE) -> 0.5 | I39: =VLOOKUP($G$39,'【国内】兼职人力-数据源'!$G$28:$I$41,3,TRUE) -> 0 | J39: =H39+I39 -> 0.5 | K39: =IF(E39="2H以内/样本",G39*'【国内】兼职人力-数据源'!J25,IF(E39="2~4H/样本",G39*'【国内】兼职人力-数据源'!J26,IF(E39="4~6H/样本",G39*'【国内】兼职人力-数据源'!J27))) -> 1800

Sheet 【国内】用户招募成本估算（完整版）
B1: 【网易UX】研究资源标准化成本估算表 —— 样本招募
A2: 1. 下表人力为预估值，实际会根据需求执行情况出现上、下浮动，对应职级人天投入浮动在0.1~0.5之间； 2. 下表估算人力包含“甄别/邀约”工作，若前台自主执行“甄别/邀约”，则推算人力减少20%； 3. 若线下测试在广/杭/沪以外的地区，则视需求情况，人力提升1.2~1.5倍。
A3: 服务编号 | B3: 样本属性 | C3: 测试方式 | D3: 执行方式 | E3: 难度等级 | F3: 测试时长（单位：小时） （以0.5为单位区间输入） | G3: 样本量（单位：人） | H3: P5 | I3: P3 | J3: OP | K3: 实习生 | L3: 人天投入合计 | M3: 玩家礼金合计 | N3: 招募费用合计 | O3: 甄别费用合计 | P3: 单样本招募人力（2H） | U3: 单样本招募人力（1H）
A4: GT001 | B4: 常规用户 （普通游戏玩家，无身份/职业限制要求） | C4: 实验室测试/座谈会 （广/杭/沪地区） | D4: OP单独执行 | E4: 一级难度 | F4: ='①【国内】研究资源成本估算 (v1.0)'!G7 -> 3 | G4: ='①【国内】研究资源成本估算 (v1.0)'!J7 -> 50 | H4: =VLOOKUP(G4,'【国内】常规用户招募-数据源 (OP)'!$A:$E,2,FALSE) -> 0.525 | I4: =VLOOKUP(G4,'【国内】常规用户招募-数据源 (OP)'!$A:$E,3,FALSE) -> 0 | J4: =VLOOKUP(G4,'【国内】常规用户招募-数据源 (OP)'!$A:$E,4,FALSE) -> 9.76875 | K4: =VLOOKUP(G4,'【国内】常规用户招募-数据源 (OP)'!$A:$E,5,FALSE) -> 9.5 | L4: =K4+J4+H4 -> 19.79375 | M4: =(IF(F4>2,200+INT((F4-2)/0.5)*50,IF(AND(F4>0,F4<=2),200,0)))*G4 -> 15000 | N4: =G4*50 -> 2500 | O4: =G4*20 -> 1000 | P4: =(H4*5900+I4*3400+J4*1200+K4*300)/G4 -> 353.4 | U4: =P4/2 -> 176.7
A5: GT002 | B5: 常规用户 （普通游戏玩家，无身份/职业限制要求） | C5: 实验室测试/座谈会 （广/杭/沪地区） | D5: OP单独执行 | E5: 二级难度 | F5: ='①【国内】研究资源成本估算 (v1.0)'!G7 -> 3 | G5: ='①【国内】研究资源成本估算 (v1.0)'!J7 -> 50 | H5: =VLOOKUP(G5,'【国内】常规用户招募-数据源 (OP)'!$N:$R,2,FALSE) -> 0.9 | I5: =VLOOKUP(G5,'【国内】常规用户招募-数据源 (OP)'!$A:$E,3,FALSE) -> 0 | J5: =VLOOKUP(G5,'【国内】常规用户招募-数据源 (OP)'!$N:$R,4,FALSE) -> 9.1916667 | K5: =VLOOKUP(G5,'【国内】常规用户招募-数据源 (OP)'!$N:$R,5,FALSE) -> 10 | L5: =K5+J5+H5 -> 20.091667 | M5: =(IF(F5>2,200+INT((F5-2)/0.5)*50,IF(AND(F5>0,F5<=2),200,0)))*G5 -> 15000 | N5: =G5*50 -> 2500 | O5: =G5*20 -> 1000 | P5: =(H5*5900+J5*1200+K5*300)/G5 -> 386.8 | U5: =P5/2 -> 193.4
A6: GT003 | B6: 常规用户 （普通游戏玩家，无身份/职业限制要求） | C6: 实验室测试/座谈会 （广/杭/沪地区） | D6: OP单独执行 | E6: 三级难度 | F6: ='①【国内】研究资源成本估算 (v1.0)'!G7 -> 3 | G6: ='①【国内】研究资源成本估算 (v1.0)'!J7 -> 50 | H6: =VLOOKUP(G6,'【国内】常规用户招募-数据源 (OP)'!$Z:$AD,2,FALSE) -> 1.6 | I6: =VLOOKUP(G6,'【国内】常规用户招募-数据源 (OP)'!$A:$E,3,FALSE) -> 0 | J6: =VLOOKUP(G6,'【国内】常规用户招募-数据源 (OP)'!$Z:$AD,4,FALSE) -> 12.041667 | K6: =VLOOKUP(G6,'【国内】常规用户招募-数据源 (OP)'!$Z:$AD,5,FALSE) -> 12 | L6: =K6+J6+H6 -> 25.641667 | M6: =(IF(F6>2,200+INT((F6-2)/0.5)*50,IF(AND(F6>0,F6<=2),200,0)))*G6 -> 15000 | N6: =G6*50 -> 2500 | O6: =G6*20 -> 1000 | P6: =(H6*5900+J6*1200+K6*300)/G6 -> 549.8 | U6: =P6/2 -> 274.9
A7: GT004 | B7: 常规用户 （普通游戏玩家，无身份/职业限制要求） | C7: 实验室测试/座谈会 （广/杭/沪地区） | D7: OP单独执行 | E7: 四级难度 | F7: ='①【国内】研究资源成本估算 (v1.0)'!G7 -> 3 | G7: ='①【国内】研究资源成本估算 (v1.0)'!J7 -> 50 | H7: =VLOOKUP(G7,'【国内】常规用户招募-数据源 (OP)'!$AM:$AQ,2,FALSE) -> 2.3 | I7: =VLOOKUP(G7,'【国内】常规用户招募-数据源 (OP)'!$A:$E,3,FALSE) -> 0 | J7: =VLOOKUP(G7,'【国内】常规用户招募-数据源 (OP)'!$AM:$AQ,4,FALSE) -> 12.585 | K7: =VLOOKUP(G7,'【国内】常规用户招募-数据源 (OP)'!$AM:$AQ,5,FALSE) -> 12.96 | L7: =K7+J7+H7 -> 27.845 | M7: =(IF(F7>2,200+INT((F7-2)/0.5)*50,IF(AND(F7>0,F7<=2),200,0)))*G7 -> 15000 | N7: =G7*50 -> 2500 | O7: =G7*20 -> 1000 | P7: =(H7*5900+J7*1200+K7*300)/G7 -> 651.2 | U7: =P7/2 -> 325.6
A8: GT005 | B8: 常规用户 （普通游戏玩家，无身份/职业限制要求） | C8: 实验室测试/座谈会 （广/杭/沪地区） | D8: OP单独执行 | E8: 五级难度 | F8: ='①【国内】研究资源成本估算 (v1.0)'!G7 -> 3 | G8: ='①【国内】研究资源成本估算 (v1.0)'!J7 -> 50 | H8: =VLOOKUP(G8,'【国内】常规用户招募-数据源 (OP)'!AZ:BD,2,FALSE) -> 2.3 | I8: =VLOOKUP(G8,'【国内】常规用户招募-数据源 (OP)'!$A:$E,3,FALSE) -> 0 | J8: =VLOOKUP(G8,'【国内】常规用户招募-数据源 (OP)'!AZ:BD,4,FALSE) -> 13.288733 | K8: =VLOOKUP(G8,'【国内】常规用户招募-数据源 (OP)'!AZ:BD,5,FALSE) -> 13.4784 | L8: =K8+J8+H8 -> 29.067133 | M8: =(IF(F8>2,200+INT((F8-2)/0.5)*50,IF(AND(F8>0,F8<=2),200,0)))*G8 -> 15000 | N8: =G8*50 -> 2500 | O8: =G8*20 -> 1000 | P8: =(H8*5900+J8*1200+K8*300)/G8 -> 671.2 | U8: =P8/2 -> 335.6
B9: 常规用户 （普通游戏玩家，无身份/职业限制要求） | C9: 实验室测试/座谈会 （广/杭/沪地区） | D9: P3单独执行 | E9: 一级难度 | F9: ='①【国内】研究资源成本估算 (v1.0)'!G7 -> 3 | G9: ='①【国内】研究资源成本估算 (v1.0)'!J7 -> 50 | H9: =VLOOKUP(G9,'【国内】常规用户招募-数据源 （正职）'!A:E,2,FALSE) -> 0.3 | I9: =VLOOKUP(G9,'【国内】常规用户招募-数据源 （正职）'!A:E,4,FALSE) -> 4.2 | J9: 0 | K9: =VLOOKUP(G9,'【国内】常规用户招募-数据源 （正职）'!A:E,5,FALSE) -> 5.4 | L9: =K9+I9+H9 -> 9.9 | M9: =(IF(F9>2,200+INT((F9-2)/0.5)*50,IF(AND(F9>0,F9<=2),200,0)))*G9 -> 15000 | N9: =G9*50 -> 2500 | O9: =G9*20 -> 1000 | P9: =(H9*5900+I9*3400+K9*300)/G9 -> 353.4 | U9: =P9/2 -> 176.7
B10: 常规用户 （普通游戏玩家，无身份/职业限制要求） | C10: 实验室测试/座谈会 （广/杭/沪地区） | D10: P3单独执行 | E10: 二级难度 | F10: ='①【国内】研究资源成本估算 (v1.0)'!G7 -> 3 | G10: ='①【国内】研究资源成本估算 (v1.0)'!J7 -> 50 | H10: =VLOOKUP(G10,'【国内】常规用户招募-数据源 （正职）'!L:P,2,FALSE) -> 0.5 | I10: =VLOOKUP(G10,'【国内】常规用户招募-数据源 （正职）'!L:P,4,FALSE) -> 4.3 | J10: 0 | K10: =VLOOKUP(G10,'【国内】常规用户招募-数据源 （正职）'!L:P,5,FALSE) -> 5.9 | L10: =K10+I10+H10 -> 10.7 | M10: =(IF(F10>2,200+INT((F10-2)/0.5)*50,IF(AND(F10>0,F10<=2),200,0)))*G10 -> 15000 | N10: =G10*50 -> 2500 | O10: =G10*20 -> 1000 | P10: =(H10*5900+I10*3400+K10*300)/G10 -> 386.8 | U10: =P10/2 -> 193.4
B11: 常规用户 （普通游戏玩家，无身份/职业限制要求） | C11: 实验室测试/座谈会 （广/杭/沪地区） | D11: P3单独执行 | E11: 三级难度 | F11: ='①【国内】研究资源成本估算 (v1.0)'!G7 -> 3 | G11: ='①【国内】研究资源成本估算 (v1.0)'!J7 -> 50 | H11: =VLOOKUP(G11,'【国内】常规用户招募-数据源 （正职）'!V:Z,2,FALSE) -> 0.8 | I11: =VLOOKUP(G11,'【国内】常规用户招募-数据源 （正职）'!V:Z,4,FALSE) -> 6 | J11: 0 | K11: =VLOOKUP(G11,'【国内】常规用户招募-数据源 （正职）'!V:Z,5,FALSE) -> 7.9 | L11: =K11+I11+H11 -> 14.7 | M11: =(IF(F11>2,200+INT((F11-2)/0.5)*50,IF(AND(F11>0,F11<=2),200,0)))*G11 -> 15000 | N11: =G11*50 -> 2500 | O11: =G11*20 -> 1000 | P11: =(H11*5900+I11*3400+K11*300)/G11 -> 549.8 | U11: =P11/2 -> 274.9
B12: 常规用户 （普通游戏玩家，无身份/职业限制要求） | C12: 实验室测试/座谈会 （广/杭/沪地区） | D12: P3单独执行 | E12: 四级难度 | F12: ='①【国内】研究资源成本估算 (v1.0)'!G7 -> 3 | G12: ='①【国内】研究资源成本估算 (v1.0)'!J7 -> 50 | H12: =VLOOKUP(G12,'【国内】常规用户招募-数据源 （正职）'!AF:AJ,2,FALSE) -> 1 | I12: =VLOOKUP(G12,'【国内】常规用户招募-数据源 （正职）'!AF:AJ,4,FALSE) -> 7.1 | J12: 0 | K12: =VLOOKUP(G12,'【国内】常规用户招募-数据源 （正职）'!AF:AJ,5,FALSE) -> 8.4 | L12: =K12+I12+H12 -> 16.5 | M12: =(IF(F12>2,200+INT((F12-2)/0.5)*50,IF(AND(F12>0,F12<=2),200,0)))*G12 -> 15000 | N12: =G12*50 -> 2500 | O12: =G12*20 -> 1000 | P12: =(H12*5900+I12*3400+K12*300)/G12 -> 651.2 | U12: =P12/2 -> 325.6
B13: 常规用户 （普通游戏玩家，无身份/职业限制要求） | C13: 实验室测试/座谈会 （广/杭/沪地区） | D13: P3单独执行 | E13: 五级难度 | F13: ='①【国内】研究资源成本估算 (v1.0)'!G7 -> 3 | G13: ='①【国内】研究资源成本估算 (v1.0)'!J7 -> 50 | H13: =VLOOKUP(G13,'【国内】常规用户招募-数据源 （正职）'!AP:AT,2,FALSE) -> 1 | I13: =VLOOKUP(G13,'【国内】常规用户招募-数据源 （正职）'!AP:AT,4,FALSE) -> 7.5 | J13: 0 | K13: =VLOOKUP(G13,'【国内】常规用户招募-数据源 （正职）'!AP:AT,5,FALSE) -> 7.2 | L13: =K13+I13+H13 -> 15.7 | M13: =(IF(F13>2,200+INT((F13-2)/0.5)*50,IF(AND(F13>0,F13<=2),200,0)))*G13 -> 15000 | N13: =G13*50 -> 2500 | O13: =G13*20 -> 1000 | P13: =(H13*5900+I13*3400+K13*300)/G13 -> 671.2 | U13: =P13/2 -> 335.6
B14: 常规用户 （普通游戏玩家，无身份/职业限制要求） | C14: 实验室测试/座谈会 （广/杭/沪地区） | D14: 混合执行 | E14: 一级难度 | F14: ='①【国内】研究资源成本估算 (v1.0)'!G7 -> 3 | G14: ='①【国内】研究资源成本估算 (v1.0)'!J7 -> 50 | H14: =VLOOKUP(G14,'【国内】常规用户招募-数据源(正职+OP混合执行）'!A:F,2,FALSE) -> 0.39 | I14: =VLOOKUP(G14,'【国内】常规用户招募-数据源(正职+OP混合执行）'!A:F,3,FALSE) -> 2.52 | J14: =VLOOKUP(G14,'【国内】常规用户招募-数据源(正职+OP混合执行）'!A:F,4,FALSE) -> 4.3175 | K14: =VLOOKUP(G14,'【国内】常规用户招募-数据源(正职+OP混合执行）'!A:F,5,FALSE) -> 5.4 | L14: =K14+J14+H14 -> 10.1075 | M14: =(IF(F14>2,200+INT((F14-2)/0.5)*50,IF(AND(F14>0,F14<=2),200,0)))*G14 -> 15000 | N14: =G14*50 -> 2500 | O14: =G14*20 -> 1000 | P14: =(H14*5900+I14*3400+J14*1200+K14*300)/G14 -> 353.4 | U14: =P14/2 -> 176.7
B15: 常规用户 （普通游戏玩家，无身份/职业限制要求） | C15: 实验室测试/座谈会 （广/杭/沪地区） | D15: 混合执行 | E15: 二级难度 | F15: ='①【国内】研究资源成本估算 (v1.0)'!G7 -> 3 | G15: ='①【国内】研究资源成本估算 (v1.0)'!J7 -> 50 | H15: =VLOOKUP(G15,'【国内】常规用户招募-数据源(正职+OP混合执行）'!N:S,2,FALSE) -> 0.65 | I15: =VLOOKUP(G15,'【国内】常规用户招募-数据源(正职+OP混合执行）'!N:S,3,FALSE) -> 2.58 | J15: =VLOOKUP(G15,'【国内】常规用户招募-数据源(正职+OP混合执行）'!N:S,4,FALSE) -> 4.1653333 | K15: =VLOOKUP(G15,'【国内】常规用户招募-数据源(正职+OP混合执行）'!N:S,5,FALSE) -> 5.782 | L15: =K15+J15+H15 -> 10.597333 | M15: =(IF(F15>2,200+INT((F15-2)/0.5)*50,IF(AND(F15>0,F15<=2),200,0)))*G15 -> 15000 | N15: =G15*50 -> 2500 | O15: =G15*20 -> 1000 | P15: =(H15*5900+I15*3400+J15*1200+K15*300)/G15 -> 386.8 | U15: =P15/2 -> 193.4
B16: 常规用户 （普通游戏玩家，无身份/职业限制要求） | C16: 实验室测试/座谈会 （广/杭/沪地区） | D16: 混合执行 | E16: 三级难度 | F16: ='①【国内】研究资源成本估算 (v1.0)'!G7 -> 3 | G16: ='①【国内】研究资源成本估算 (v1.0)'!J7 -> 50 | H16: =VLOOKUP(G16,'【国内】常规用户招募-数据源(正职+OP混合执行）'!Z:AE,2,FALSE) -> 1.04 | I16: =VLOOKUP(G16,'【国内】常规用户招募-数据源(正职+OP混合执行）'!Z:AE,3,FALSE) -> 3.6 | J16: =VLOOKUP(G16,'【国内】常规用户招募-数据源(正职+OP混合执行）'!Z:AE,4,FALSE) -> 5.225 | K16: =VLOOKUP(G16,'【国内】常规用户招募-数据源(正职+OP混合执行）'!Z:AE,5,FALSE) -> 9.48 | L16: =K16+J16+H16 -> 15.745 | M16: =(IF(F16>2,200+INT((F16-2)/0.5)*50,IF(AND(F16>0,F16<=2),200,0)))*G16 -> 15000 | N16: =G16*50 -> 2500 | O16: =G16*20 -> 1000 | P16: =(H16*5900+I16*3400+J16*1200+K16*300)/G16 -> 549.8 | U16: =P16/2 -> 274.9
B17: 常规用户 （普通游戏玩家，无身份/职业限制要求） | C17: 实验室测试/座谈会 （广/杭/沪地区） | D17: 混合执行 | E17: 四级难度 | F17: ='①【国内】研究资源成本估算 (v1.0)'!G7 -> 3 | G17: ='①【国内】研究资源成本估算 (v1.0)'!J7 -> 50 | H17: =VLOOKUP(G17,'【国内】常规用户招募-数据源(正职+OP混合执行）'!AL:AP,2,FALSE) -> 1.3 | I17: =VLOOKUP(G17,'【国内】常规用户招募-数据源(正职+OP混合执行）'!AL:AP,3,FALSE) -> 4.26 | J17: =VLOOKUP(G17,'【国内】常规用户招募-数据源(正职+OP混合执行）'!AL:AP,4,FALSE) -> 6.4036667 | K17: =VLOOKUP(G17,'【国内】常规用户招募-数据源(正职+OP混合执行）'!AL:AP,5,FALSE) -> 9.072 | L17: =K17+J17+H17 -> 16.775667 | M17: =(IF(F17>2,200+INT((F17-2)/0.5)*50,IF(AND(F17>0,F17<=2),200,0)))*G17 -> 15000 | N17: =G17*50 -> 2500 | O17: =G17*20 -> 1000 | P17: =(H17*5900+I17*3400+J17*1200+K17*300)/G17 -> 651.2 | U17: =P17/2 -> 325.6
B18: 常规用户 （普通游戏玩家，无身份/职业限制要求） | C18: 实验室测试/座谈会 （广/杭/沪地区） | D18: 混合执行 | E18: 五级难度 | F18: ='①【国内】研究资源成本估算 (v1.0)'!G7 -> 3 | G18: ='①【国内】研究资源成本估算 (v1.0)'!J7 -> 50 | H18: =VLOOKUP(G18,'【国内】常规用户招募-数据源(正职+OP混合执行）'!AX:BB,2,FALSE) -> 1.3 | I18: =VLOOKUP(G18,'【国内】常规用户招募-数据源(正职+OP混合执行）'!AX:BB,3,FALSE) -> 4.5 | J18: =VLOOKUP(G18,'【国内】常规用户招募-数据源(正职+OP混合执行）'!AX:BB,4,FALSE) -> 6.845 | K18: =VLOOKUP(G18,'【国内】常规用户招募-数据源(正职+OP混合执行）'!AX:BB,5,FALSE) -> 7.92 | L18: =K18+J18+H18 -> 16.065 | M18: =(IF(F18>2,200+INT((F18-2)/0.5)*50,IF(AND(F18>0,F18<=2),200,0)))*G18 -> 15000 | N18: =G18*50 -> 2500 | O18: =G18*20 -> 1000 | P18: =(H18*5900+I18*3400+J18*1200+K18*300)/G18 -> 671.2 | Q18: P5 | R18: P3 | S18: OP | T18: 实习生 | U18: =P18/2 -> 335.6
A19: GT006 | B19: 常规用户 （普通游戏玩家，无身份/职业限制要求） | C19: 入户调研 （广/杭/沪地区） | D19: OP单独执行 | E19: 一级难度 | F19: ='①【国内】研究资源成本估算 (v1.0)'!$G$8 -> 1.5 | G19: ='①【国内】研究资源成本估算 (v1.0)'!$J$8 -> 10 | H19: =Q19 -> 0 | I19: =R19*1.1 -> 0 | J19: =S19*1.12 -> 2.7533333 | K19: =T19 -> 3 | L19: =K19+J19+H19 -> 5.7533333 | M19: =(IF(F19>2,300+INT((F19-2)/0.5)*70,IF(AND(F19>0,F19<=2),300,0)))*G19 -> 3000 | N19: =G19*60 -> 600 | O19: =G19*20 -> 200 | P19: =(H19*5900+J19*1200+K19*300)/G19 -> 420.4 | Q19: =VLOOKUP($G$19,'【国内】常规用户招募-数据源 (OP)'!$A:$E,2,FALSE) -> 0 | R19: =VLOOKUP($G$19,'【国内】常规用户招募-数据源 (OP)'!$A:$E,3,FALSE) -> 0 | S19: =VLOOKUP($G$19,'【国内】常规用户招募-数据源 (OP)'!$A:$E,4,FALSE) -> 2.4583333 | T19: =VLOOKUP($G$19,'【国内】常规用户招募-数据源 (OP)'!$A:$E,5,FALSE) -> 3 | U19: =P19/2 -> 210.2
A20: GT007 | B20: 常规用户 （普通游戏玩家，无身份/职业限制要求） | C20: 入户调研 （广/杭/沪地区） | D20: OP单独执行 | E20: 二级难度 | F20: ='①【国内】研究资源成本估算 (v1.0)'!$G$8 -> 1.5 | G20: ='①【国内】研究资源成本估算 (v1.0)'!$J$8 -> 10 | H20: =Q20 -> 0 | I20: =R20*1.1 -> 0 | J20: =S20*1.12 -> 3.444 | K20: =T20 -> 3 | L20: =K20+J20+H20 -> 6.444 | M20: =(IF(F20>2,300+INT((F20-2)/0.5)*70,IF(AND(F20>0,F20<=2),300,0)))*G20 -> 3000 | N20: =G20*60 -> 600 | O20: =G20*20 -> 200 | P20: =(H20*5900+J20*1200+K20*300)/G20 -> 503.28 | Q20: =VLOOKUP($G$20,'【国内】常规用户招募-数据源 (OP)'!$N:$R,2,FALSE) -> 0 | R20: =VLOOKUP($G$20,'【国内】常规用户招募-数据源 (OP)'!$N:$R,3,FALSE) -> 0 | S20: =VLOOKUP($G$20,'【国内】常规用户招募-数据源 (OP)'!$N:$R,4,FALSE) -> 3.075 | T20: =VLOOKUP($G$20,'【国内】常规用户招募-数据源 (OP)'!$N:$R,5,FALSE) -> 3 | U20: =P20/2 -> 251.64
A21: GT008 | B21: 常规用户 （普通游戏玩家，无身份/职业限制要求） | C21: 入户调研 （广/杭/沪地区） | D21: OP单独执行 | E21: 三级难度 | F21: ='①【国内】研究资源成本估算 (v1.0)'!$G$8 -> 1.5 | G21: ='①【国内】研究资源成本估算 (v1.0)'!$J$8 -> 10 | H21: =Q21 -> 0 | I21: =R21*1.1 -> 0 | J21: =S21*1.12 -> 4.256 | K21: =T21 -> 3.4 | L21: =K21+J21+H21 -> 7.656 | M21: =(IF(F21>2,300+INT((F21-2)/0.5)*70,IF(AND(F21>0,F21<=2),300,0)))*G21 -> 3000 | N21: =G21*60 -> 600 | O21: =G21*20 -> 200 | P21: =(H21*5900+J21*1200+K21*300)/G21 -> 612.72 | Q21: =VLOOKUP($G$21,'【国内】常规用户招募-数据源 (OP)'!$Z:$AD,2,FALSE) -> 0 | R21: =VLOOKUP($G$21,'【国内】常规用户招募-数据源 (OP)'!$Z:$AD,3,FALSE) -> 0 | S21: =VLOOKUP($G$21,'【国内】常规用户招募-数据源 (OP)'!$Z:$AD,4,FALSE) -> 3.8 | T21: =VLOOKUP($G$21,'【国内】常规用户招募-数据源 (OP)'!$Z:$AD,5,FALSE) -> 3.4 | U21: =P21/2 -> 306.36
A22: GT009 | B22: 常规用户 （普通游戏玩家，无身份/职业限制要求） | C22: 入户调研 （广/杭/沪地区） | D22: OP单独执行 | E22: 四级难度 | F22: ='①【国内】研究资源成本估算 (v1.0)'!$G$8 -> 1.5 | G22: ='①【国内】研究资源成本估算 (v1.0)'!$J$8 -> 10 | H22: =Q22 -> 0.22 | I22: =R22*1.1 -> 0 | J22: =S22*1.12 -> 3.9203733 | K22: =T22 -> 3.672 | L22: =K22+J22+H22 -> 7.8123733 | M22: =(IF(F22>2,300+INT((F22-2)/0.5)*70,IF(AND(F22>0,F22<=2),300,0)))*G22 -> 3000 | N22: =G22*60 -> 600 | O22: =G22*20 -> 200 | P22: =(H22*5900+J22*1200+K22*300)/G22 -> 710.4048 | Q22: =VLOOKUP($G$22,'【国内】常规用户招募-数据源 (OP)'!$AM:$AQ,2,FALSE) -> 0.22 | R22: =VLOOKUP($G$22,'【国内】常规用户招募-数据源 (OP)'!$AM:$AQ,3,FALSE) -> 0 | S22: =VLOOKUP($G$22,'【国内】常规用户招募-数据源 (OP)'!$AM:$AQ,4,FALSE) -> 3.5003333 | T22: =VLOOKUP($G$22,'【国内】常规用户招募-数据源 (OP)'!$AM:$AQ,5,FALSE) -> 3.672 | U22: =P22/2 -> 355.2024
A23: GT010 | B23: 常规用户 （普通游戏玩家，无身份/职业限制要求） | C23: 入户调研 （广/杭/沪地区） | D23: OP单独执行 | E23: 五级难度 | F23: ='①【国内】研究资源成本估算 (v1.0)'!$G$8 -> 1.5 | G23: ='①【国内】研究资源成本估算 (v1.0)'!$J$8 -> 10 | H23: =Q23 -> 0.23 | I23: =R23*1.1 -> 0 | J23: =S23*1.12 -> 4.8141333 | K23: =T23 -> 3.3 | L23: =K23+J23+H23 -> 8.3441333 | M23: =(IF(F23>2,300+INT((F23-2)/0.5)*70,IF(AND(F23>0,F23<=2),300,0)))*G23 -> 3000 | N23: =G23*60 -> 600 | O23: =G23*20 -> 200 | P23: =(H23*5900+J23*1200+K23*300)/G23 -> 812.396 | Q23: =VLOOKUP($G$23,'【国内】常规用户招募-数据源 (OP)'!$AZ:$BF,2,FALSE) -> 0.23 | R23: =VLOOKUP($G$23,'【国内】常规用户招募-数据源 (OP)'!$AZ:$BF,3,FALSE) -> 0 | S23: =VLOOKUP($G$23,'【国内】常规用户招募-数据源 (OP)'!$AZ:$BF,4,FALSE) -> 4.2983333 | T23: =VLOOKUP($G$23,'【国内】常规用户招募-数据源 (OP)'!$AZ:$BF,5,FALSE) -> 3.3 | U23: =P23/2 -> 406.198
B24: 常规用户 （普通游戏玩家，无身份/职业限制要求） | C24: 入户调研 （广/杭/沪地区） | D24: P3单独执行 | E24: 一级难度 | F24: ='①【国内】研究资源成本估算 (v1.0)'!$G$8 -> 1.5 | G24: ='①【国内】研究资源成本估算 (v1.0)'!$J$8 -> 10 | H24: =Q24 -> 0 | I24: =R24*1.1 -> 1.1 | J24: =S24 -> 0 | K24: =T24 -> 1.5 | L24: =K24+J24+H24 -> 1.5 | M24: =(IF(F24>2,300+INT((F24-2)/0.5)*70,IF(AND(F24>0,F24<=2),300,0)))*G24 -> 3000 | N24: =G24*60 -> 600 | O24: =G24*20 -> 200 | P24: =(H24*5900+I24*3400+K24*300)/G24 -> 419 | Q24: =VLOOKUP($G$24,'【国内】常规用户招募-数据源 （正职）'!$A:$E,2,FALSE) -> 0 | R24: =VLOOKUP($G$24,'【国内】常规用户招募-数据源 （正职）'!$A:$E,4,FALSE) -> 1 | S24: 0 | T24: =VLOOKUP($G$24,'【国内】常规用户招募-数据源 （正职）'!$A:$E,5,FALSE) -> 1.5 | U24: =P24/2 -> 209.5
B25: 常规用户 （普通游戏玩家，无身份/职业限制要求） | C25: 入户调研 （广/杭/沪地区） | D25: P3单独执行 | E25: 二级难度 | F25: ='①【国内】研究资源成本估算 (v1.0)'!$G$8 -> 1.5 | G25: ='①【国内】研究资源成本估算 (v1.0)'!$J$8 -> 10 | H25: =Q25 -> 0 | I25: =R25*1.1 -> 1.32 | J25: =S25 -> 0 | K25: =T25 -> 1.7 | L25: =K25+I25+H25 -> 3.02 | M25: =(IF(F25>2,300+INT((F25-2)/0.5)*70,IF(AND(F25>0,F25<=2),300,0)))*G25 -> 3000 | N25: =G25*60 -> 600 | O25: =G25*20 -> 200 | P25: =(H25*5900+I25*3400+K25*300)/G25 -> 499.8 | Q25: =VLOOKUP($G$25,'【国内】常规用户招募-数据源 （正职）'!$L:$P,2,FALSE) -> 0 | R25: =VLOOKUP($G$25,'【国内】常规用户招募-数据源 （正职）'!$L:$P,4,FALSE) -> 1.2 | S25: 0 | T25: =VLOOKUP($G$25,'【国内】常规用户招募-数据源 （正职）'!$L:$P,5,FALSE) -> 1.7 | U25: =P25/2 -> 249.9
B26: 常规用户 （普通游戏玩家，无身份/职业限制要求） | C26: 入户调研 （广/杭/沪地区） | D26: P3单独执行 | E26: 三级难度 | F26: ='①【国内】研究资源成本估算 (v1.0)'!$G$8 -> 1.5 | G26: ='①【国内】研究资源成本估算 (v1.0)'!$J$8 -> 10 | H26: =Q26 -> 0 | I26: =R26*1.1 -> 1.65 | J26: =S26 -> 0 | K26: =T26 -> 1.6 | L26: =K26+I26+H26 -> 3.25 | M26: =(IF(F26>2,300+INT((F26-2)/0.5)*70,IF(AND(F26>0,F26<=2),300,0)))*G26 -> 3000 | N26: =G26*60 -> 600 | O26: =G26*20 -> 200 | P26: =(H26*5900+I26*3400+K26*300)/G26 -> 609 | Q26: =VLOOKUP($G$26,'【国内】常规用户招募-数据源 （正职）'!$V:$Z,2,FALSE) -> 0 | R26: =VLOOKUP($G$26,'【国内】常规用户招募-数据源 （正职）'!$V:$Z,4,FALSE) -> 1.5 | S26: 0 | T26: =VLOOKUP($G$26,'【国内】常规用户招募-数据源 （正职）'!$V:$Z,5,FALSE) -> 1.6 | U26: =P26/2 -> 304.5
B27: 常规用户 （普通游戏玩家，无身份/职业限制要求） | C27: 入户调研 （广/杭/沪地区） | D27: P3单独执行 | E27: 四级难度 | F27: ='①【国内】研究资源成本估算 (v1.0)'!$G$8 -> 1.5 | G27: ='①【国内】研究资源成本估算 (v1.0)'!$J$8 -> 10 | H27: =Q27 -> 0.1 | I27: =R27*1.1 -> 1.76 | J27: =S27 -> 0 | K27: =T27 -> 1.9 | L27: =K27+I27+H27 -> 3.76 | M27: =(IF(F27>2,300+INT((F27-2)/0.5)*70,IF(AND(F27>0,F27<=2),300,0)))*G27 -> 3000 | N27: =G27*60 -> 600 | O27: =G27*20 -> 200 | P27: =(H27*5900+I27*3400+K27*300)/G27 -> 714.4 | Q27: =VLOOKUP($G$27,'【国内】常规用户招募-数据源 （正职）'!$AF:$AJ,2,FALSE) -> 0.1 | R27: =VLOOKUP($G$27,'【国内】常规用户招募-数据源 （正职）'!$AF:$AJ,4,FALSE) -> 1.6 | S27: 0 | T27: =VLOOKUP($G$27,'【国内】常规用户招募-数据源 （正职）'!$AF:$AJ,5,FALSE) -> 1.9 | U27: =P27/2 -> 357.2
B28: 常规用户 （普通游戏玩家，无身份/职业限制要求） | C28: 入户调研 （广/杭/沪地区） | D28: P3单独执行 | E28: 五级难度 | F28: ='①【国内】研究资源成本估算 (v1.0)'!$G$8 -> 1.5 | G28: ='①【国内】研究资源成本估算 (v1.0)'!$J$8 -> 10 | H28: =Q28 -> 0.1 | I28: =R28*1.1 -> 2.0625 | J28: =S28 -> 0 | K28: =T28 -> 1.8 | L28: =K28+I28+H28 -> 3.9625 | M28: =(IF(F28>2,300+INT((F28-2)/0.5)*70,IF(AND(F28>0,F28<=2),300,0)))*G28 -> 3000 | N28: =G28*60 -> 600 | O28: =G28*20 -> 200 | P28: =(H28*5900+I28*3400+K28*300)/G28 -> 814.25 | Q28: =VLOOKUP($G$28,'【国内】常规用户招募-数据源 （正职）'!$AP:$AT,2,FALSE) -> 0.1 | R28: =VLOOKUP($G$28,'【国内】常规用户招募-数据源 （正职）'!$AP:$AT,4,FALSE) -> 1.875 | S28: 0 | T28: =VLOOKUP($G$28,'【国内】常规用户招募-数据源 （正职）'!$AP:$AT,5,FALSE) -> 1.8 | U28: =P28/2 -> 407.125
B29: 常规用户 （普通游戏玩家，无身份/职业限制要求） | C29: 入户调研 （广/杭/沪地区） | D29: 混合执行 | E29: 一级难度 | F29: ='①【国内】研究资源成本估算 (v1.0)'!$G$8 -> 1.5 | G29: ='①【国内】研究资源成本估算 (v1.0)'!$J$8 -> 10 | H29: =Q29 -> 0 | I29: =R29*1.1 -> 0.66 | J29: =S29*1.1 -> 1.2466667 | K29: =T29*1.2 -> 1.8 | L29: =K29+J29+H29 -> 3.0466667 | M29: =(IF(F29>2,300+INT((F29-2)/0.5)*70,IF(AND(F29>0,F29<=2),300,0)))*G29 -> 3000 | N29: =G29*60 -> 600 | O29: =G29*20 -> 200 | P29: =(H29*5900+I29*3400+J29*1200+K29*300)/G29 -> 428 | Q29: =VLOOKUP(G29,'【国内】常规用户招募-数据源(正职+OP混合执行）'!A:E,2,FALSE) -> 0 | R29: =VLOOKUP(G29,'【国内】常规用户招募-数据源(正职+OP混合执行）'!A:E,3,FALSE) -> 0.6 | S29: =VLOOKUP(G29,'【国内】常规用户招募-数据源(正职+OP混合执行）'!A:E,4,FALSE) -> 1.1333333 | T29: =VLOOKUP(G29,'【国内】常规用户招募-数据源(正职+OP混合执行）'!A:E,5,FALSE) -> 1.5 | U29: =P29/2 -> 214
B30: 常规用户 （普通游戏玩家，无身份/职业限制要求） | C30: 入户调研 （广/杭/沪地区） | D30: 混合执行 | E30: 二级难度 | F30: ='①【国内】研究资源成本估算 (v1.0)'!$G$8 -> 1.5 | G30: ='①【国内】研究资源成本估算 (v1.0)'!$J$8 -> 10 | H30: =Q30 -> 0 | I30: =R30*1.1 -> 0.792 | J30: =S30*1.1 -> 1.50535 | K30: =T30*1.2 -> 1.9992 | L30: =K30+J30+H30 -> 3.50455 | M30: =(IF(F30>2,300+INT((F30-2)/0.5)*70,IF(AND(F30>0,F30<=2),300,0)))*G30 -> 3000 | N30: =G30*60 -> 600 | O30: =G30*20 -> 200 | P30: =(H30*5900+I30*3400+J30*1200+K30*300)/G30 -> 509.898 | Q30: =VLOOKUP(G30,'【国内】常规用户招募-数据源(正职+OP混合执行）'!N:R,2,FALSE) -> 0 | R30: =VLOOKUP(G30,'【国内】常规用户招募-数据源(正职+OP混合执行）'!N:R,3,FALSE) -> 0.72 | S30: =VLOOKUP(G30,'【国内】常规用户招募-数据源(正职+OP混合执行）'!N:R,4,FALSE) -> 1.3685 | T30: =VLOOKUP(G30,'【国内】常规用户招募-数据源(正职+OP混合执行）'!N:R,5,FALSE) -> 1.666 | U30: =P30/2 -> 254.949
B31: 常规用户 （普通游戏玩家，无身份/职业限制要求） | C31: 入户调研 （广/杭/沪地区） | D31: 混合执行 | E31: 三级难度 | F31: ='①【国内】研究资源成本估算 (v1.0)'!$G$8 -> 1.5 | G31: ='①【国内】研究资源成本估算 (v1.0)'!$J$8 -> 10 | H31: =Q31 -> 0 | I31: =R31*1.1 -> 0.99 | J31: =S31*1.1 -> 1.782 | K31: =T31*1.2 -> 2.304 | L31: =K31+J31+H31 -> 4.086 | M31: =(IF(F31>2,300+INT((F31-2)/0.5)*70,IF(AND(F31>0,F31<=2),300,0)))*G31 -> 3000 | N31: =G31*60 -> 600 | O31: =G31*20 -> 200 | P31: =(H31*5900+I31*3400+J31*1200+K31*300)/G31 -> 619.56 | Q31: =VLOOKUP(G31,'【国内】常规用户招募-数据源(正职+OP混合执行）'!Z:AD,2,FALSE) -> 0 | R31: =VLOOKUP(G31,'【国内】常规用户招募-数据源(正职+OP混合执行）'!Z:AD,3,FALSE) -> 0.9 | S31: =VLOOKUP(G31,'【国内】常规用户招募-数据源(正职+OP混合执行）'!Z:AD,4,FALSE) -> 1.62 | T31: =VLOOKUP(G31,'【国内】常规用户招募-数据源(正职+OP混合执行）'!Z:AD,5,FALSE) -> 1.92 | U31: =P31/2 -> 309.78
B32: 常规用户 （普通游戏玩家，无身份/职业限制要求） | C32: 入户调研 （广/杭/沪地区） | D32: 混合执行 | E32: 四级难度 | F32: ='①【国内】研究资源成本估算 (v1.0)'!$G$8 -> 1.5 | G32: ='①【国内】研究资源成本估算 (v1.0)'!$J$8 -> 10 | H32: =Q32 -> 0.13 | I32: =R32*1.1 -> 1.056 | J32: =S32*1.1 -> 1.7906167 | K32: =T32*1.2 -> 2.4624 | L32: =K32+J32+H32 -> 4.3830167 | M32: =(IF(F32>2,300+INT((F32-2)/0.5)*70,IF(AND(F32>0,F32<=2),300,0)))*G32 -> 3000 | N32: =G32*60 -> 600 | O32: =G32*20 -> 200 | P32: =(H32*5900+I32*3400+J32*1200+K32*300)/G32 -> 724.486 | Q32: =VLOOKUP(G32,'【国内】常规用户招募-数据源(正职+OP混合执行）'!AL:AP,2,FALSE) -> 0.13 | R32: =VLOOKUP(G32,'【国内】常规用户招募-数据源(正职+OP混合执行）'!AL:AP,3,FALSE) -> 0.96 | S32: =VLOOKUP(G32,'【国内】常规用户招募-数据源(正职+OP混合执行）'!AL:AP,4,FALSE) -> 1.6278333 | T32: =VLOOKUP(G32,'【国内】常规用户招募-数据源(正职+OP混合执行）'!AL:AP,5,FALSE) -> 2.052 | U32: =P32/2 -> 362.243
B33: 常规用户 （普通游戏玩家，无身份/职业限制要求） | C33: 入户调研 （广/杭/沪地区） | D33: 混合执行 | E33: 五级难度 | F33: ='①【国内】研究资源成本估算 (v1.0)'!$G$8 -> 1.5 | G33: ='①【国内】研究资源成本估算 (v1.0)'!$J$8 -> 10 | H33: =Q33 -> 0.13 | I33: =R33*1.1 -> 1.2375 | J33: =S33*1.1 -> 2.12575 | K33: =T33*1.2 -> 2.376 | L33: =K33+J33+H33 -> 4.63175 | M33: =(IF(F33>2,300+INT((F33-2)/0.5)*70,IF(AND(F33>0,F33<=2),300,0)))*G33 -> 3000 | N33: =G33*60 -> 600 | O33: =G33*20 -> 200 | P33: =(H33*5900+I33*3400+J33*1200+K33*300)/G33 -> 823.82 | Q33: =VLOOKUP($G33,'【国内】常规用户招募-数据源(正职+OP混合执行）'!AX:BB,2,FALSE) -> 0.13 | R33: =VLOOKUP(G33,'【国内】常规用户招募-数据源(正职+OP混合执行）'!AX:BB,3,FALSE) -> 1.125 | S33: =VLOOKUP(G33,'【国内】常规用户招募-数据源(正职+OP混合执行）'!AX:BB,4,FALSE) -> 1.9325 | T33: =VLOOKUP($G33,'【国内】常规用户招募-数据源(正职+OP混合执行）'!AX:BB,5,FALSE) -> 1.98 | U33: =P33/2 -> 411.91
A34: GT012 | B34: 常规用户 （普通游戏玩家，无身份/职业限制要求） | C34: 实验室测试/座谈会 （广/杭/沪以外地区） | D34: OP单独执行 | E34: 一级难度 | F34: ='①【国内】研究资源成本估算 (v1.0)'!$G$9 -> 3 | G34: ='①【国内】研究资源成本估算 (v1.0)'!$J$9 -> 20 | H34: =Q34*1.1 -> 0.1925 | I34: =R34 -> 0 | J34: =S34*1.16 -> 5.5945833 | K34: =T34*1.1 -> 4.51 | L34: =K34+J34+H34 -> 10.297083 | M34: =(IF(F34>2,200+INT((F34-2)/0.5)*50,IF(AND(F34>0,F34<=2),200,0)))*G34 -> 6000 | N34: =G34*100 -> 2000 | O34: =G34*20 -> 400 | P34: =(H34*5900+I34*3400+J34*1200+K34*300)/G34 -> 460.1125 | Q34: =VLOOKUP(G34,'【国内】常规用户招募-数据源 (OP)'!A:E,2,FALSE) -> 0.175 | R34: =VLOOKUP(G34,'【国内】常规用户招募-数据源 (OP)'!A:E,3,FALSE) -> 0 | S34: =VLOOKUP(G34,'【国内】常规用户招募-数据源 (OP)'!A:E,4,FALSE) -> 4.8229167 | T34: =VLOOKUP(G34,'【国内】常规用户招募-数据源 (OP)'!A:E,5,FALSE) -> 4.1 | U34: =P34/2 -> 230.05625
A35: GT013 | B35: 常规用户 （普通游戏玩家，无身份/职业限制要求） | C35: 实验室测试/座谈会 （广/杭/沪以外地区） | D35: OP单独执行 | E35: 二级难度 | F35: ='①【国内】研究资源成本估算 (v1.0)'!$G$9 -> 3 | G35: ='①【国内】研究资源成本估算 (v1.0)'!$J$9 -> 20 | H35: =Q35*1.1 -> 0.396 | I35: =R35 -> 0 | J35: =S35*1.16 -> 5.2912337 | K35: =T35*1.1 -> 5.39847 | L35: =K35+J35+H35 -> 11.085704 | M35: =(IF(F35>2,200+INT((F35-2)/0.5)*50,IF(AND(F35>0,F35<=2),200,0)))*G35 -> 6000 | N35: =G35*100 -> 2000 | O35: =G35*20 -> 400 | P35: =(H35*5900+I35*3400+J35*1200+K35*300)/G35 -> 515.27107 | Q35: =VLOOKUP(G35,'【国内】常规用户招募-数据源 (OP)'!N:R,2,FALSE) -> 0.36 | R35: =VLOOKUP(G35,'【国内】常规用户招募-数据源 (OP)'!N:R,3,FALSE) -> 0 | S35: =VLOOKUP(G35,'【国内】常规用户招募-数据源 (OP)'!N:R,4,FALSE) -> 4.5614083 | T35: =VLOOKUP(G35,'【国内】常规用户招募-数据源 (OP)'!N:R,5,FALSE) -> 4.9077 | U35: =P35/2 -> 257.63554
A36: GT014 | B36: 常规用户 （普通游戏玩家，无身份/职业限制要求） | C36: 实验室测试/座谈会 （广/杭/沪以外地区） | D36: OP单独执行 | E36: 三级难度 | F36: ='①【国内】研究资源成本估算 (v1.0)'!$G$9 -> 3 | G36: ='①【国内】研究资源成本估算 (v1.0)'!$J$9 -> 20 | H36: =Q36*1.1 -> 0.44 | I36: =R36 -> 0 | J36: =S36*1.16 -> 6.7376667 | K36: =T36*1.1 -> 5.83 | L36: =K36+J36+H36 -> 13.007667 | M36: =(IF(F36>2,200+INT((F36-2)/0.5)*50,IF(AND(F36>0,F36<=2),200,0)))*G36 -> 6000 | N36: =G36*100 -> 2000 | O36: =G36*20 -> 400 | P36: =(H36*5900+I36*3400+J36*1200+K36*300)/G36 -> 621.51 | Q36: =VLOOKUP(G36,'【国内】常规用户招募-数据源 (OP)'!Z:AD,2,FALSE) -> 0.4 | R36: =VLOOKUP(G36,'【国内】常规用户招募-数据源 (OP)'!Z:AD,3,FALSE) -> 0 | S36: =VLOOKUP(G36,'【国内】常规用户招募-数据源 (OP)'!Z:AD,4,FALSE) -> 5.8083333 | T36: =VLOOKUP(G36,'【国内】常规用户招募-数据源 (OP)'!Z:AD,5,FALSE) -> 5.3 | U36: =P36/2 -> 310.755
A37: GT015 | B37: 常规用户 （普通游戏玩家，无身份/职业限制要求） | C37: 实验室测试/座谈会 （广/杭/沪以外地区） | D37: OP单独执行 | E37: 四级难度 | F37: ='①【国内】研究资源成本估算 (v1.0)'!$G$9 -> 3 | G37: ='①【国内】研究资源成本估算 (v1.0)'!$J$9 -> 20 | H37: =Q37*1.1 -> 0.726 | I37: =R37 -> 0 | J37: =S37*1.16 -> 6.7751733 | K37: =T37*1.1 -> 6.2964 | L37: =K37+J37+H37 -> 13.797573 | M37: =(IF(F37>2,200+INT((F37-2)/0.5)*50,IF(AND(F37>0,F37<=2),200,0)))*G37 -> 6000 | N37: =G37*100 -> 2000 | O37: =G37*20 -> 400 | P37: =(H37*5900+I37*3400+J37*1200+K37*300)/G37 -> 715.1264 | Q37: =VLOOKUP(G37,'【国内】常规用户招募-数据源 (OP)'!AM:AQ,2,FALSE) -> 0.66 | R37: =VLOOKUP(G37,'【国内】常规用户招募-数据源 (OP)'!AM:AQ,3,FALSE) -> 0 | S37: =VLOOKUP(G37,'【国内】常规用户招募-数据源 (OP)'!AM:AQ,4,FALSE) -> 5.8406667 | T37: =VLOOKUP(G37,'【国内】常规用户招募-数据源 (OP)'!AM:AQ,5,FALSE) -> 5.724 | U37: =P37/2 -> 357.5632
A38: GT016 | B38: 常规用户 （普通游戏玩家，无身份/职业限制要求） | C38: 实验室测试/座谈会 （广/杭/沪以外地区） | D38: OP单独执行 | E38: 五级难度 | F38: ='①【国内】研究资源成本估算 (v1.0)'!$G$9 -> 3 | G38: ='①【国内】研究资源成本估算 (v1.0)'!$J$9 -> 20 | H38: =Q38*1.1 -> 0.759 | I38: =R38 -> 0 | J38: =S38*1.16 -> 7.7460083 | K38: =T38*1.1 -> 6.548256 | L38: =K38+J38+H38 -> 15.053264 | M38: =(IF(F38>2,200+INT((F38-2)/0.5)*50,IF(AND(F38>0,F38<=2),200,0)))*G38 -> 6000 | N38: =G38*100 -> 2000 | O38: =G38*20 -> 400 | P38: =(H38*5900+I38*3400+J38*1200+K38*300)/G38 -> 786.88934 | Q38: =VLOOKUP(G38,'【国内】常规用户招募-数据源 (OP)'!AZ:BD,2,FALSE) -> 0.69 | R38: =VLOOKUP(G38,'【国内】常规用户招募-数据源 (OP)'!AZ:BD,3,FALSE) -> 0 | S38: =VLOOKUP(G38,'【国内】常规用户招募-数据源 (OP)'!AZ:BD,4,FALSE) -> 6.6775933 | T38: =VLOOKUP(G38,'【国内】常规用户招募-数据源 (OP)'!AZ:BD,5,FALSE) -> 5.95296 | U38: =P38/2 -> 393.44467
B39: 常规用户 （普通游戏玩家，无身份/职业限制要求） | C39: 实验室测试/座谈会 （广/杭/沪以外地区） | D39: P3单独执行 | E39: 一级难度 | F39: ='①【国内】研究资源成本估算 (v1.0)'!$G$9 -> 3 | G39: ='①【国内】研究资源成本估算 (v1.0)'!$J$9 -> 20 | H39: =Q39*1.1 -> 0.11 | I39: =R39*1.15 -> 2.3 | J39: =S39 -> 0 | K39: =T39*1.1 -> 2.42 | L39: =K39+J39+H39 -> 2.53 | M39: =(IF(F39>2,200+INT((F39-2)/0.5)*50,IF(AND(F39>0,F39<=2),200,0)))*G39 -> 6000 | N39: =G39*100 -> 2000 | O39: =G39*20 -> 400 | P39: =(H39*5900+I39*3400+J39*1200+K39*300)/G39 -> 459.75 | Q39: =VLOOKUP(G39,'【国内】常规用户招募-数据源 （正职）'!A:E,2,FALSE) -> 0.1 | R39: =VLOOKUP(G39,'【国内】常规用户招募-数据源 （正职）'!A:E,4,FALSE) -> 2 | S39: 0 | T39: =VLOOKUP(G39,'【国内】常规用户招募-数据源 （正职）'!A:E,5,FALSE) -> 2.2 | U39: =P39/2 -> 229.875
B40: 常规用户 （普通游戏玩家，无身份/职业限制要求） | C40: 实验室测试/座谈会 （广/杭/沪以外地区） | D40: P3单独执行 | E40: 二级难度 | F40: ='①【国内】研究资源成本估算 (v1.0)'!$G$9 -> 3 | G40: ='①【国内】研究资源成本估算 (v1.0)'!$J$9 -> 20 | H40: =Q40*1.1 -> 0.22 | I40: =R40*1.15 -> 2.415 | J40: =S40 -> 0 | K40: =T40*1.1 -> 2.75 | L40: =K40+J40+H40 -> 2.97 | M40: =(IF(F40>2,200+INT((F40-2)/0.5)*50,IF(AND(F40>0,F40<=2),200,0)))*G40 -> 6000 | N40: =G40*100 -> 2000 | O40: =G40*20 -> 400 | P40: =(H40*5900+I40*3400+J40*1200+K40*300)/G40 -> 516.7 | Q40: =VLOOKUP(G40,'【国内】常规用户招募-数据源 （正职）'!L:P,2,FALSE) -> 0.2 | R40: =VLOOKUP(G40,'【国内】常规用户招募-数据源 （正职）'!L:P,4,FALSE) -> 2.1 | S40: 0 | T40: =VLOOKUP(G40,'【国内】常规用户招募-数据源 （正职）'!L:P,5,FALSE) -> 2.5 | U40: =P40/2 -> 258.35
B41: 常规用户 （普通游戏玩家，无身份/职业限制要求） | C41: 实验室测试/座谈会 （广/杭/沪以外地区） | D41: P3单独执行 | E41: 三级难度 | F41: ='①【国内】研究资源成本估算 (v1.0)'!$G$9 -> 3 | G41: ='①【国内】研究资源成本估算 (v1.0)'!$J$9 -> 20 | H41: =Q41*1.1 -> 0.22 | I41: =R41*1.15 -> 2.99 | J41: =S41 -> 0 | K41: =T41*1.1 -> 3.3 | L41: =K41+J41+H41 -> 3.52 | M41: =(IF(F41>2,200+INT((F41-2)/0.5)*50,IF(AND(F41>0,F41<=2),200,0)))*G41 -> 6000 | N41: =G41*100 -> 2000 | O41: =G41*20 -> 400 | P41: =(H41*5900+I41*3400+J41*1200+K41*300)/G41 -> 622.7 | Q41: =VLOOKUP(G41,'【国内】常规用户招募-数据源 （正职）'!V:Z,2,FALSE) -> 0.2 | R41: =VLOOKUP(G41,'【国内】常规用户招募-数据源 （正职）'!V:Z,4,FALSE) -> 2.6 | S41: 0 | T41: =VLOOKUP(G41,'【国内】常规用户招募-数据源 （正职）'!V:Z,5,FALSE) -> 3 | U41: =P41/2 -> 311.35
B42: 常规用户 （普通游戏玩家，无身份/职业限制要求） | C42: 实验室测试/座谈会 （广/杭/沪以外地区） | D42: P3单独执行 | E42: 四级难度 | F42: ='①【国内】研究资源成本估算 (v1.0)'!$G$9 -> 3 | G42: ='①【国内】研究资源成本估算 (v1.0)'!$J$9 -> 20 | H42: =Q42*1.1 -> 0.33 | I42: =R42*1.15 -> 3.335 | J42: =S42 -> 0 | K42: =T42*1.1 -> 3.63 | L42: =K42+J42+H42 -> 3.96 | M42: =(IF(F42>2,200+INT((F42-2)/0.5)*50,IF(AND(F42>0,F42<=2),200,0)))*G42 -> 6000 | N42: =G42*100 -> 2000 | O42: =G42*20 -> 400 | P42: =(H42*5900+I42*3400+J42*1200+K42*300)/G42 -> 718.75 | Q42: =VLOOKUP(G42,'【国内】常规用户招募-数据源 （正职）'!AF:AJ,2,FALSE) -> 0.3 | R42: =VLOOKUP(G42,'【国内】常规用户招募-数据源 （正职）'!AF:AJ,4,FALSE) -> 2.9 | S42: 0 | T42: =VLOOKUP(G42,'【国内】常规用户招募-数据源 （正职）'!AF:AJ,5,FALSE) -> 3.3 | U42: =P42/2 -> 359.375
B43: 常规用户 （普通游戏玩家，无身份/职业限制要求） | C43: 实验室测试/座谈会 （广/杭/沪以外地区） | D43: P3单独执行 | E43: 五级难度 | F43: ='①【国内】研究资源成本估算 (v1.0)'!$G$9 -> 3 | G43: ='①【国内】研究资源成本估算 (v1.0)'!$J$9 -> 20 | H43: =Q43*1.1 -> 0.33 | I43: =R43*1.15 -> 3.7375 | J43: =S43 -> 0 | K43: =T43*1.1 -> 3.85 | L43: =K43+J43+H43 -> 4.18 | M43: =(IF(F43>2,200+INT((F43-2)/0.5)*50,IF(AND(F43>0,F43<=2),200,0)))*G43 -> 6000 | N43: =G43*100 -> 2000 | O43: =G43*20 -> 400 | P43: =(H43*5900+I43*3400+J43*1200+K43*300)/G43 -> 790.475 | Q43: =VLOOKUP(G43,'【国内】常规用户招募-数据源 （正职）'!AP:AT,2,FALSE) -> 0.3 | R43: =VLOOKUP(G43,'【国内】常规用户招募-数据源 （正职）'!AP:AT,4,FALSE) -> 3.25 | S43: 0 | T43: =VLOOKUP(G43,'【国内】常规用户招募-数据源 （正职）'!AP:AT,5,FALSE) -> 3.5 | U43: =P43/2 -> 395.2375
B44: 常规用户 （普通游戏玩家，无身份/职业限制要求） | C44: 实验室测试/座谈会 （广/杭/沪以外地区） | D44: 混合执行 | E44: 一级难度 | F44: ='①【国内】研究资源成本估算 (v1.0)'!$G$9 -> 3 | G44: ='①【国内】研究资源成本估算 (v1.0)'!$J$9 -> 20 | H44: =Q44 -> 0.13 | I44: =R44*1.15 -> 1.38 | J44: =S44*1.2 -> 2.543 | K44: =T44*1.1 -> 2.42 | L44: =K44+J44+H44 -> 5.093 | M44: =(IF(F44>2,200+INT((F44-2)/0.5)*50,IF(AND(F44>0,F44<=2),200,0)))*G44 -> 6000 | N44: =G44*100 -> 2000 | O44: =G44*20 -> 400 | P44: =(H44*5900+I44*3400+J44*1200+K44*300)/G44 -> 461.83 | Q44: =VLOOKUP(G44,'【国内】常规用户招募-数据源(正职+OP混合执行）'!A:E,2,FALSE) -> 0.13 | R44: =VLOOKUP(G44,'【国内】常规用户招募-数据源(正职+OP混合执行）'!A:E,3,FALSE) -> 1.2 | S44: =VLOOKUP(G44,'【国内】常规用户招募-数据源(正职+OP混合执行）'!A:E,4,FALSE) -> 2.1191667 | T44: =VLOOKUP(G44,'【国内】常规用户招募-数据源(正职+OP混合执行）'!A:E,5,FALSE) -> 2.2 | U44: =P44/2 -> 230.915
B45: 常规用户 （普通游戏玩家，无身份/职业限制要求） | C45: 实验室测试/座谈会 （广/杭/沪以外地区） | D45: 混合执行 | E45: 二级难度 | F45: ='①【国内】研究资源成本估算 (v1.0)'!$G$9 -> 3 | G45: ='①【国内】研究资源成本估算 (v1.0)'!$J$9 -> 20 | H45: =Q45 -> 0.26 | I45: =R45*1.15 -> 1.449 | J45: =S45*1.2 -> 2.517 | K45: =T45*1.1 -> 2.695 | L45: =K45+J45+H45 -> 5.472 | M45: =(IF(F45>2,200+INT((F45-2)/0.5)*50,IF(AND(F45>0,F45<=2),200,0)))*G45 -> 6000 | N45: =G45*100 -> 2000 | O45: =G45*20 -> 400 | P45: =(H45*5900+I45*3400+J45*1200+K45*300)/G45 -> 514.475 | Q45: =VLOOKUP(G45,'【国内】常规用户招募-数据源(正职+OP混合执行）'!N:R,2,FALSE) -> 0.26 | R45: =VLOOKUP(G45,'【国内】常规用户招募-数据源(正职+OP混合执行）'!N:R,3,FALSE) -> 1.26 | S45: =VLOOKUP(G45,'【国内】常规用户招募-数据源(正职+OP混合执行）'!N:R,4,FALSE) -> 2.0975 | T45: =VLOOKUP(G45,'【国内】常规用户招募-数据源(正职+OP混合执行）'!N:R,5,FALSE) -> 2.45 | U45: =P45/2 -> 257.2375
B46: 常规用户 （普通游戏玩家，无身份/职业限制要求） | C46: 实验室测试/座谈会 （广/杭/沪以外地区） | D46: 混合执行 | E46: 三级难度 | F46: ='①【国内】研究资源成本估算 (v1.0)'!$G$9 -> 3 | G46: ='①【国内】研究资源成本估算 (v1.0)'!$J$9 -> 20 | H46: =Q46 -> 0.26 | I46: =R46*1.15 -> 1.794 | J46: =S46*1.2 -> 3.002 | K46: =T46*1.1 -> 3.96 | L46: =K46+J46+H46 -> 7.222 | M46: =(IF(F46>2,200+INT((F46-2)/0.5)*50,IF(AND(F46>0,F46<=2),200,0)))*G46 -> 6000 | N46: =G46*100 -> 2000 | O46: =G46*20 -> 400 | P46: =(H46*5900+I46*3400+J46*1200+K46*300)/G46 -> 621.2 | Q46: =VLOOKUP(G46,'【国内】常规用户招募-数据源(正职+OP混合执行）'!Z:AD,2,FALSE) -> 0.26 | R46: =VLOOKUP(G46,'【国内】常规用户招募-数据源(正职+OP混合执行）'!Z:AD,3,FALSE) -> 1.56 | S46: =VLOOKUP(G46,'【国内】常规用户招募-数据源(正职+OP混合执行）'!Z:AD,4,FALSE) -> 2.5016667 | T46: =VLOOKUP(G46,'【国内】常规用户招募-数据源(正职+OP混合执行）'!Z:AD,5,FALSE) -> 3.6 | U46: =P46/2 -> 310.6
B47: 常规用户 （普通游戏玩家，无身份/职业限制要求） | C47: 实验室测试/座谈会 （广/杭/沪以外地区） | D47: 混合执行 | E47: 四级难度 | F47: ='①【国内】研究资源成本估算 (v1.0)'!$G$9 -> 3 | G47: ='①【国内】研究资源成本估算 (v1.0)'!$J$9 -> 20 | H47: =Q47 -> 0.39 | I47: =R47*1.15 -> 2.001 | J47: =S47*1.2 -> 3.3338 | K47: =T47*1.1 -> 3.9204 | L47: =K47+J47+H47 -> 7.6442 | M47: =(IF(F47>2,200+INT((F47-2)/0.5)*50,IF(AND(F47>0,F47<=2),200,0)))*G47 -> 6000 | N47: =G47*100 -> 2000 | O47: =G47*20 -> 400 | P47: =(H47*5900+I47*3400+J47*1200+K47*300)/G47 -> 714.054 | Q47: =VLOOKUP(G47,'【国内】常规用户招募-数据源(正职+OP混合执行）'!AL:AP,2,FALSE) -> 0.39 | R47: =VLOOKUP(G47,'【国内】常规用户招募-数据源(正职+OP混合执行）'!AL:AP,3,FALSE) -> 1.74 | S47: =VLOOKUP(G47,'【国内】常规用户招募-数据源(正职+OP混合执行）'!AL:AP,4,FALSE) -> 2.7781667 | T47: =VLOOKUP(G47,'【国内】常规用户招募-数据源(正职+OP混合执行）'!AL:AP,5,FALSE) -> 3.564 | U47: =P47/2 -> 357.027
B48: 常规用户 （普通游戏玩家，无身份/职业限制要求） | C48: 实验室测试/座谈会 （广/杭/沪以外地区） | D48: 混合执行 | E48: 五级难度 | F48: ='①【国内】研究资源成本估算 (v1.0)'!$G$9 -> 3 | G48: ='①【国内】研究资源成本估算 (v1.0)'!$J$9 -> 20 | H48: =Q48 -> 0.39 | I48: =R48*1.15 -> 2.2425 | J48: =S48*1.2 -> 3.949 | K48: =T48*1.1 -> 3.63 | L48: =K48+J48+H48 -> 7.969 | M48: =(IF(F48>2,200+INT((F48-2)/0.5)*50,IF(AND(F48>0,F48<=2),200,0)))*G48 -> 6000 | N48: =G48*100 -> 2000 | O48: =G48*20 -> 400 | P48: =(H48*5900+I48*3400+J48*1200+K48*300)/G48 -> 787.665 | Q48: =VLOOKUP($G48,'【国内】常规用户招募-数据源(正职+OP混合执行）'!AX:BB,2,FALSE) -> 0.39 | R48: =VLOOKUP(G48,'【国内】常规用户招募-数据源(正职+OP混合执行）'!AX:BB,3,FALSE) -> 1.95 | S48: =VLOOKUP(G48,'【国内】常规用户招募-数据源(正职+OP混合执行）'!AX:BB,4,FALSE) -> 3.2908333 | T48: =VLOOKUP($G48,'【国内】常规用户招募-数据源(正职+OP混合执行）'!AX:BB,5,FALSE) -> 3.3 | U48: =P48/2 -> 393.8325
A49: GT018 | B49: 常规用户 （普通游戏玩家，无身份/职业限制要求） | C49: 入户调研 （广/杭/沪以外地区） | D49: OP单独执行 | E49: 一级难度 | F49: ='①【国内】研究资源成本估算 (v1.0)'!$G$10 -> 2 | G49: ='①【国内】研究资源成本估算 (v1.0)'!$J$10 -> 20 | H49: =Q49*1.1 -> 0.1925 | I49: =R49*1.2 -> 0 | J49: =S49*1.3 -> 6.2697917 | K49: =T49*1.3 -> 5.33 | L49: =K49+J49+H49 -> 11.792292 | M49: =(IF(F49>2,300+INT((F49-2)/0.5)*70,IF(AND(F49>0,F49<=2),300,0)))*G49 -> 6000 | N49: =G49*150 -> 3000 | O49: =G49*20 -> 400 | P49: =(H49*5900+I49*3400+J49*1200+K49*300)/G49 -> 512.925 | Q49: =VLOOKUP(G49,'【国内】常规用户招募-数据源 (OP)'!A:E,2,FALSE) -> 0.175 | R49: =VLOOKUP(G49,'【国内】常规用户招募-数据源 (OP)'!A:E,3,FALSE) -> 0 | S49: =VLOOKUP(G49,'【国内】常规用户招募-数据源 (OP)'!A:E,4,FALSE) -> 4.8229167 | T49: =VLOOKUP(G49,'【国内】常规用户招募-数据源 (OP)'!A:E,5,FALSE) -> 4.1 | U49: =P49/2 -> 256.4625
A50: GT019 | B50: 常规用户 （普通游戏玩家，无身份/职业限制要求） | C50: 入户调研 （广/杭/沪以外地区） | D50: OP单独执行 | E50: 二级难度 | F50: ='①【国内】研究资源成本估算 (v1.0)'!$G$10 -> 2 | G50: ='①【国内】研究资源成本估算 (v1.0)'!$J$10 -> 20 | H50: =Q50*1.1 -> 0.396 | I50: =R50*1.2 -> 0 | J50: =S50*1.3 -> 5.9298308 | K50: =T50*1.3 -> 6.38001 | L50: =K50+J50+H50 -> 12.705841 | M50: =(IF(F50>2,300+INT((F50-2)/0.5)*70,IF(AND(F50>0,F50<=2),300,0)))*G50 -> 6000 | N50: =G50*150 -> 3000 | O50: =G50*20 -> 400 | P50: =(H50*5900+I50*3400+J50*1200+K50*300)/G50 -> 568.31 | Q50: =VLOOKUP(G50,'【国内】常规用户招募-数据源 (OP)'!N:R,2,FALSE) -> 0.36 | R50: =VLOOKUP(G50,'【国内】常规用户招募-数据源 (OP)'!N:R,3,FALSE) -> 0 | S50: =VLOOKUP(G50,'【国内】常规用户招募-数据源 (OP)'!N:R,4,FALSE) -> 4.5614083 | T50: =VLOOKUP(G50,'【国内】常规用户招募-数据源 (OP)'!N:R,5,FALSE) -> 4.9077 | U50: =P50/2 -> 284.155
A51: GT020 | B51: 常规用户 （普通游戏玩家，无身份/职业限制要求） | C51: 入户调研 （广/杭/沪以外地区） | D51: OP单独执行 | E51: 三级难度 | F51: ='①【国内】研究资源成本估算 (v1.0)'!$G$10 -> 2 | G51: ='①【国内】研究资源成本估算 (v1.0)'!$J$10 -> 20 | H51: =Q51*1.1 -> 0.44 | I51: =R51*1.2 -> 0 | J51: =S51*1.3 -> 7.5508333 | K51: =T51*1.3 -> 6.89 | L51: =K51+J51+H51 -> 14.880833 | M51: =(IF(F51>2,300+INT((F51-2)/0.5)*70,IF(AND(F51>0,F51<=2),300,0)))*G51 -> 6000 | N51: =G51*150 -> 3000 | O51: =G51*20 -> 400 | P51: =(H51*5900+I51*3400+J51*1200+K51*300)/G51 -> 686.2 | Q51: =VLOOKUP(G51,'【国内】常规用户招募-数据源 (OP)'!Z:AD,2,FALSE) -> 0.4 | R51: =VLOOKUP(G51,'【国内】常规用户招募-数据源 (OP)'!Z:AD,3,FALSE) -> 0 | S51: =VLOOKUP(G51,'【国内】常规用户招募-数据源 (OP)'!Z:AD,4,FALSE) -> 5.8083333 | T51: =VLOOKUP(G51,'【国内】常规用户招募-数据源 (OP)'!Z:AD,5,FALSE) -> 5.3 | U51: =P51/2 -> 343.1
A52: GT021 | B52: 常规用户 （普通游戏玩家，无身份/职业限制要求） | C52: 入户调研 （广/杭/沪以外地区） | D52: OP单独执行 | E52: 四级难度 | F52: ='①【国内】研究资源成本估算 (v1.0)'!$G$10 -> 2 | G52: ='①【国内】研究资源成本估算 (v1.0)'!$J$10 -> 20 | H52: =Q52*1.1 -> 0.726 | I52: =R52*1.2 -> 0 | J52: =S52*1.3 -> 7.5928667 | K52: =T52*1.3 -> 7.4412 | L52: =K52+J52+H52 -> 15.760067 | M52: =(IF(F52>2,300+INT((F52-2)/0.5)*70,IF(AND(F52>0,F52<=2),300,0)))*G52 -> 6000 | N52: =G52*150 -> 3000 | O52: =G52*20 -> 400 | P52: =(H52*5900+I52*3400+J52*1200+K52*300)/G52 -> 781.36 | Q52: =VLOOKUP(G52,'【国内】常规用户招募-数据源 (OP)'!AM:AQ,2,FALSE) -> 0.66 | R52: =VLOOKUP(G52,'【国内】常规用户招募-数据源 (OP)'!AM:AQ,3,FALSE) -> 0 | S52: =VLOOKUP(G52,'【国内】常规用户招募-数据源 (OP)'!AM:AQ,4,FALSE) -> 5.8406667 | T52: =VLOOKUP(G52,'【国内】常规用户招募-数据源 (OP)'!AM:AQ,5,FALSE) -> 5.724 | U52: =P52/2 -> 390.68
A53: GT022 | B53: 常规用户 （普通游戏玩家，无身份/职业限制要求） | C53: 入户调研 （广/杭/沪以外地区） | D53: OP单独执行 | E53: 五级难度 | F53: ='①【国内】研究资源成本估算 (v1.0)'!$G$10 -> 2 | G53: ='①【国内】研究资源成本估算 (v1.0)'!$J$10 -> 20 | H53: =Q53*1.1 -> 0.759 | I53: =R53*1.2 -> 0 | J53: =S53*1.3 -> 8.6808713 | K53: =T53*1.3 -> 7.738848 | L53: =K53+J53+H53 -> 17.178719 | M53: =(IF(F53>2,300+INT((F53-2)/0.5)*70,IF(AND(F53>0,F53<=2),300,0)))*G53 -> 6000 | N53: =G53*150 -> 3000 | O53: =G53*20 -> 400 | P53: =(H53*5900+I53*3400+J53*1200+K53*300)/G53 -> 860.84 | Q53: =VLOOKUP(G53,'【国内】常规用户招募-数据源 (OP)'!AZ:BD,2,FALSE) -> 0.69 | R53: =VLOOKUP(G53,'【国内】常规用户招募-数据源 (OP)'!AZ:BD,3,FALSE) -> 0 | S53: =VLOOKUP(G53,'【国内】常规用户招募-数据源 (OP)'!AZ:BD,4,FALSE) -> 6.6775933 | T53: =VLOOKUP(G53,'【国内】常规用户招募-数据源 (OP)'!AZ:BD,5,FALSE) -> 5.95296 | U53: =P53/2 -> 430.42
B54: 常规用户 （普通游戏玩家，无身份/职业限制要求） | C54: 入户调研 （广/杭/沪以外地区） | D54: P3单独执行 | E54: 一级难度 | F54: ='①【国内】研究资源成本估算 (v1.0)'!$G$10 -> 2 | G54: ='①【国内】研究资源成本估算 (v1.0)'!$J$10 -> 20 | H54: =Q54*1.1 -> 0.11 | I54: =R54*1.2 -> 2.4 | J54: =S54*1.3 -> 0 | K54: =T54*1.3 -> 2.86 | L54: =K54+J54+H54 -> 2.97 | M54: =(IF(F54>2,300+INT((F54-2)/0.5)*70,IF(AND(F54>0,F54<=2),300,0)))*G54 -> 6000 | N54: =G54*150 -> 3000 | O54: =G54*20 -> 400 | P54: =(H54*5900+I54*3400+J54*1200+K54*300)/G54 -> 483.35 | Q54: =VLOOKUP(G54,'【国内】常规用户招募-数据源 （正职）'!A:E,2,FALSE) -> 0.1 | R54: =VLOOKUP(G54,'【国内】常规用户招募-数据源 （正职）'!A:E,4,FALSE) -> 2 | S54: 0 | T54: =VLOOKUP(G54,'【国内】常规用户招募-数据源 （正职）'!A:E,5,FALSE) -> 2.2 | U54: =P54/2 -> 241.675
B55: 常规用户 （普通游戏玩家，无身份/职业限制要求） | C55: 入户调研 （广/杭/沪以外地区） | D55: P3单独执行 | E55: 二级难度 | F55: ='①【国内】研究资源成本估算 (v1.0)'!$G$10 -> 2 | G55: ='①【国内】研究资源成本估算 (v1.0)'!$J$10 -> 20 | H55: =Q55*1.1 -> 0.22 | I55: =R55*1.2 -> 2.52 | J55: =S55*1.3 -> 0 | K55: =T55*1.3 -> 3.25 | L55: =K55+J55+H55 -> 3.47 | M55: =(IF(F55>2,300+INT((F55-2)/0.5)*70,IF(AND(F55>0,F55<=2),300,0)))*G55 -> 6000 | N55: =G55*150 -> 3000 | O55: =G55*20 -> 400 | P55: =(H55*5900+I55*3400+J55*1200+K55*300)/G55 -> 542.05 | Q55: =VLOOKUP(G55,'【国内】常规用户招募-数据源 （正职）'!L:P,2,FALSE) -> 0.2 | R55: =VLOOKUP(G55,'【国内】常规用户招募-数据源 （正职）'!L:P,4,FALSE) -> 2.1 | S55: 0 | T55: =VLOOKUP(G55,'【国内】常规用户招募-数据源 （正职）'!L:P,5,FALSE) -> 2.5 | U55: =P55/2 -> 271.025
B56: 常规用户 （普通游戏玩家，无身份/职业限制要求） | C56: 入户调研 （广/杭/沪以外地区） | D56: P3单独执行 | E56: 三级难度 | F56: ='①【国内】研究资源成本估算 (v1.0)'!$G$10 -> 2 | G56: ='①【国内】研究资源成本估算 (v1.0)'!$J$10 -> 20 | H56: =Q56*1.1 -> 0.22 | I56: =R56*1.2 -> 3.12 | J56: =S56*1.3 -> 0 | K56: =T56*1.3 -> 3.9 | L56: =K56+J56+H56 -> 4.12 | M56: =(IF(F56>2,300+INT((F56-2)/0.5)*70,IF(AND(F56>0,F56<=2),300,0)))*G56 -> 6000 | N56: =G56*150 -> 3000 | O56: =G56*20 -> 400 | P56: =(H56*5900+I56*3400+J56*1200+K56*300)/G56 -> 653.8 | Q56: =VLOOKUP(G56,'【国内】常规用户招募-数据源 （正职）'!V:Z,2,FALSE) -> 0.2 | R56: =VLOOKUP(G56,'【国内】常规用户招募-数据源 （正职）'!V:Z,4,FALSE) -> 2.6 | S56: 0 | T56: =VLOOKUP(G56,'【国内】常规用户招募-数据源 （正职）'!V:Z,5,FALSE) -> 3 | U56: =P56/2 -> 326.9
B57: 常规用户 （普通游戏玩家，无身份/职业限制要求） | C57: 入户调研 （广/杭/沪以外地区） | D57: P3单独执行 | E57: 四级难度 | F57: ='①【国内】研究资源成本估算 (v1.0)'!$G$10 -> 2 | G57: ='①【国内】研究资源成本估算 (v1.0)'!$J$10 -> 20 | H57: =Q57*1.1 -> 0.33 | I57: =R57*1.2 -> 3.48 | J57: =S57*1.3 -> 0 | K57: =T57*1.3 -> 4.29 | L57: =K57+J57+H57 -> 4.62 | M57: =(IF(F57>2,300+INT((F57-2)/0.5)*70,IF(AND(F57>0,F57<=2),300,0)))*G57 -> 6000 | N57: =G57*150 -> 3000 | O57: =G57*20 -> 400 | P57: =(H57*5900+I57*3400+J57*1200+K57*300)/G57 -> 753.3 | Q57: =VLOOKUP(G57,'【国内】常规用户招募-数据源 （正职）'!AF:AJ,2,FALSE) -> 0.3 | R57: =VLOOKUP(G57,'【国内】常规用户招募-数据源 （正职）'!AF:AJ,4,FALSE) -> 2.9 | S57: 0 | T57: =VLOOKUP(G57,'【国内】常规用户招募-数据源 （正职）'!AF:AJ,5,FALSE) -> 3.3 | U57: =P57/2 -> 376.65
B58: 常规用户 （普通游戏玩家，无身份/职业限制要求） | C58: 入户调研 （广/杭/沪以外地区） | D58: P3单独执行 | E58: 五级难度 | F58: ='①【国内】研究资源成本估算 (v1.0)'!$G$10 -> 2 | G58: ='①【国内】研究资源成本估算 (v1.0)'!$J$10 -> 20 | H58: =Q58*1.1 -> 0.33 | I58: =R58*1.2 -> 3.9 | J58: =S58*1.3 -> 0 | K58: =T58*1.3 -> 4.55 | L58: =K58+J58+H58 -> 4.88 | M58: =(IF(F58>2,300+INT((F58-2)/0.5)*70,IF(AND(F58>0,F58<=2),300,0)))*G58 -> 6000 | N58: =G58*150 -> 3000 | O58: =G58*20 -> 400 | P58: =(H58*5900+I58*3400+J58*1200+K58*300)/G58 -> 828.6 | Q58: =VLOOKUP(G58,'【国内】常规用户招募-数据源 （正职）'!AP:AT,2,FALSE) -> 0.3 | R58: =VLOOKUP(G58,'【国内】常规用户招募-数据源 （正职）'!AP:AT,4,FALSE) -> 3.25 | S58: 0 | T58: =VLOOKUP(G58,'【国内】常规用户招募-数据源 （正职）'!AP:AT,5,FALSE) -> 3.5 | U58: =P58/2 -> 414.3
B59: 常规用户 （普通游戏玩家，无身份/职业限制要求） | C59: 入户调研 （广/杭/沪以外地区） | D59: 混合执行 | E59: 一级难度 | F59: ='①【国内】研究资源成本估算 (v1.0)'!$G$10 -> 2 | G59: ='①【国内】研究资源成本估算 (v1.0)'!$J$10 -> 20 | H59: =Q59*1.1 -> 0.143 | I59: =R59*1.2 -> 1.44 | J59: =S59*1.3 -> 2.7549167 | K59: =T59*1.3 -> 2.86 | L59: =H59+I59+J59+K59 -> 7.1979167 | M59: =(IF(F59>2,300+INT((F59-2)/0.5)*70,IF(AND(F59>0,F59<=2),300,0)))*G59 -> 6000 | N59: =G59*150 -> 3000 | P59: =(H59*5900+I59*3400+J59*1200+K59*300)/G59 -> 495.18 | Q59: =VLOOKUP(G59,'【国内】常规用户招募-数据源(正职+OP混合执行）'!A:E,2,FALSE) -> 0.13 | R59: =VLOOKUP(G59,'【国内】常规用户招募-数据源(正职+OP混合执行）'!A:E,3,FALSE) -> 1.2 | S59: =VLOOKUP(G59,'【国内】常规用户招募-数据源(正职+OP混合执行）'!A:E,4,FALSE) -> 2.1191667 | T59: =VLOOKUP(G59,'【国内】常规用户招募-数据源(正职+OP混合执行）'!A:E,5,FALSE) -> 2.2 | U59: =P59/2 -> 247.59
B60: 常规用户 （普通游戏玩家，无身份/职业限制要求） | C60: 入户调研 （广/杭/沪以外地区） | D60: 混合执行 | E60: 二级难度 | F60: ='①【国内】研究资源成本估算 (v1.0)'!$G$10 -> 2 | G60: ='①【国内】研究资源成本估算 (v1.0)'!$J$10 -> 20 | H60: =Q60*1.1 -> 0.286 | I60: =R60*1.2 -> 1.512 | J60: =S60*1.3 -> 2.72675 | K60: =T60*1.3 -> 3.185 | L60: =H60+I60+J60+K60 -> 7.70975 | M60: =(IF(F60>2,300+INT((F60-2)/0.5)*70,IF(AND(F60>0,F60<=2),300,0)))*G60 -> 6000 | N60: =G60*150 -> 3000 | P60: =(H60*5900+I60*3400+J60*1200+K60*300)/G60 -> 552.79 | Q60: =VLOOKUP(G60,'【国内】常规用户招募-数据源(正职+OP混合执行）'!N:R,2,FALSE) -> 0.26 | R60: =VLOOKUP(G60,'【国内】常规用户招募-数据源(正职+OP混合执行）'!N:R,3,FALSE) -> 1.26 | S60: =VLOOKUP(G60,'【国内】常规用户招募-数据源(正职+OP混合执行）'!N:R,4,FALSE) -> 2.0975 | T60: =VLOOKUP(G60,'【国内】常规用户招募-数据源(正职+OP混合执行）'!N:R,5,FALSE) -> 2.45 | U60: =P60/2 -> 276.395
B61: 常规用户 （普通游戏玩家，无身份/职业限制要求） | C61: 入户调研 （广/杭/沪以外地区） | D61: 混合执行 | E61: 三级难度 | F61: ='①【国内】研究资源成本估算 (v1.0)'!$G$10 -> 2 | G61: ='①【国内】研究资源成本估算 (v1.0)'!$J$10 -> 20 | H61: =Q61*1.1 -> 0.286 | I61: =R61*1.2 -> 1.872 | J61: =S61*1.3 -> 3.2521667 | K61: =T61*1.3 -> 4.68 | L61: =H61+I61+J61+K61 -> 10.090167 | M61: =(IF(F61>2,300+INT((F61-2)/0.5)*70,IF(AND(F61>0,F61<=2),300,0)))*G61 -> 6000 | N61: =G61*150 -> 3000 | P61: =(H61*5900+I61*3400+J61*1200+K61*300)/G61 -> 667.94 | Q61: =VLOOKUP(G61,'【国内】常规用户招募-数据源(正职+OP混合执行）'!Z:AD,2,FALSE) -> 0.26 | R61: =VLOOKUP(G61,'【国内】常规用户招募-数据源(正职+OP混合执行）'!Z:AD,3,FALSE) -> 1.56 | S61: =VLOOKUP(G61,'【国内】常规用户招募-数据源(正职+OP混合执行）'!Z:AD,4,FALSE) -> 2.5016667 | T61: =VLOOKUP(G61,'【国内】常规用户招募-数据源(正职+OP混合执行）'!Z:AD,5,FALSE) -> 3.6 | U61: =P61/2 -> 333.97
B62: 常规用户 （普通游戏玩家，无身份/职业限制要求） | C62: 入户调研 （广/杭/沪以外地区） | D62: 混合执行 | E62: 四级难度 | F62: ='①【国内】研究资源成本估算 (v1.0)'!$G$10 -> 2 | G62: ='①【国内】研究资源成本估算 (v1.0)'!$J$10 -> 20 | H62: =Q62*1.1 -> 0.429 | I62: =R62*1.2 -> 2.088 | J62: =S62*1.3 -> 3.6116167 | K62: =T62*1.3 -> 4.6332 | L62: =H62+I62+J62+K62 -> 10.761817 | M62: =(IF(F62>2,300+INT((F62-2)/0.5)*70,IF(AND(F62>0,F62<=2),300,0)))*G62 -> 6000 | N62: =G62*150 -> 3000 | P62: =(H62*5900+I62*3400+J62*1200+K62*300)/G62 -> 767.71 | Q62: =VLOOKUP(G62,'【国内】常规用户招募-数据源(正职+OP混合执行）'!AL:AP,2,FALSE) -> 0.39 | R62: =VLOOKUP(G62,'【国内】常规用户招募-数据源(正职+OP混合执行）'!AL:AP,3,FALSE) -> 1.74 | S62: =VLOOKUP(G62,'【国内】常规用户招募-数据源(正职+OP混合执行）'!AL:AP,4,FALSE) -> 2.7781667 | T62: =VLOOKUP(G62,'【国内】常规用户招募-数据源(正职+OP混合执行）'!AL:AP,5,FALSE) -> 3.564 | U62: =P62/2 -> 383.855
B63: 常规用户 （普通游戏玩家，无身份/职业限制要求） | C63: 入户调研 （广/杭/沪以外地区） | D63: 混合执行 | E63: 五级难度 | F63: ='①【国内】研究资源成本估算 (v1.0)'!$G$10 -> 2 | G63: ='①【国内】研究资源成本估算 (v1.0)'!$J$10 -> 20 | H63: =Q63*1.1 -> 0.429 | I63: =R63*1.2 -> 2.34 | J63: =S63*1.3 -> 4.2780833 | K63: =T63*1.3 -> 4.29 | L63: =H63+I63+J63+K63 -> 11.337083 | M63: =(IF(F63>2,300+INT((F63-2)/0.5)*70,IF(AND(F63>0,F63<=2),300,0)))*G63 -> 6000 | N63: =G63*150 -> 3000 | P63: =(H63*5900+I63*3400+J63*1200+K63*300)/G63 -> 845.39 | Q63: =VLOOKUP($G63,'【国内】常规用户招募-数据源(正职+OP混合执行）'!AX:BB,2,FALSE) -> 0.39 | R63: =VLOOKUP(G63,'【国内】常规用户招募-数据源(正职+OP混合执行）'!AX:BB,3,FALSE) -> 1.95 | S63: =VLOOKUP(G63,'【国内】常规用户招募-数据源(正职+OP混合执行）'!AX:BB,4,FALSE) -> 3.2908333 | T63: =VLOOKUP($G63,'【国内】常规用户招募-数据源(正职+OP混合执行）'!AX:BB,5,FALSE) -> 3.3 | U63: =P63/2 -> 422.695
A64: GT024 | B64: 常规用户 （普通游戏玩家，无身份/职业限制要求） | C64: 线上深访/测试 （不限城市） | D64: OP单独执行 | E64: 一级难度 | F64: ='①【国内】研究资源成本估算 (v1.0)'!$G$11 -> 1.5 | G64: ='①【国内】研究资源成本估算 (v1.0)'!$J$11 -> 30 | H64: =Q64*0.8 -> 0.42 | I64: =R64*0.8 -> 0 | J64: =S64*0.8 -> 4.595 | K64: =T64*0.8 -> 5.28 | L64: =K64+J64+H64 -> 10.295 | M64: =IF(AND(F64>0,F64<=1),80,IF(F64>1,80+INT((F64-1)/0.5)*40,0))*G64 -> 3600 | N64: =G64*50 -> 1500 | O64: =G64*20 -> 600 | P64: =(H64*5900+I64*3400+J64*1200+K64*300)/G64 -> 319.2 | Q64: =VLOOKUP(G64,'【国内】常规用户招募-数据源 (OP)'!A:E,2,FALSE) -> 0.525 | R64: =VLOOKUP(G64,'【国内】常规用户招募-数据源 (OP)'!A:E,3,FALSE) -> 0 | S64: =VLOOKUP(G64,'【国内】常规用户招募-数据源 (OP)'!A:E,4,FALSE) -> 5.74375 | T64: =VLOOKUP(G64,'【国内】常规用户招募-数据源 (OP)'!A:E,5,FALSE) -> 6.6 | U64: =P64/2 -> 159.6
A65: GT025 | B65: 常规用户 （普通游戏玩家，无身份/职业限制要求） | C65: 线上深访/测试 （不限城市） | D65: OP单独执行 | E65: 二级难度 | F65: ='①【国内】研究资源成本估算 (v1.0)'!$G$11 -> 1.5 | G65: ='①【国内】研究资源成本估算 (v1.0)'!$J$11 -> 30 | H65: =Q65*0.8 -> 0.432 | I65: =R65*0.8 -> 0 | J65: =S65*0.8 -> 4.8092933 | K65: =T65*0.8 -> 6.32016 | L65: =K65+J65+H65 -> 11.561453 | M65: =IF(AND(F65>0,F65<=1),80,IF(F65>1,80+INT((F65-1)/0.5)*40,0))*G65 -> 3600 | N65: =G65*50 -> 1500 | O65: =G65*20 -> 600 | P65: =(H65*5900+I65*3400+J65*1200+K65*300)/G65 -> 340.53333 | Q65: =VLOOKUP(G65,'【国内】常规用户招募-数据源 (OP)'!N:R,2,FALSE) -> 0.54 | R65: =VLOOKUP(G65,'【国内】常规用户招募-数据源 (OP)'!N:R,3,FALSE) -> 0 | S65: =VLOOKUP(G65,'【国内】常规用户招募-数据源 (OP)'!N:R,4,FALSE) -> 6.0116167 | T65: =VLOOKUP(G65,'【国内】常规用户招募-数据源 (OP)'!N:R,5,FALSE) -> 7.9002 | U65: =P65/2 -> 170.26667
A66: GT026 | B66: 常规用户 （普通游戏玩家，无身份/职业限制要求） | C66: 线上深访/测试 （不限城市） | D66: OP单独执行 | E66: 三级难度 | F66: ='①【国内】研究资源成本估算 (v1.0)'!$G$11 -> 1.5 | G66: ='①【国内】研究资源成本估算 (v1.0)'!$J$11 -> 30 | H66: =Q66*0.8 -> 0.64 | I66: =R66*0.8 -> 0 | J66: =S66*0.8 -> 6.7333333 | K66: =T66*0.8 -> 6.4 | L66: =K66+J66+H66 -> 13.773333 | M66: =IF(AND(F66>0,F66<=1),80,IF(F66>1,80+INT((F66-1)/0.5)*40,0))*G66 -> 3600 | N66: =G66*50 -> 1500 | O66: =G66*20 -> 600 | P66: =(H66*5900+I66*3400+J66*1200+K66*300)/G66 -> 459.2 | Q66: =VLOOKUP(G66,'【国内】常规用户招募-数据源 (OP)'!Z:AD,2,FALSE) -> 0.8 | R66: =VLOOKUP(G66,'【国内】常规用户招募-数据源 (OP)'!Z:AD,3,FALSE) -> 0 | S66: =VLOOKUP(G66,'【国内】常规用户招募-数据源 (OP)'!Z:AD,4,FALSE) -> 8.4166667 | T66: =VLOOKUP(G66,'【国内】常规用户招募-数据源 (OP)'!Z:AD,5,FALSE) -> 8 | U66: =P66/2 -> 229.6
A67: GT027 | B67: 常规用户 （普通游戏玩家，无身份/职业限制要求） | C67: 线上深访/测试 （不限城市） | D67: OP单独执行 | E67: 四级难度 | F67: ='①【国内】研究资源成本估算 (v1.0)'!$G$11 -> 1.5 | G67: ='①【国内】研究资源成本估算 (v1.0)'!$J$11 -> 30 | H67: =Q67*0.8 -> 0.88 | I67: =R67*0.8 -> 0 | J67: =S67*0.8 -> 6.5786667 | K67: =T67*0.8 -> 6.912 | L67: =K67+J67+H67 -> 14.370667 | M67: =IF(AND(F67>0,F67<=1),80,IF(F67>1,80+INT((F67-1)/0.5)*40,0))*G67 -> 3600 | N67: =G67*50 -> 1500 | O67: =G67*20 -> 600 | P67: =(H67*5900+I67*3400+J67*1200+K67*300)/G67 -> 505.33333 | Q67: =VLOOKUP(G67,'【国内】常规用户招募-数据源 (OP)'!AM:AQ,2,FALSE) -> 1.1 | R67: =VLOOKUP(G67,'【国内】常规用户招募-数据源 (OP)'!AM:AQ,3,FALSE) -> 0 | S67: =VLOOKUP(G67,'【国内】常规用户招募-数据源 (OP)'!AM:AQ,4,FALSE) -> 8.2233333 | T67: =VLOOKUP(G67,'【国内】常规用户招募-数据源 (OP)'!AM:AQ,5,FALSE) -> 8.64 | U67: =P67/2 -> 252.66667
A68: GT028 | B68: 常规用户 （普通游戏玩家，无身份/职业限制要求） | C68: 线上深访/测试 （不限城市） | D68: OP单独执行 | E68: 五级难度 | F68: ='①【国内】研究资源成本估算 (v1.0)'!$G$11 -> 1.5 | G68: ='①【国内】研究资源成本估算 (v1.0)'!$J$11 -> 30 | H68: =Q68*0.8 -> 0.92 | I68: =R68*0.8 -> 0 | J68: =S68*0.8 -> 7.8995467 | K68: =T68*0.8 -> 7.18848 | L68: =K68+J68+H68 -> 16.008027 | M68: =IF(AND(F68>0,F68<=1),80,IF(F68>1,80+INT((F68-1)/0.5)*40,0))*G68 -> 3600 | N68: =G68*60 -> 1800 | O68: =G68*20 -> 600 | P68: =(H68*5900+I68*3400+J68*1200+K68*300)/G68 -> 568.8 | Q68: =VLOOKUP(G68,'【国内】常规用户招募-数据源 (OP)'!AZ:BD,2,FALSE) -> 1.15 | R68: =VLOOKUP(G68,'【国内】常规用户招募-数据源 (OP)'!AZ:BD,3,FALSE) -> 0 | S68: =VLOOKUP(G68,'【国内】常规用户招募-数据源 (OP)'!AZ:BD,4,FALSE) -> 9.8744333 | T68: =VLOOKUP(G68,'【国内】常规用户招募-数据源 (OP)'!AZ:BD,5,FALSE) -> 8.9856 | U68: =P68/2 -> 284.4
B69: 常规用户 （普通游戏玩家，无身份/职业限制要求） | C69: 线上深访/测试 （不限城市） | D69: P3单独执行 | E69: 一级难度 | F69: ='①【国内】研究资源成本估算 (v1.0)'!$G$11 -> 1.5 | G69: ='①【国内】研究资源成本估算 (v1.0)'!$J$11 -> 30 | H69: =Q69*0.8 -> 0.24 | I69: =R69*0.8 -> 2.16 | J69: =S69*0.8 -> 0 | K69: =T69*0.8 -> 2.72 | L69: =K69+J69+H69 -> 2.96 | M69: =IF(AND(F69>0,F69<=1),80,IF(F69>1,80+INT((F69-1)/0.5)*40,0))*G69 -> 3600 | N69: =G69*60 -> 1800 | O69: =G69*20 -> 600 | P69: =(H69*5900+I69*3400+J69*1200+K69*300)/G69 -> 319.2 | Q69: =VLOOKUP(G69,'【国内】常规用户招募-数据源 （正职）'!A:E,2,FALSE) -> 0.3 | R69: =VLOOKUP(G69,'【国内】常规用户招募-数据源 （正职）'!A:E,4,FALSE) -> 2.7 | S69: 0 | T69: =VLOOKUP(G69,'【国内】常规用户招募-数据源 （正职）'!A:E,5,FALSE) -> 3.4 | U69: =P69/2 -> 159.6
B70: 常规用户 （普通游戏玩家，无身份/职业限制要求） | C70: 线上深访/测试 （不限城市） | D70: P3单独执行 | E70: 二级难度 | F70: ='①【国内】研究资源成本估算 (v1.0)'!$G$11 -> 1.5 | G70: ='①【国内】研究资源成本估算 (v1.0)'!$J$11 -> 30 | H70: =Q70*0.8 -> 0.24 | I70: =R70*0.8 -> 2.32 | J70: =S70*0.8 -> 0 | K70: =T70*0.8 -> 3.04 | L70: =K70+J70+H70 -> 3.28 | M70: =IF(AND(F70>0,F70<=1),80,IF(F70>1,80+INT((F70-1)/0.5)*40,0))*G70 -> 3600 | N70: =G70*60 -> 1800 | O70: =G70*20 -> 600 | P70: =(H70*5900+I70*3400+J70*1200+K70*300)/G70 -> 340.53333 | Q70: =VLOOKUP(G70,'【国内】常规用户招募-数据源 （正职）'!L:P,2,FALSE) -> 0.3 | R70: =VLOOKUP(G70,'【国内】常规用户招募-数据源 （正职）'!L:P,4,FALSE) -> 2.9 | S70: 0 | T70: =VLOOKUP(G70,'【国内】常规用户招募-数据源 （正职）'!L:P,5,FALSE) -> 3.8 | U70: =P70/2 -> 170.26667
B71: 常规用户 （普通游戏玩家，无身份/职业限制要求） | C71: 线上深访/测试 （不限城市） | D71: P3单独执行 | E71: 三级难度 | F71: ='①【国内】研究资源成本估算 (v1.0)'!$G$11 -> 1.5 | G71: ='①【国内】研究资源成本估算 (v1.0)'!$J$11 -> 30 | H71: =Q71*0.8 -> 0.32 | I71: =R71*0.8 -> 3.2 | J71: =S71*0.8 -> 0 | K71: =T71*0.8 -> 3.36 | L71: =K71+J71+H71 -> 3.68 | M71: =IF(AND(F71>0,F71<=1),80,IF(F71>1,80+INT((F71-1)/0.5)*40,0))*G71 -> 3600 | N71: =G71*60 -> 1800 | O71: =G71*20 -> 600 | P71: =(H71*5900+I71*3400+J71*1200+K71*300)/G71 -> 459.2 | Q71: =VLOOKUP(G71,'【国内】常规用户招募-数据源 （正职）'!V:Z,2,FALSE) -> 0.4 | R71: =VLOOKUP(G71,'【国内】常规用户招募-数据源 （正职）'!V:Z,4,FALSE) -> 4 | S71: 0 | T71: =VLOOKUP(G71,'【国内】常规用户招募-数据源 （正职）'!V:Z,5,FALSE) -> 4.2 | U71: =P71/2 -> 229.6
B72: 常规用户 （普通游戏玩家，无身份/职业限制要求） | C72: 线上深访/测试 （不限城市） | D72: P3单独执行 | E72: 四级难度 | F72: ='①【国内】研究资源成本估算 (v1.0)'!$G$11 -> 1.5 | G72: ='①【国内】研究资源成本估算 (v1.0)'!$J$11 -> 30 | H72: =Q72*0.8 -> 0.4 | I72: =R72*0.8 -> 3.44 | J72: =S72*0.8 -> 0 | K72: =T72*0.8 -> 3.68 | L72: =K72+J72+H72 -> 4.08 | M72: =IF(AND(F72>0,F72<=1),80,IF(F72>1,80+INT((F72-1)/0.5)*40,0))*G72 -> 3600 | N72: =G72*60 -> 1800 | O72: =G72*20 -> 600 | P72: =(H72*5900+I72*3400+J72*1200+K72*300)/G72 -> 505.33333 | Q72: =VLOOKUP(G72,'【国内】常规用户招募-数据源 （正职）'!AF:AJ,2,FALSE) -> 0.5 | R72: =VLOOKUP(G72,'【国内】常规用户招募-数据源 （正职）'!AF:AJ,4,FALSE) -> 4.3 | S72: 0 | T72: =VLOOKUP(G72,'【国内】常规用户招募-数据源 （正职）'!AF:AJ,5,FALSE) -> 4.6 | U72: =P72/2 -> 252.66667
